Workbook

Sheet Configuração
B3: Configuração de custos
B5: Atributos sobre a forma de trabalho do cliente | C5: Config | E5: % Base | F5: $ Incremento
B6: Fornece máquina | D6: VERDADEIRO | E6: 3 | F6: =IF(D6=FALSE, E6%,0%) -> 0
B7: Fornece monitor adicional | D7: VERDADEIRO | E7: 0 | F7: =IF(D7=FALSE, E7%,0%) -> 0
B8: Fornece licenças necessárias | D8: VERDADEIRO | E8: 3 | F8: =IF(D8=FALSE, E8%,0%) -> 0
B9: Horas abertas | D9: TRUE | E9: 0.5 | F9: =IF(D9=FALSE, E9%,0%) -> 0
B10: Modo de trabalho | C10: Full Home | D10: =C10 -> Full Home | E10: 1 | F10: =IF(D10="Presencial",E10%, IF(D10="Híbrido",(E10/2)%, 0%)) -> 0
B11: Aceita colaboradores de outros estados | D11: TRUE | E11: 1 | F11: =IF(D11=FALSE, E11%,0%) -> 0
B12: Risco de atraso | C12: Baixo | D12: =C12 -> Baixo | E12: 3 | F12: =IF(D12="Alto",E12%, IF(D12="Médio",(E12/2)%, 0%)) -> 0
F13: =SUM(F6:F12) -> 0

Sheet Célula Base
E2: RESUMO | F2: Base horas mês | G2: 168 | H2: $ salários + encargos | I2: =SUM(I9:I33) -> #N/A | J2: FGTS | K2: 0.08 | L2: Nº colab bilable | M2: =COUNTIF(E9:E494, "Sim") -> 5 | N2: Valor convênio | O2: 400
F3: % Comissão vend. | G3: 0 | H3: $ faturamento | I3: =SUM(Q9:Q33) -> #N/A | J3: FGTS Multa | K3: 0.4 | L3: Nº colab no bilable | M3: =COUNTIF(E9:E494, "Não") -> 1 | N3: Valor comissão | O3: =SUM(P9:P33) -> #N/A
F4: % Imposto NF | G4: 0.1953 | H4: $ Custos | I4: =SUM(J9:J494)+SUM(M9:M494)+O3 -> #N/A | J4: INSS | K4: 0.09 | L4: % Rateio no Bilable | M4: =M6/M5 -> #N/A
G5: 1 | H5: $ lucratividade | I5: =I3-I4 -> #N/A | J5: Ticket Rest. Dia | K5: 30 | L5: Total Billable | M5: =SUMIF(E9:E33,"Sim",O9:O33) -> #N/A
F6: Taxa de risco | G6: =Configuração!F13 -> 0 | H6: % lucro real | I6: =I5/I3 -> #N/A | J6: Tarifa média hr. | K6: =SUM(Q9:Q33)/SUM(D9:D33) -> #N/A | L6: Total No Bilable | M6: =SUMIF(E9:E33,"Não",O9:O33) -> #N/A
B7: CONFIGURAÇÃO EQUIPE | C7: CONFIG RECURSO | F7: C U S T O S C O M C O L A B O R A D O R E S | K7: T A R I F A / F A T U R A M E N T O | S7: C U S T O S C L T | AC7: IMPOSTOS | AD7: LUCRATIVIDADE
B8: Necessidade cliente | C8: Reg | D8: H.trab | E8: Billable | F8: $ Negociado/salário | G8: $ salário cheio | H8: $ Salário real | I8: $ Custo Colab | J8: $ Custo colab + Imp | K8: $ Tarifa negociada | L8: Markup | M8: $ Risco | N8: $ Tar. cheia | O8: $ Tar. calculada | P8: $ Comissão | Q8: $ Tarifa bilable | R8: Valor hora | S8: FGTS | T8: FGTS multa | U8: Férias | V8: 1/3 férias | W8: 13º salário | X8: Aviso Remuner | Y8: Vl. Restaurante | Z8: INSS | AA8: Convênio | AB8: $ Total Encargos | AC8: Imposto Nota | AD8: $ lucro | AE8: % Lucro
B9: Gerente T.I. Gestão | C9: PJ | D9: 20 | E9: Não | F9: 0 | G9: =IF(F9>0,F9, IF(B9<>"", IF(C9="CLT",VLOOKUP(B9,'Lista Profissionais'!$C$11:$H$348,3,0), VLOOKUP(B9,'Lista Profissionais'!$C$11:$H$348,4,0)), 0)) -> #N/A | H9: =(G9/$G$2)*D9 -> #N/A | I9: =H9+AB9 -> #N/A | J9: =I9+AC9 -> #N/A | K9: 0 | L9: 0 | M9: =I9*$G$6 -> #N/A | N9: =IF(K9>0,K9, IF(L9>0,(G9*(1+L9)+M9), (G9*(1+$G$5)+M9))) -> #N/A | O9: =(N9/$G$2)*D9 -> #N/A | P9: =IF(E9="Sim", O9*$G$3,0) -> 0 | Q9: =IF(E9="Não",0, O9+(O9*$M$4)+P9 ) -> 0 | R9: =Q9/$G$2 -> 0 | S9: =IF(C9="CLT", H9*$K$2, 0) -> 0 | T9: =IF(C9="CLT", S9*$K$3, 0) -> 0 | U9: =IF(C9="CLT", H9/12, 0) -> 0 | V9: =IF(C9="CLT", U9/3, 0) -> 0 | W9: =IF(C9="CLT", H9/12, 0) -> 0 | X9: =IF(C9="CLT", H9/12, 0) -> 0 | Y9: =IF(B9<>"", IF(C9="CLT", 22*$K$5,0),0) -> 0 | Z9: =IF(C9="CLT", H9*$K$4, 0) -> 0 | AA9: =IF(B9<>"", IF(C9="CLT", $O$2, 0),0) -> 0 | AB9: =SUM(S9:AA9) -> 0 | AC9: =IF(E9="Sim", Q9*$G$4, 0) -> 0 | AD9: =Q9-AC9-I9-M9-P9 -> #N/A | AE9: =(IF(AD9>0,AD9/Q9,0)) -> #N/A
B10: Coordenador de Qualidade de Software Gestão | C10: PJ | D10: 168 | E10: Sim | F10: 0 | G10: =IF(F10>0,F10, IF(B10<>"", IF(C10="CLT",VLOOKUP(B10,'Lista Profissionais'!$C$11:$H$348,3,0), VLOOKUP(B10,'Lista Profissionais'!$C$11:$H$348,4,0)), 0)) -> #N/A | H10: =(G10/$G$2)*D10 -> #N/A | I10: =H10+AB10 -> #N/A | J10: =I10+AC10 -> #N/A | K10: 0 | L10: 0 | M10: =I10*$G$6 -> #N/A | N10: =IF(K10>0,K10, IF(L10>0,(G10*(1+L10)+M10), (G10*(1+$G$5)+M10))) -> #N/A | O10: =(N10/$G$2)*D10 -> #N/A | P10: =IF(E10="Sim", O10*$G$3,0) -> #N/A | Q10: =IF(E10="Não",0, O10+(O10*$M$4)+P10 ) -> #N/A | R10: =Q10/$G$2 -> #N/A | S10: =IF(C10="CLT", H10*$K$2, 0) -> 0 | T10: =IF(C10="CLT", S10*$K$3, 0) -> 0 | U10: =IF(C10="CLT", H10/12, 0) -> 0 | V10: =IF(C10="CLT", U10/3, 0) -> 0 | W10: =IF(C10="CLT", H10/12, 0) -> 0 | X10: =IF(C10="CLT", H10/12, 0) -> 0 | Y10: =IF(B10<>"", IF(C10="CLT", 22*$K$5,0),0) -> 0 | Z10: =IF(C10="CLT", H10*$K$4, 0) -> 0 | AA10: =IF(B10<>"", IF(C10="CLT", $O$2, 0),0) -> 0 | AB10: =SUM(S10:AA10) -> 0 | AC10: =IF(E10="Sim", Q10*$G$4, 0) -> #N/A | AD10: =Q10-AC10-I10-M10-P10 -> #N/A | AE10: =(IF(AD10>0,AD10/Q10,"")) -> #N/A
B11: Analista Q.A. Sênior | C11: PJ | D11: 168 | E11: Sim | F11: 0 | G11: =IF(F11>0,F11, IF(B11<>"", IF(C11="CLT",VLOOKUP(B11,'Lista Profissionais'!$C$11:$H$348,3,0), VLOOKUP(B11,'Lista Profissionais'!$C$11:$H$348,4,0)), 0)) -> #N/A | H11: =(G11/$G$2)*D11 -> #N/A | I11: =H11+AB11 -> #N/A | J11: =I11+AC11 -> #N/A | K11: 0 | L11: 0 | M11: =I11*$G$6 -> #N/A | N11: =IF(K11>0,K11, IF(L11>0,(G11*(1+L11)+M11), (G11*(1+$G$5)+M11))) -> #N/A | O11: =(N11/$G$2)*D11 -> #N/A | P11: =IF(E11="Sim", O11*$G$3,0) -> #N/A | Q11: =IF(E11="Não",0, O11+(O11*$M$4)+P11 ) -> #N/A | R11: =Q11/$G$2 -> #N/A | S11: =IF(C11="CLT", H11*$K$2, 0) -> 0 | T11: =IF(C11="CLT", S11*$K$3, 0) -> 0 | U11: =IF(C11="CLT", H11/12, 0) -> 0 | V11: =IF(C11="CLT", U11/3, 0) -> 0 | W11: =IF(C11="CLT", H11/12, 0) -> 0 | X11: =IF(C11="CLT", H11/12, 0) -> 0 | Y11: =IF(B11<>"", IF(C11="CLT", 22*$K$5,0),0) -> 0 | Z11: =IF(C11="CLT", H11*$K$4, 0) -> 0 | AA11: =IF(B11<>"", IF(C11="CLT", $O$2, 0),0) -> 0 | AB11: =SUM(S11:AA11) -> 0 | AC11: =IF(E11="Sim", Q11*$G$4, 0) -> #N/A | AD11: =Q11-AC11-I11-M11-P11 -> #N/A | AE11: =(IF(AD11>0,AD11/Q11,"")) -> #N/A
B12: Analista Q.A. Pleno | C12: PJ | D12: 168 | E12: Sim | F12: 0 | G12: =IF(F12>0,F12, IF(B12<>"", IF(C12="CLT",VLOOKUP(B12,'Lista Profissionais'!$C$11:$H$348,3,0), VLOOKUP(B12,'Lista Profissionais'!$C$11:$H$348,4,0)), 0)) -> #N/A | H12: =(G12/$G$2)*D12 -> #N/A | I12: =H12+AB12 -> #N/A | J12: =I12+AC12 -> #N/A | K12: 0 | L12: 0 | M12: =I12*$G$6 -> #N/A | N12: =IF(K12>0,K12, IF(L12>0,(G12*(1+L12)+M12), (G12*(1+$G$5)+M12))) -> #N/A | O12: =(N12/$G$2)*D12 -> #N/A | P12: =IF(E12="Sim", O12*$G$3,0) -> #N/A | Q12: =IF(E12="Não",0, O12+(O12*$M$4)+P12 ) -> #N/A | R12: =Q12/$G$2 -> #N/A | S12: =IF(C12="CLT", H12*$K$2, 0) -> 0 | T12: =IF(C12="CLT", S12*$K$3, 0) -> 0 | U12: =IF(C12="CLT", H12/12, 0) -> 0 | V12: =IF(C12="CLT", U12/3, 0) -> 0 | W12: =IF(C12="CLT", H12/12, 0) -> 0 | X12: =IF(C12="CLT", H12/12, 0) -> 0 | Y12: =IF(B12<>"", IF(C12="CLT", 22*$K$5,0),0) -> 0 | Z12: =IF(C12="CLT", H12*$K$4, 0) -> 0 | AA12: =IF(B12<>"", IF(C12="CLT", $O$2, 0),0) -> 0 | AB12: =SUM(S12:AA12) -> 0 | AC12: =IF(E12="Sim", Q12*$G$4, 0) -> #N/A | AD12: =Q12-AC12-I12-M12-P12 -> #N/A | AE12: =(IF(AD12>0,AD12/Q12,"")) -> #N/A
B13: Analista Q.A. Júnior | C13: PJ | D13: 168 | E13: Sim | F13: 0 | G13: =IF(F13>0,F13, IF(B13<>"", IF(C13="CLT",VLOOKUP(B13,'Lista Profissionais'!$C$11:$H$348,3,0), VLOOKUP(B13,'Lista Profissionais'!$C$11:$H$348,4,0)), 0)) -> #N/A | H13: =(G13/$G$2)*D13 -> #N/A | I13: =H13+AB13 -> #N/A | J13: =I13+AC13 -> #N/A | K13: 0 | L13: 0 | M13: =I13*$G$6 -> #N/A | N13: =IF(K13>0,K13, IF(L13>0,(G13*(1+L13)+M13), (G13*(1+$G$5)+M13))) -> #N/A | O13: =(N13/$G$2)*D13 -> #N/A | P13: =IF(E13="Sim", O13*$G$3,0) -> #N/A | Q13: =IF(E13="Não",0, O13+(O13*$M$4)+P13 ) -> #N/A | R13: =Q13/$G$2 -> #N/A | S13: =IF(C13="CLT", H13*$K$2, 0) -> 0 | T13: =IF(C13="CLT", S13*$K$3, 0) -> 0 | U13: =IF(C13="CLT", H13/12, 0) -> 0 | V13: =IF(C13="CLT", U13/3, 0) -> 0 | W13: =IF(C13="CLT", H13/12, 0) -> 0 | X13: =IF(C13="CLT", H13/12, 0) -> 0 | Y13: =IF(B13<>"", IF(C13="CLT", 22*$K$5,0),0) -> 0 | Z13: =IF(C13="CLT", H13*$K$4, 0) -> 0 | AA13: =IF(B13<>"", IF(C13="CLT", $O$2, 0),0) -> 0 | AB13: =SUM(S13:AA13) -> 0 | AC13: =IF(E13="Sim", Q13*$G$4, 0) -> #N/A | AD13: =Q13-AC13-I13-M13-P13 -> #N/A | AE13: =(IF(AD13>0,AD13/Q13,"")) -> #N/A
B14: Analista Q.A. Júnior | C14: PJ | D14: 168 | E14: Sim | F14: 0 | G14: =IF(F14>0,F14, IF(B14<>"", IF(C14="CLT",VLOOKUP(B14,'Lista Profissionais'!$C$11:$H$348,3,0), VLOOKUP(B14,'Lista Profissionais'!$C$11:$H$348,4,0)), 0)) -> #N/A | H14: =(G14/$G$2)*D14 -> #N/A | I14: =H14+AB14 -> #N/A | J14: =I14+AC14 -> #N/A | K14: 0 | L14: 0 | M14: =I14*$G$6 -> #N/A | N14: =IF(K14>0,K14, IF(L14>0,(G14*(1+L14)+M14), (G14*(1+$G$5)+M14))) -> #N/A | O14: =(N14/$G$2)*D14 -> #N/A | P14: =IF(E14="Sim", O14*$G$3,0) -> #N/A | Q14: =IF(E14="Não",0, O14+(O14*$M$4)+P14 ) -> #N/A | R14: =Q14/$G$2 -> #N/A | S14: =IF(C14="CLT", H14*$K$2, 0) -> 0 | T14: =IF(C14="CLT", S14*$K$3, 0) -> 0 | U14: =IF(C14="CLT", H14/12, 0) -> 0 | V14: =IF(C14="CLT", U14/3, 0) -> 0 | W14: =IF(C14="CLT", H14/12, 0) -> 0 | X14: =IF(C14="CLT", H14/12, 0) -> 0 | Y14: =IF(B14<>"", IF(C14="CLT", 22*$K$5,0),0) -> 0 | Z14: =IF(C14="CLT", H14*$K$4, 0) -> 0 | AA14: =IF(B14<>"", IF(C14="CLT", $O$2, 0),0) -> 0 | AB14: =SUM(S14:AA14) -> 0 | AC14: =IF(E14="Sim", Q14*$G$4, 0) -> #N/A | AD14: =Q14-AC14-I14-M14-P14 -> #N/A | AE14: =(IF(AD14>0,AD14/Q14,"")) -> #N/A
C15: PJ | F15: 0 | G15: =IF(F15>0,F15, IF(B15<>"", IF(C15="CLT",VLOOKUP(B15,'Lista Profissionais'!$C$11:$H$348,3,0), VLOOKUP(B15,'Lista Profissionais'!$C$11:$H$348,4,0)), 0)) -> 0 | H15: =(G15/$G$2)*D15 -> 0 | I15: =H15+AB15 -> 0 | J15: =I15+AC15 -> 0 | K15: 0 | L15: 0 | M15: =I15*$G$6 -> 0 | N15: =IF(K15>0,K15, IF(L15>0,(G15*(1+L15)+M15), (G15*(1+$G$5)+M15))) -> 0 | O15: =(N15/$G$2)*D15 -> 0 | P15: =IF(E15="Sim", O15*$G$3,0) -> 0 | Q15: =IF(E15="Não",0, O15+(O15*$M$4)+P15 ) -> #N/A | R15: =Q15/$G$2 -> #N/A | S15: =IF(C15="CLT", H15*$K$2, 0) -> 0 | T15: =IF(C15="CLT", S15*$K$3, 0) -> 0 | U15: =IF(C15="CLT", H15/12, 0) -> 0 | V15: =IF(C15="CLT", U15/3, 0) -> 0 | W15: =IF(C15="CLT", H15/12, 0) -> 0 | X15: =IF(C15="CLT", H15/12, 0) -> 0 | Y15: =IF(B15<>"", IF(C15="CLT", 22*$K$5,0),0) -> 0 | Z15: =IF(C15="CLT", H15*$K$4, 0) -> 0 | AA15: =IF(B15<>"", IF(C15="CLT", $O$2, 0),0) -> 0 | AB15: =SUM(S15:AA15) -> 0 | AC15: =IF(E15="Sim", Q15*$G$4, 0) -> 0 | AD15: =Q15-AC15-I15-M15-P15 -> #N/A | AE15: =(IF(AD15>0,AD15/Q15,"")) -> #N/A
C16: PJ | F16: 0 | G16: =IF(F16>0,F16, IF(B16<>"", IF(C16="CLT",VLOOKUP(B16,'Lista Profissionais'!$C$11:$H$348,3,0), VLOOKUP(B16,'Lista Profissionais'!$C$11:$H$348,4,0)), 0)) -> 0 | H16: =(G16/$G$2)*D16 -> 0 | I16: =H16+AB16 -> 0 | J16: =I16+AC16 -> 0 | K16: 0 | L16: 0 | M16: =I16*$G$6 -> 0 | N16: =IF(K16>0,K16, IF(L16>0,(G16*(1+L16)+M16), (G16*(1+$G$5)+M16))) -> 0 | O16: =(N16/$G$2)*D16 -> 0 | P16: =IF(E16="Sim", O16*$G$3,0) -> 0 | Q16: =IF(E16="Não",0, O16+(O16*$M$4)+P16 ) -> #N/A | R16: =Q16/$G$2 -> #N/A | S16: =IF(C16="CLT", H16*$K$2, 0) -> 0 | T16: =IF(C16="CLT", S16*$K$3, 0) -> 0 | U16: =IF(C16="CLT", H16/12, 0) -> 0 | V16: =IF(C16="CLT", U16/3, 0) -> 0 | W16: =IF(C16="CLT", H16/12, 0) -> 0 | X16: =IF(C16="CLT", H16/12, 0) -> 0 | Y16: =IF(B16<>"", IF(C16="CLT", 22*$K$5,0),0) -> 0 | Z16: =IF(C16="CLT", H16*$K$4, 0) -> 0 | AA16: =IF(B16<>"", IF(C16="CLT", $O$2, 0),0) -> 0 | AB16: =SUM(S16:AA16) -> 0 | AC16: =IF(E16="Sim", Q16*$G$4, 0) -> 0 | AD16: =Q16-AC16-I16-M16-P16 -> #N/A | AE16: =(IF(AD16>0,AD16/Q16,"")) -> #N/A
C17: PJ | F17: 0 | G17: =IF(F17>0,F17, IF(B17<>"", IF(C17="CLT",VLOOKUP(B17,'Lista Profissionais'!$C$11:$H$348,3,0), VLOOKUP(B17,'Lista Profissionais'!$C$11:$H$348,4,0)), 0)) -> 0 | H17: =(G17/$G$2)*D17 -> 0 | I17: =H17+AB17 -> 0 | J17: =I17+AC17 -> 0 | K17: 0 | L17: 0 | M17: =I17*$G$6 -> 0 | N17: =IF(K17>0,K17, IF(L17>0,(G17*(1+L17)+M17), (G17*(1+$G$5)+M17))) -> 0 | O17: =(N17/$G$2)*D17 -> 0 | P17: =IF(E17="Sim", O17*$G$3,0) -> 0 | Q17: =IF(E17="Não",0, O17+(O17*$M$4)+P17 ) -> #N/A | R17: =Q17/$G$2 -> #N/A | S17: =IF(C17="CLT", H17*$K$2, 0) -> 0 | T17: =IF(C17="CLT", S17*$K$3, 0) -> 0 | U17: =IF(C17="CLT", H17/12, 0) -> 0 | V17: =IF(C17="CLT", U17/3, 0) -> 0 | W17: =IF(C17="CLT", H17/12, 0) -> 0 | X17: =IF(C17="CLT", H17/12, 0) -> 0 | Y17: =IF(B17<>"", IF(C17="CLT", 22*$K$5,0),0) -> 0 | Z17: =IF(C17="CLT", H17*$K$4, 0) -> 0 | AA17: =IF(B17<>"", IF(C17="CLT", $O$2, 0),0) -> 0 | AB17: =SUM(S17:AA17) -> 0 | AC17: =IF(E17="Sim", Q17*$G$4, 0) -> 0 | AD17: =Q17-AC17-I17-M17-P17 -> #N/A | AE17: =(IF(AD17>0,AD17/Q17,"")) -> #N/A
C18: PJ | F18: 0 | G18: =IF(F18>0,F18, IF(B18<>"", IF(C18="CLT",VLOOKUP(B18,'Lista Profissionais'!$C$11:$H$348,3,0), VLOOKUP(B18,'Lista Profissionais'!$C$11:$H$348,4,0)), 0)) -> 0 | H18: =(G18/$G$2)*D18 -> 0 | I18: =H18+AB18 -> 0 | J18: =I18+AC18 -> 0 | K18: 0 | L18: 0 | M18: =I18*$G$6 -> 0 | N18: =IF(K18>0,K18, IF(L18>0,(G18*(1+L18)+M18), (G18*(1+$G$5)+M18))) -> 0 | O18: =(N18/$G$2)*D18 -> 0 | P18: =IF(E18="Sim", O18*$G$3,0) -> 0 | Q18: =IF(E18="Não",0, O18+(O18*$M$4)+P18 ) -> #N/A | R18: =Q18/$G$2 -> #N/A | S18: =IF(C18="CLT", H18*$K$2, 0) -> 0 | T18: =IF(C18="CLT", S18*$K$3, 0) -> 0 | U18: =IF(C18="CLT", H18/12, 0) -> 0 | V18: =IF(C18="CLT", U18/3, 0) -> 0 | W18: =IF(C18="CLT", H18/12, 0) -> 0 | X18: =IF(C18="CLT", H18/12, 0) -> 0 | Y18: =IF(B18<>"", IF(C18="CLT", 22*$K$5,0),0) -> 0 | Z18: =IF(C18="CLT", H18*$K$4, 0) -> 0 | AA18: =IF(B18<>"", IF(C18="CLT", $O$2, 0),0) -> 0 | AB18: =SUM(S18:AA18) -> 0 | AC18: =IF(E18="Sim", Q18*$G$4, 0) -> 0 | AD18: =Q18-AC18-I18-M18-P18 -> #N/A | AE18: =(IF(AD18>0,AD18/Q18,"")) -> #N/A
C19: PJ | F19: 0 | G19: =IF(F19>0,F19, IF(B19<>"", IF(C19="CLT",VLOOKUP(B19,'Lista Profissionais'!$C$11:$H$348,3,0), VLOOKUP(B19,'Lista Profissionais'!$C$11:$H$348,4,0)), 0)) -> 0 | H19: =(G19/$G$2)*D19 -> 0 | I19: =H19+AB19 -> 0 | J19: =I19+AC19 -> 0 | K19: 0 | L19: 0 | M19: =I19*$G$6 -> 0 | N19: =IF(K19>0,K19, IF(L19>0,(G19*(1+L19)+M19), (G19*(1+$G$5)+M19))) -> 0 | O19: =(N19/$G$2)*D19 -> 0 | P19: =IF(E19="Sim", O19*$G$3,0) -> 0 | Q19: =IF(E19="Não",0, O19+(O19*$M$4)+P19 ) -> #N/A | R19: =Q19/$G$2 -> #N/A | S19: =IF(C19="CLT", H19*$K$2, 0) -> 0 | T19: =IF(C19="CLT", S19*$K$3, 0) -> 0 | U19: =IF(C19="CLT", H19/12, 0) -> 0 | V19: =IF(C19="CLT", U19/3, 0) -> 0 | W19: =IF(C19="CLT", H19/12, 0) -> 0 | X19: =IF(C19="CLT", H19/12, 0) -> 0 | Y19: =IF(B19<>"", IF(C19="CLT", 22*$K$5,0),0) -> 0 | Z19: =IF(C19="CLT", H19*$K$4, 0) -> 0 | AA19: =IF(B19<>"", IF(C19="CLT", $O$2, 0),0) -> 0 | AB19: =SUM(S19:AA19) -> 0 | AC19: =IF(E19="Sim", Q19*$G$4, 0) -> 0 | AD19: =Q19-AC19-I19-M19-P19 -> #N/A | AE19: =(IF(AD19>0,AD19/Q19,"")) -> #N/A
C20: PJ | F20: 0 | G20: =IF(F20>0,F20, IF(B20<>"", IF(C20="CLT",VLOOKUP(B20,'Lista Profissionais'!$C$11:$H$348,3,0), VLOOKUP(B20,'Lista Profissionais'!$C$11:$H$348,4,0)), 0)) -> 0 | H20: =(G20/$G$2)*D20 -> 0 | I20: =H20+AB20 -> 0 | J20: =I20+AC20 -> 0 | K20: 0 | L20: 0 | M20: =I20*$G$6 -> 0 | N20: =IF(K20>0,K20, IF(L20>0,(G20*(1+L20)+M20), (G20*(1+$G$5)+M20))) -> 0 | O20: =(N20/$G$2)*D20 -> 0 | P20: =IF(E20="Sim", O20*$G$3,0) -> 0 | Q20: =IF(E20="Não",0, O20+(O20*$M$4)+P20 ) -> #N/A | R20: =Q20/$G$2 -> #N/A | S20: =IF(C20="CLT", H20*$K$2, 0) -> 0 | T20: =IF(C20="CLT", S20*$K$3, 0) -> 0 | U20: =IF(C20="CLT", H20/12, 0) -> 0 | V20: =IF(C20="CLT", U20/3, 0) -> 0 | W20: =IF(C20="CLT", H20/12, 0) -> 0 | X20: =IF(C20="CLT", H20/12, 0) -> 0 | Y20: =IF(B20<>"", IF(C20="CLT", 22*$K$5,0),0) -> 0 | Z20: =IF(C20="CLT", H20*$K$4, 0) -> 0 | AA20: =IF(B20<>"", IF(C20="CLT", $O$2, 0),0) -> 0 | AB20: =SUM(S20:AA20) -> 0 | AC20: =IF(E20="Sim", Q20*$G$4, 0) -> 0 | AD20: =Q20-AC20-I20-M20-P20 -> #N/A | AE20: =(IF(AD20>0,AD20/Q20,"")) -> #N/A
C21: PJ | F21: 0 | G21: =IF(F21>0,F21, IF(B21<>"", IF(C21="CLT",VLOOKUP(B21,'Lista Profissionais'!$C$11:$H$348,3,0), VLOOKUP(B21,'Lista Profissionais'!$C$11:$H$348,4,0)), 0)) -> 0 | H21: =(G21/$G$2)*D21 -> 0 | I21: =H21+AB21 -> 0 | J21: =I21+AC21 -> 0 | K21: 0 | L21: 0 | M21: =I21*$G$6 -> 0 | N21: =IF(K21>0,K21, IF(L21>0,(G21*(1+L21)+M21), (G21*(1+$G$5)+M21))) -> 0 | O21: =(N21/$G$2)*D21 -> 0 | P21: =IF(E21="Sim", O21*$G$3,0) -> 0 | Q21: =IF(E21="Não",0, O21+(O21*$M$4)+P21 ) -> #N/A | R21: =Q21/$G$2 -> #N/A | S21: =IF(C21="CLT", H21*$K$2, 0) -> 0 | T21: =IF(C21="CLT", S21*$K$3, 0) -> 0 | U21: =IF(C21="CLT", H21/12, 0) -> 0 | V21: =IF(C21="CLT", U21/3, 0) -> 0 | W21: =IF(C21="CLT", H21/12, 0) -> 0 | X21: =IF(C21="CLT", H21/12, 0) -> 0 | Y21: =IF(B21<>"", IF(C21="CLT", 22*$K$5,0),0) -> 0 | Z21: =IF(C21="CLT", H21*$K$4, 0) -> 0 | AA21: =IF(B21<>"", IF(C21="CLT", $O$2, 0),0) -> 0 | AB21: =SUM(S21:AA21) -> 0 | AC21: =IF(E21="Sim", Q21*$G$4, 0) -> 0 | AD21: =Q21-AC21-I21-M21-P21 -> #N/A | AE21: =(IF(AD21>0,AD21/Q21,"")) -> #N/A
C22: PJ | F22: 0 | G22: =IF(F22>0,F22, IF(B22<>"", IF(C22="CLT",VLOOKUP(B22,'Lista Profissionais'!$C$11:$H$348,3,0), VLOOKUP(B22,'Lista Profissionais'!$C$11:$H$348,4,0)), 0)) -> 0 | H22: =(G22/$G$2)*D22 -> 0 | I22: =H22+AB22 -> 0 | J22: =I22+AC22 -> 0 | K22: 0 | L22: 0 | M22: =I22*$G$6 -> 0 | N22: =IF(K22>0,K22, IF(L22>0,(G22*(1+L22)+M22), (G22*(1+$G$5)+M22))) -> 0 | O22: =(N22/$G$2)*D22 -> 0 | P22: =IF(E22="Sim", O22*$G$3,0) -> 0 | Q22: =IF(E22="Não",0, O22+(O22*$M$4)+P22 ) -> #N/A | R22: =Q22/$G$2 -> #N/A | S22: =IF(C22="CLT", H22*$K$2, 0) -> 0 | T22: =IF(C22="CLT", S22*$K$3, 0) -> 0 | U22: =IF(C22="CLT", H22/12, 0) -> 0 | V22: =IF(C22="CLT", U22/3, 0) -> 0 | W22: =IF(C22="CLT", H22/12, 0) -> 0 | X22: =IF(C22="CLT", H22/12, 0) -> 0 | Y22: =IF(B22<>"", IF(C22="CLT", 22*$K$5,0),0) -> 0 | Z22: =IF(C22="CLT", H22*$K$4, 0) -> 0 | AA22: =IF(B22<>"", IF(C22="CLT", $O$2, 0),0) -> 0 | AB22: =SUM(S22:AA22) -> 0 | AC22: =IF(E22="Sim", Q22*$G$4, 0) -> 0 | AD22: =Q22-AC22-I22-M22-P22 -> #N/A | AE22: =(IF(AD22>0,AD22/Q22,"")) -> #N/A
C23: PJ | F23: 0 | G23: =IF(F23>0,F23, IF(B23<>"", IF(C23="CLT",VLOOKUP(B23,'Lista Profissionais'!$C$11:$H$348,3,0), VLOOKUP(B23,'Lista Profissionais'!$C$11:$H$348,4,0)), 0)) -> 0 | H23: =(G23/$G$2)*D23 -> 0 | I23: =H23+AB23 -> 0 | J23: =I23+AC23 -> 0 | K23: 0 | L23: 0 | M23: =I23*$G$6 -> 0 | N23: =IF(K23>0,K23, IF(L23>0,(G23*(1+L23)+M23), (G23*(1+$G$5)+M23))) -> 0 | O23: =(N23/$G$2)*D23 -> 0 | P23: =IF(E23="Sim", O23*$G$3,0) -> 0 | Q23: =IF(E23="Não",0, O23+(O23*$M$4)+P23 ) -> #N/A | R23: =Q23/$G$2 -> #N/A | S23: =IF(C23="CLT", H23*$K$2, 0) -> 0 | T23: =IF(C23="CLT", S23*$K$3, 0) -> 0 | U23: =IF(C23="CLT", H23/12, 0) -> 0 | V23: =IF(C23="CLT", U23/3, 0) -> 0 | W23: =IF(C23="CLT", H23/12, 0) -> 0 | X23: =IF(C23="CLT", H23/12, 0) -> 0 | Y23: =IF(B23<>"", IF(C23="CLT", 22*$K$5,0),0) -> 0 | Z23: =IF(C23="CLT", H23*$K$4, 0) -> 0 | AA23: =IF(B23<>"", IF(C23="CLT", $O$2, 0),0) -> 0 | AB23: =SUM(S23:AA23) -> 0 | AC23: =IF(E23="Sim", Q23*$G$4, 0) -> 0 | AD23: =Q23-AC23-I23-M23-P23 -> #N/A | AE23: =(IF(AD23>0,AD23/Q23,"")) -> #N/A
C24: PJ | F24: 0 | G24: =IF(F24>0,F24, IF(B24<>"", IF(C24="CLT",VLOOKUP(B24,'Lista Profissionais'!$C$11:$H$348,3,0), VLOOKUP(B24,'Lista Profissionais'!$C$11:$H$348,4,0)), 0)) -> 0 | H24: =(G24/$G$2)*D24 -> 0 | I24: =H24+AB24 -> 0 | J24: =I24+AC24 -> 0 | K24: 0 | L24: 0 | M24: =I24*$G$6 -> 0 | N24: =IF(K24>0,K24, IF(L24>0,(G24*(1+L24)+M24), (G24*(1+$G$5)+M24))) -> 0 | O24: =(N24/$G$2)*D24 -> 0 | P24: =IF(E24="Sim", O24*$G$3,0) -> 0 | Q24: =IF(E24="Não",0, O24+(O24*$M$4)+P24 ) -> #N/A | R24: =Q24/$G$2 -> #N/A | S24: =IF(C24="CLT", H24*$K$2, 0) -> 0 | T24: =IF(C24="CLT", S24*$K$3, 0) -> 0 | U24: =IF(C24="CLT", H24/12, 0) -> 0 | V24: =IF(C24="CLT", U24/3, 0) -> 0 | W24: =IF(C24="CLT", H24/12, 0) -> 0 | X24: =IF(C24="CLT", H24/12, 0) -> 0 | Y24: =IF(B24<>"", IF(C24="CLT", 22*$K$5,0),0) -> 0 | Z24: =IF(C24="CLT", H24*$K$4, 0) -> 0 | AA24: =IF(B24<>"", IF(C24="CLT", $O$2, 0),0) -> 0 | AB24: =SUM(S24:AA24) -> 0 | AC24: =IF(E24="Sim", Q24*$G$4, 0) -> 0 | AD24: =Q24-AC24-I24-M24-P24 -> #N/A | AE24: =(IF(AD24>0,AD24/Q24,"")) -> #N/A
C25: PJ | F25: 0 | G25: =IF(F25>0,F25, IF(B25<>"", IF(C25="CLT",VLOOKUP(B25,'Lista Profissionais'!$C$11:$H$348,3,0), VLOOKUP(B25,'Lista Profissionais'!$C$11:$H$348,4,0)), 0)) -> 0 | H25: =(G25/$G$2)*D25 -> 0 | I25: =H25+AB25 -> 0 | J25: =I25+AC25 -> 0 | K25: 0 | L25: 0 | M25: =I25*$G$6 -> 0 | N25: =IF(K25>0,K25, IF(L25>0,(G25*(1+L25)+M25), (G25*(1+$G$5)+M25))) -> 0 | O25: =(N25/$G$2)*D25 -> 0 | P25: =IF(E25="Sim", O25*$G$3,0) -> 0 | Q25: =IF(E25="Não",0, O25+(O25*$M$4)+P25 ) -> #N/A | R25: =Q25/$G$2 -> #N/A | S25: =IF(C25="CLT", H25*$K$2, 0) -> 0 | T25: =IF(C25="CLT", S25*$K$3, 0) -> 0 | U25: =IF(C25="CLT", H25/12, 0) -> 0 | V25: =IF(C25="CLT", U25/3, 0) -> 0 | W25: =IF(C25="CLT", H25/12, 0) -> 0 | X25: =IF(C25="CLT", H25/12, 0) -> 0 | Y25: =IF(B25<>"", IF(C25="CLT", 22*$K$5,0),0) -> 0 | Z25: =IF(C25="CLT", H25*$K$4, 0) -> 0 | AA25: =IF(B25<>"", IF(C25="CLT", $O$2, 0),0) -> 0 | AB25: =SUM(S25:AA25) -> 0 | AC25: =IF(E25="Sim", Q25*$G$4, 0) -> 0 | AD25: =Q25-AC25-I25-M25-P25 -> #N/A | AE25: =(IF(AD25>0,AD25/Q25,"")) -> #N/A
C26: PJ | F26: 0 | G26: =IF(F26>0,F26, IF(B26<>"", IF(C26="CLT",VLOOKUP(B26,'Lista Profissionais'!$C$11:$H$348,3,0), VLOOKUP(B26,'Lista Profissionais'!$C$11:$H$348,4,0)), 0)) -> 0 | H26: =(G26/$G$2)*D26 -> 0 | I26: =H26+AB26 -> 0 | J26: =I26+AC26 -> 0 | K26: 0 | L26: 0 | M26: =I26*$G$6 -> 0 | N26: =IF(K26>0,K26, IF(L26>0,(G26*(1+L26)+M26), (G26*(1+$G$5)+M26))) -> 0 | O26: =(N26/$G$2)*D26 -> 0 | P26: =IF(E26="Sim", O26*$G$3,0) -> 0 | Q26: =IF(E26="Não",0, O26+(O26*$M$4)+P26 ) -> #N/A | R26: =Q26/$G$2 -> #N/A | S26: =IF(C26="CLT", H26*$K$2, 0) -> 0 | T26: =IF(C26="CLT", S26*$K$3, 0) -> 0 | U26: =IF(C26="CLT", H26/12, 0) -> 0 | V26: =IF(C26="CLT", U26/3, 0) -> 0 | W26: =IF(C26="CLT", H26/12, 0) -> 0 | X26: =IF(C26="CLT", H26/12, 0) -> 0 | Y26: =IF(B26<>"", IF(C26="CLT", 22*$K$5,0),0) -> 0 | Z26: =IF(C26="CLT", H26*$K$4, 0) -> 0 | AA26: =IF(B26<>"", IF(C26="CLT", $O$2, 0),0) -> 0 | AB26: =SUM(S26:AA26) -> 0 | AC26: =IF(E26="Sim", Q26*$G$4, 0) -> 0 | AD26: =Q26-AC26-I26-M26-P26 -> #N/A | AE26: =(IF(AD26>0,AD26/Q26,"")) -> #N/A
... C33: PJ | F33: 0 | G33: =IF(F33>0,F33, IF(B33<>"", IF(C33="CLT",VLOOKUP(B33,'Lista Profissionais'!$C$11:$H$348,3,0), VLOOKUP(B33,'Lista Profissionais'!$C$11:$H$348,4,0)), 0)) -> 0 | H33: =(G33/$G$2)*D33 -> 0 | I33: =H33+AB33 -> 0 | J33: =I33+AC33 -> 0 | K33: 0 | L33: 0 | M33: =I33*$G$6 -> 0 | N33: =IF(K33>0,K33, IF(L33>0,(G33*(1+L33)+M33), (G33*(1+$G$5)+M33))) -> 0 | O33: =(N33/$G$2)*D33 -> 0 | P33: =IF(E33="Sim", O33*$G$3,0) -> 0 | Q33: =IF(E33="Não",0, O33+(O33*$M$4)+P33 ) -> #N/A | R33: =Q33/$G$2 -> #N/A | S33: =IF(C33="CLT", H33*$K$2, 0) -> 0 | T33: =IF(C33="CLT", S33*$K$3, 0) -> 0 | U33: =IF(C33="CLT", H33/12, 0) -> 0 | V33: =IF(C33="CLT", U33/3, 0) -> 0 | W33: =IF(C33="CLT", H33/12, 0) -> 0 | X33: =IF(C33="CLT", H33/12, 0) -> 0 | Y33: =IF(B33<>"", IF(C33="CLT", 22*$K$5,0),0) -> 0 | Z33: =IF(C33="CLT", H33*$K$4, 0) -> 0 | AA33: =IF(B33<>"", IF(C33="CLT", $O$2, 0),0) -> 0 | AB33: =SUM(S33:AA33) -> 0 | AC33: =IF(E33="Sim", Q33*$G$4, 0) -> 0 | AD33: =Q33-AC33-I33-M33-P33 -> #N/A | AE33: =(IF(AD33>0,AD33/Q33,"")) -> #N/A
O37: Q | P37: P | Q37: I | S37: M | T37: AB
O38: Tarifa com rateio | P38: Comissão | Q38: Salario | S38: Risco | T38: Imposto | U38: Custo | V38: Lucro
O39: =Q9 -> 0 | P39: =P9 -> 0 | Q39: =I9 -> #N/A | S39: =M9 -> #N/A | T39: =AC9 -> 0 | U39: =SUBTOTAL(9,P39:T39) -> #N/A | V39: =O39-U39 -> #N/A
O40: =Q10 -> #N/A | P40: =P10 -> #N/A | Q40: =I10 -> #N/A | S40: =M10 -> #N/A | T40: =AC10 -> #N/A | U40: =SUBTOTAL(9,P40:T40) -> #N/A | V40: =O40-U40 -> #N/A
O41: =Q11 -> #N/A | P41: =P11 -> #N/A | Q41: =I11 -> #N/A | S41: =M11 -> #N/A | T41: =AC11 -> #N/A | U41: =SUBTOTAL(9,P41:T41) -> #N/A | V41: =O41-U41 -> #N/A
O42: =Q12 -> #N/A | P42: =P12 -> #N/A | Q42: =I12 -> #N/A | S42: =M12 -> #N/A | T42: =AC12 -> #N/A | U42: =SUBTOTAL(9,P42:T42) -> #N/A | V42: =O42-U42 -> #N/A
O43: =Q13 -> #N/A | P43: =P13 -> #N/A | Q43: =I13 -> #N/A | S43: =M13 -> #N/A | T43: =AC13 -> #N/A | U43: =SUBTOTAL(9,P43:T43) -> #N/A | V43: =O43-U43 -> #N/A
O44: =Q14 -> #N/A | P44: =P14 -> #N/A | Q44: =I14 -> #N/A | S44: =M14 -> #N/A | T44: =AC14 -> #N/A | U44: =SUBTOTAL(9,P44:T44) -> #N/A | V44: =O44-U44 -> #N/A
O45: =SUM(O39:O44) -> #N/A | P45: =SUM(P39:P44) -> #N/A | Q45: =SUM(Q39:Q44) -> #N/A | S45: =SUM(S39:S44) -> #N/A | T45: =SUM(T39:T44) -> #N/A | U45: =SUBTOTAL(9,P45:T45) -> #N/A | V45: =O45-U45 -> #N/A

Sheet Lista Profissionais
B1: Composição de preços (CLT e PJ)
B3: Diferença de CLT para PJ | D3: Júnior | E3: 0.3
D4: Pleno | E4: 0.3
D5: Sênior | E5: 0.3 | L5: Dif. Alta | M5: =COUNTIF(M11:M526,"Alta") -> 0
D6: Automatizador | E6: 0.3 | L6: Dif. Média | M6: =COUNTIF(M11:M526,"Média") -> 0
B7: Utilizar valores da Tabela | C7: AVN | D7: Especialista | E7: 0.3 | L7: Dif. Baixa | M7: =COUNTIF(M11:M526,"Baixa") -> 0
D8: Agilista | E8: 0.3
D9: Gestão | E9: 0.3 | G9: 0.2 | I9: BASE | L9: % Dif | O9: Definição | P9: FONTE PESQUISA
B10: Especialidade | C10: Perfil | D10: Senioridade | E10: CLT | F10: Base CLT | G10: Redução benefício | H10: PJ | I10: Mínimo CLT | J10: Média CLT | K10: Máximo CLT | L10: % | M10: Diferença | N10: Enviar | O10: AVN | P10: TECH HUB | Q10: TALENT | R10: GLASS DOR | S10: ROBERT HALF | T10: CATHO
B11: Administrador/Consultor Salesforce - Especialista | C11: =B11 -> Administrador/Consultor Salesforce - Especialista | D11: Especialista | E11: =F11-G11 -> 9600 | F11: 12000 | G11: =F11*$G$9 -> 2400 | H11: =E11+(E11*IF(D11<>"",IF(D11<>"",VLOOKUP(D11,$D$3:$E$9,2,0)),"")) -> 12480 | I11: =_xlfn.MINIFS(Q11:T11,Q11:T11,">0",Q11:T11,"<>"&"") -> #NAME? | J11: =IF(SUM(Q11:T11)>0, AVERAGEIFS(Q11:T11, Q11:T11,">0",Q11:T11,"<>"&""), 0) -> 11525.985 | K11: =_xlfn.MAXIFS(Q11:T11,Q11:T11,">0",Q11:T11,"<>"&"") -> #NAME? | L11: =(K11-I11)/I11 -> #NAME? | M11: {=_xlfn.IFS(L11>=70%,"Alta",L11>20%,"Média",L11<=20%,"Baixa")} -> #NAME? | O11: =J11 -> 11525.985 | P11: 0 | Q11: 11051.97 | R11: 12000 | S11: 0 | T11: 0
B12: Administrador/Consultor Salesforce - Junior | C12: =B12 -> Administrador/Consultor Salesforce - Junior | D12: Júnior | E12: =F12-G12 -> 3040 | F12: 3800 | G12: =F12*$G$9 -> 760 | H12: =E12+(E12*IF(D12<>"",IF(D12<>"",VLOOKUP(D12,$D$3:$E$9,2,0)),"")) -> 3952 | I12: =_xlfn.MINIFS(Q12:T12,Q12:T12,">0",Q12:T12,"<>"&"") -> #NAME? | J12: =IF(SUM(Q12:T12)>0, AVERAGEIFS(Q12:T12, Q12:T12,">0",Q12:T12,"<>"&""), 0) -> 4906.5 | K12: =_xlfn.MAXIFS(Q12:T12,Q12:T12,">0",Q12:T12,"<>"&"") -> #NAME? | L12: =(K12-I12)/I12 -> #NAME? | M12: {=_xlfn.IFS(L12>=70%,"Alta",L12>20%,"Média",L12<=20%,"Baixa")} -> #NAME? | O12: =J12 -> 4906.5 | P12: =K12 -> #NAME? | Q12: 5813 | R12: 4000 | S12: 0 | T12: 0
B13: Administrador/Consultor Salesforce - Pleno | C13: =B13 -> Administrador/Consultor Salesforce - Pleno | D13: Pleno | E13: =F13-G13 -> 6320 | F13: 7900 | G13: =F13*$G$9 -> 1580 | H13: =E13+(E13*IF(D13<>"",IF(D13<>"",VLOOKUP(D13,$D$3:$E$9,2,0)),"")) -> 8216 | I13: =_xlfn.MINIFS(Q13:T13,Q13:T13,">0",Q13:T13,"<>"&"") -> #NAME? | J13: =IF(SUM(Q13:T13)>0, AVERAGEIFS(Q13:T13, Q13:T13,">0",Q13:T13,"<>"&""), 0) -> 7278.45 | K13: =_xlfn.MAXIFS(Q13:T13,Q13:T13,">0",Q13:T13,"<>"&"") -> #NAME? | L13: =(K13-I13)/I13 -> #NAME? | M13: {=_xlfn.IFS(L13>=70%,"Alta",L13>20%,"Média",L13<=20%,"Baixa")} -> #NAME? | O13: =J13 -> 7278.45 | P13: 0 | Q13: 7556.9 | R13: 7000 | S13: 0 | T13: 0
B14: Administrador/Consultor Salesforce - Senior | C14: =B14 -> Administrador/Consultor Salesforce - Senior | D14: Sênior | E14: =F14-G14 -> 8400 | F14: 10500 | G14: =F14*$G$9 -> 2100 | H14: =E14+(E14*IF(D14<>"",IF(D14<>"",VLOOKUP(D14,$D$3:$E$9,2,0)),"")) -> 10920 | I14: =_xlfn.MINIFS(Q14:T14,Q14:T14,">0",Q14:T14,"<>"&"") -> #NAME? | J14: =IF(SUM(Q14:T14)>0, AVERAGEIFS(Q14:T14, Q14:T14,">0",Q14:T14,"<>"&""), 0) -> 9723.0625 | K14: =_xlfn.MAXIFS(Q14:T14,Q14:T14,">0",Q14:T14,"<>"&"") -> #NAME? | L14: =(K14-I14)/I14 -> #NAME? | M14: {=_xlfn.IFS(L14>=70%,"Alta",L14>20%,"Média",L14<=20%,"Baixa")} -> #NAME? | O14: =J14 -> 9723.0625 | P14: 0 | Q14: 9446.125 | R14: 10000 | S14: 0 | T14: 0
B15: Agilista | C15: =B15& " " &D15 -> Agilista Especialista | D15: Especialista | E15: =F15-G15 -> 10800 | F15: 13500 | G15: =F15*$G$9 -> 2700 | H15: =F15+(F15*IF(D15<>"",IF(D15<>"",VLOOKUP(D15,$D$3:$F$9,2,0)),"")) -> 17550 | I15: =_xlfn.MINIFS(Q15:T15,Q15:T15,">0",Q15:T15,"<>"&"") -> #NAME? | J15: =IF(SUM(Q15:T15)>0, AVERAGEIFS(Q15:T15, Q15:T15,">0",Q15:T15,"<>"&""), 0) -> 10122.875 | K15: =_xlfn.MAXIFS(Q15:T15,Q15:T15,">0",Q15:T15,"<>"&"") -> #NAME? | L15: =(K15-I15)/I15 -> #NAME? | M15: {=_xlfn.IFS(L15>=70%,"Alta",L15>20%,"Média",L15<=20%,"Baixa")} -> #NAME? | N15: SIM | O15: =J15 -> 10122.875 | P15: 0 | Q15: 8745.75 | R15: 11500 | S15: 0 | T15: 0
B16: Agilista - Junior | C16: =B16& " " &D16 -> Agilista - Junior Júnior | D16: Júnior | E16: =F16-G16 -> 3920 | F16: 4900 | G16: =F16*$G$9 -> 980 | H16: =F16+(F16*IF(D16<>"",IF(D16<>"",VLOOKUP(D16,$D$3:$F$9,2,0)),"")) -> 6370 | I16: =_xlfn.MINIFS(Q16:T16,Q16:T16,">0",Q16:T16,"<>"&"") -> #NAME? | J16: =IF(SUM(Q16:T16)>0, AVERAGEIFS(Q16:T16, Q16:T16,">0",Q16:T16,"<>"&""), 0) -> 4300 | K16: =_xlfn.MAXIFS(Q16:T16,Q16:T16,">0",Q16:T16,"<>"&"") -> #NAME? | L16: =(K16-I16)/I16 -> #NAME? | M16: {=_xlfn.IFS(L16>=70%,"Alta",L16>20%,"Média",L16<=20%,"Baixa")} -> #NAME? | N16: SIM | O16: =J16 -> 4300 | P16: 0 | Q16: 4600 | R16: 4000 | S16: 0 | T16: 0
B17: Agilista | C17: =B17& " " &D17 -> Agilista Pleno | D17: Pleno | E17: =F17-G17 -> 6320 | F17: 7900 | G17: =F17*$G$9 -> 1580 | H17: =F17+(F17*IF(D17<>"",IF(D17<>"",VLOOKUP(D17,$D$3:$F$9,2,0)),"")) -> 10270 | I17: =_xlfn.MINIFS(Q17:T17,Q17:T17,">0",Q17:T17,"<>"&"") -> #NAME? | J17: =IF(SUM(Q17:T17)>0, AVERAGEIFS(Q17:T17, Q17:T17,">0",Q17:T17,"<>"&""), 0) -> 6490 | K17: =_xlfn.MAXIFS(Q17:T17,Q17:T17,">0",Q17:T17,"<>"&"") -> #NAME? | L17: =(K17-I17)/I17 -> #NAME? | M17: {=_xlfn.IFS(L17>=70%,"Alta",L17>20%,"Média",L17<=20%,"Baixa")} -> #NAME? | N17: SIM | O17: =J17 -> 6490 | P17: 0 | Q17: 5980 | R17: 7000 | S17: 0 | T17: 0
B18: Agilista | C18: =B18& " " &D18 -> Agilista Sênior | D18: Sênior | E18: =F18-G18 -> 9200 | F18: 11500 | G18: =F18*$G$9 -> 2300 | H18: =F18+(F18*IF(D18<>"",IF(D18<>"",VLOOKUP(D18,$D$3:$F$9,2,0)),"")) -> 14950 | I18: =_xlfn.MINIFS(Q18:T18,Q18:T18,">0",Q18:T18,"<>"&"") -> #NAME? | J18: =IF(SUM(Q18:T18)>0, AVERAGEIFS(Q18:T18, Q18:T18,">0",Q18:T18,"<>"&""), 0) -> 8487.5 | K18: =_xlfn.MAXIFS(Q18:T18,Q18:T18,">0",Q18:T18,"<>"&"") -> #NAME? | L18: =(K18-I18)/I18 -> #NAME? | M18: {=_xlfn.IFS(L18>=70%,"Alta",L18>20%,"Média",L18<=20%,"Baixa")} -> #NAME? | N18: SIM | O18: =J18 -> 8487.5 | P18: 0 | Q18: 7475 | R18: 9500 | S18: 0 | T18: 0
B19: Analista de Dados/ BI | C19: =B19& " " &D19 -> Analista de Dados/ BI Especialista | D19: Especialista | E19: =F19-G19 -> 8800 | F19: 11000 | G19: =F19*$G$9 -> 2200 | H19: =F19+(F19*IF(D19<>"",IF(D19<>"",VLOOKUP(D19,$D$3:$F$9,2,0)),"")) -> 14300 | I19: =_xlfn.MINIFS(Q19:T19,Q19:T19,">0",Q19:T19,"<>"&"") -> #NAME? | J19: =IF(SUM(Q19:T19)>0, AVERAGEIFS(Q19:T19, Q19:T19,">0",Q19:T19,"<>"&""), 0) -> 10200 | K19: =_xlfn.MAXIFS(Q19:T19,Q19:T19,">0",Q19:T19,"<>"&"") -> #NAME? | L19: =(K19-I19)/I19 -> #NAME? | M19: {=_xlfn.IFS(L19>=70%,"Alta",L19>20%,"Média",L19<=20%,"Baixa")} -> #NAME? | N19: SIM | O19: =J19 -> 10200 | P19: 0 | Q19: 9400 | R19: 11000 | S19: 0 | T19: 0
B20: Analista de Dados/ BI | C20: =B20& " " &D20 -> Analista de Dados/ BI Júnior | D20: Júnior | E20: =F20-G20 -> 3360 | F20: 4200 | G20: =F20*$G$9 -> 840 | H20: =F20+(F20*IF(D20<>"",IF(D20<>"",VLOOKUP(D20,$D$3:$F$9,2,0)),"")) -> 5460 | I20: =_xlfn.MINIFS(Q20:T20,Q20:T20,">0",Q20:T20,"<>"&"") -> #NAME? | J20: =IF(SUM(Q20:T20)>0, AVERAGEIFS(Q20:T20, Q20:T20,">0",Q20:T20,"<>"&""), 0) -> 3519 | K20: =_xlfn.MAXIFS(Q20:T20,Q20:T20,">0",Q20:T20,"<>"&"") -> #NAME? | L20: =(K20-I20)/I20 -> #NAME? | M20: {=_xlfn.IFS(L20>=70%,"Alta",L20>20%,"Média",L20<=20%,"Baixa")} -> #NAME? | N20: SIM | O20: =J20 -> 3519 | P20: 0 | Q20: 4538 | R20: 2500 | S20: 0 | T20: 0
B21: Analista de Dados/ BI | C21: =B21& " " &D21 -> Analista de Dados/ BI Pleno | D21: Pleno | E21: =F21-G21 -> 6000 | F21: 7500 | G21: =F21*$G$9 -> 1500 | H21: =F21+(F21*IF(D21<>"",IF(D21<>"",VLOOKUP(D21,$D$3:$F$9,2,0)),"")) -> 9750 | I21: =_xlfn.MINIFS(Q21:T21,Q21:T21,">0",Q21:T21,"<>"&"") -> #NAME? | J21: =IF(SUM(Q21:T21)>0, AVERAGEIFS(Q21:T21, Q21:T21,">0",Q21:T21,"<>"&""), 0) -> 6000 | K21: =_xlfn.MAXIFS(Q21:T21,Q21:T21,">0",Q21:T21,"<>"&"") -> #NAME? | L21: =(K21-I21)/I21 -> #NAME? | M21: {=_xlfn.IFS(L21>=70%,"Alta",L21>20%,"Média",L21<=20%,"Baixa")} -> #NAME? | N21: SIM | O21: =J21 -> 6000 | P21: 0 | Q21: 6500 | R21: 5500 | S21: 0 | T21: 0
B22: Analista de Dados/ BI | C22: =B22& " " &D22 -> Analista de Dados/ BI Sênior | D22: Sênior | E22: =F22-G22 -> 7600 | F22: 9500 | G22: =F22*$G$9 -> 1900 | H22: =F22+(F22*IF(D22<>"",IF(D22<>"",VLOOKUP(D22,$D$3:$F$9,2,0)),"")) -> 12350 | I22: =_xlfn.MINIFS(Q22:T22,Q22:T22,">0",Q22:T22,"<>"&"") -> #NAME? | J22: =IF(SUM(Q22:T22)>0, AVERAGEIFS(Q22:T22, Q22:T22,">0",Q22:T22,"<>"&""), 0) -> 8125 | K22: =_xlfn.MAXIFS(Q22:T22,Q22:T22,">0",Q22:T22,"<>"&"") -> #NAME? | L22: =(K22-I22)/I22 -> #NAME? | M22: {=_xlfn.IFS(L22>=70%,"Alta",L22>20%,"Média",L22<=20%,"Baixa")} -> #NAME? | N22: SIM | O22: =J22 -> 8125 | P22: 0 | Q22: 8250 | R22: 8000 | S22: 0 | T22: 0
B23: Analista de Inteligência Artificial | C23: =B23& " " &D23 -> Analista de Inteligência Artificial Especialista | D23: Especialista | E23: =F23-G23 -> 10800 | F23: 13500 | G23: =F23*$G$9 -> 2700 | H23: =F23+(F23*IF(D23<>"",IF(D23<>"",VLOOKUP(D23,$D$3:$F$9,2,0)),"")) -> 17550 | I23: =_xlfn.MINIFS(Q23:T23,Q23:T23,">0",Q23:T23,"<>"&"") -> #NAME? | J23: =IF(SUM(Q23:T23)>0, AVERAGEIFS(Q23:T23, Q23:T23,">0",Q23:T23,"<>"&""), 0) -> 10396.641 | K23: =_xlfn.MAXIFS(Q23:T23,Q23:T23,">0",Q23:T23,"<>"&"") -> #NAME? | L23: =(K23-I23)/I23 -> #NAME? | M23: {=_xlfn.IFS(L23>=70%,"Alta",L23>20%,"Média",L23<=20%,"Baixa")} -> #NAME? | N23: SIM | O23: =J23 -> 10396.641 | P23: 0 | Q23: 8793.2812 | R23: 12000 | S23: 0 | T23: 0
B24: Analista de Inteligência Artificial | C24: =B24& " " &D24 -> Analista de Inteligência Artificial Júnior | D24: Júnior | E24: =F24-G24 -> 3920 | F24: 4900 | G24: =F24*$G$9 -> 980 | H24: =F24+(F24*IF(D24<>"",IF(D24<>"",VLOOKUP(D24,$D$3:$F$9,2,0)),"")) -> 6370 | I24: =_xlfn.MINIFS(Q24:T24,Q24:T24,">0",Q24:T24,"<>"&"") -> #NAME? | J24: =IF(SUM(Q24:T24)>0, AVERAGEIFS(Q24:T24, Q24:T24,">0",Q24:T24,"<>"&""), 0) -> 4400 | K24: =_xlfn.MAXIFS(Q24:T24,Q24:T24,">0",Q24:T24,"<>"&"") -> #NAME? | L24: =(K24-I24)/I24 -> #NAME? | M24: {=_xlfn.IFS(L24>=70%,"Alta",L24>20%,"Média",L24<=20%,"Baixa")} -> #NAME? | N24: SIM | O24: =J24 -> 4400 | P24: 0 | Q24: 5300 | R24: 3500 | S24: 0 | T24: 0
B25: Analista de Inteligência Artificial | C25: =B25& " " &D25 -> Analista de Inteligência Artificial Pleno | D25: Pleno | E25: =F25-G25 -> 6000 | F25: 7500 | G25: =F25*$G$9 -> 1500 | H25: =F25+(F25*IF(D25<>"",IF(D25<>"",VLOOKUP(D25,$D$3:$F$9,2,0)),"")) -> 9750 | I25: =_xlfn.MINIFS(Q25:T25,Q25:T25,">0",Q25:T25,"<>"&"") -> #NAME? | J25: =IF(SUM(Q25:T25)>0, AVERAGEIFS(Q25:T25, Q25:T25,">0",Q25:T25,"<>"&""), 0) -> 6506.25 | K25: =_xlfn.MAXIFS(Q25:T25,Q25:T25,">0",Q25:T25,"<>"&"") -> #NAME? | L25: =(K25-I25)/I25 -> #NAME? | M25: {=_xlfn.IFS(L25>=70%,"Alta",L25>20%,"Média",L25<=20%,"Baixa")} -> #NAME? | N25: SIM | O25: =J25 -> 6506.25 | P25: 0 | Q25: 6012.5 | R25: 7000 | S25: 0 | T25: 0
B26: Analista de Inteligência Artificial | C26: =B26& " " &D26 -> Analista de Inteligência Artificial Sênior | D26: Sênior | E26: =F26-G26 -> 8800 | F26: 11000 | G26: =F26*$G$9 -> 2200 | H26: =F26+(F26*IF(D26<>"",IF(D26<>"",VLOOKUP(D26,$D$3:$F$9,2,0)),"")) -> 14300 | I26: =_xlfn.MINIFS(Q26:T26,Q26:T26,">0",Q26:T26,"<>"&"") -> #NAME? | J26: =IF(SUM(Q26:T26)>0, AVERAGEIFS(Q26:T26, Q26:T26,">0",Q26:T26,"<>"&""), 0) -> 8757.8125 | K26: =_xlfn.MAXIFS(Q26:T26,Q26:T26,">0",Q26:T26,"<>"&"") -> #NAME? | L26: =(K26-I26)/I26 -> #NAME? | M26: {=_xlfn.IFS(L26>=70%,"Alta",L26>20%,"Média",L26<=20%,"Baixa")} -> #NAME? | N26: SIM | O26: =J26 -> 8757.8125 | P26: 0 | Q26: 7515.625 | R26: 10000 | S26: 0 | T26: 0
... B30: Analista de Processos | C30: =B30& " " &D30 -> Analista de Processos Sênior | D30: Sênior | E30: =F30-G30 -> 8000 | F30: 10000 | G30: =F30*$G$9 -> 2000 | H30: =F30+(F30*IF(D30<>"",IF(D30<>"",VLOOKUP(D30,$D$3:$F$9,2,0)),"")) -> 13000 | I30: =_xlfn.MINIFS(Q30:T30,Q30:T30,">0",Q30:T30,"<>"&"") -> #NAME? | J30: =IF(SUM(Q30:T30)>0, AVERAGEIFS(Q30:T30, Q30:T30,">0",Q30:T30,"<>"&""), 0) -> 7250 | K30: =_xlfn.MAXIFS(Q30:T30,Q30:T30,">0",Q30:T30,"<>"&"") -> #NAME? | L30: =(K30-I30)/I30 -> #NAME? | M30: {=_xlfn.IFS(L30>=70%,"Alta",L30>20%,"Média",L30<=20%,"Baixa")} -> #NAME? | N30: SIM | O30: =J30 -> 7250 | P30: 0 | Q30: 6500 | R30: 8000 | S30: 0 | T30: 0
B31: Analista de Qualidade | C31: =B31& " " &D31 -> Analista de Qualidade Especialista | D31: Especialista | E31: =F31-G31 -> 8000 | F31: 10000 | G31: =F31*$G$9 -> 2000 | H31: =F31+(F31*IF(D31<>"",IF(D31<>"",VLOOKUP(D31,$D$3:$F$9,2,0)),"")) -> 13000 | I31: =_xlfn.MINIFS(Q31:T31,Q31:T31,">0",Q31:T31,"<>"&"") -> #NAME? | J31: =IF(SUM(Q31:T31)>0, AVERAGEIFS(Q31:T31, Q31:T31,">0",Q31:T31,"<>"&""), 0) -> 8552.5 | K31: =_xlfn.MAXIFS(Q31:T31,Q31:T31,">0",Q31:T31,"<>"&"") -> #NAME? | L31: =(K31-I31)/I31 -> #NAME? | M31: {=_xlfn.IFS(L31>=70%,"Alta",L31>20%,"Média",L31<=20%,"Baixa")} -> #NAME? | N31: SIM | O31: 8300 | P31: 0 | Q31: 7605 | R31: 9500 | S31: 0 | T31: 0
B32: Analista de Qualidade | C32: =B32& " " &D32 -> Analista de Qualidade Júnior | D32: Júnior | E32: =F32-G32 -> 2800 | F32: 3500 | G32: =F32*$G$9 -> 700 | H32: =F32+(F32*IF(D32<>"",IF(D32<>"",VLOOKUP(D32,$D$3:$F$9,2,0)),"")) -> 4550 | I32: =_xlfn.MINIFS(Q32:T32,Q32:T32,">0",Q32:T32,"<>"&"") -> #NAME? | J32: =IF(SUM(Q32:T32)>0, AVERAGEIFS(Q32:T32, Q32:T32,">0",Q32:T32,"<>"&""), 0) -> 3500 | K32: =_xlfn.MAXIFS(Q32:T32,Q32:T32,">0",Q32:T32,"<>"&"") -> #NAME? | L32: =(K32-I32)/I32 -> #NAME? | M32: {=_xlfn.IFS(L32>=70%,"Alta",L32>20%,"Média",L32<=20%,"Baixa")} -> #NAME? | N32: SIM | O32: =J32 -> 3500 | P32: 0 | Q32: 4000 | R32: 3000 | S32: 0 | T32: 0
B33: Analista de Qualidade | C33: =B33& " " &D33 -> Analista de Qualidade Pleno | D33: Pleno | E33: =F33-G33 -> 4400 | F33: 5500 | G33: =F33*$G$9 -> 1100 | H33: =F33+(F33*IF(D33<>"",IF(D33<>"",VLOOKUP(D33,$D$3:$F$9,2,0)),"")) -> 7150 | I33: =_xlfn.MINIFS(Q33:T33,Q33:T33,">0",Q33:T33,"<>"&"") -> #NAME? | J33: =IF(SUM(Q33:T33)>0, AVERAGEIFS(Q33:T33, Q33:T33,">0",Q33:T33,"<>"&""), 0) -> 6100 | K33: =_xlfn.MAXIFS(Q33:T33,Q33:T33,">0",Q33:T33,"<>"&"") -> #NAME? | L33: =(K33-I33)/I33 -> #NAME? | M33: {=_xlfn.IFS(L33>=70%,"Alta",L33>20%,"Média",L33<=20%,"Baixa")} -> #NAME? | N33: SIM | O33: =J33 -> 6100 | P33: 0 | Q33: 5200 | R33: 7000 | S33: 0 | T33: 0
B34: Analista de Qualidade | C34: =B34& " " &D34 -> Analista de Qualidade Sênior | D34: Sênior | E34: =F34-G34 -> 5416 | F34: 6770 | G34: =F34*$G$9 -> 1354 | H34: =F34+(F34*IF(D34<>"",IF(D34<>"",VLOOKUP(D34,$D$3:$F$9,2,0)),"")) -> 8801 | I34: =_xlfn.MINIFS(Q34:T34,Q34:T34,">0",Q34:T34,"<>"&"") -> #NAME? | J34: =IF(SUM(Q34:T34)>0, AVERAGEIFS(Q34:T34, Q34:T34,">0",Q34:T34,"<>"&""), 0) -> 7500 | K34: =_xlfn.MAXIFS(Q34:T34,Q34:T34,">0",Q34:T34,"<>"&"") -> #NAME? | L34: =(K34-I34)/I34 -> #NAME? | M34: {=_xlfn.IFS(L34>=70%,"Alta",L34>20%,"Média",L34<=20%,"Baixa")} -> #NAME? | N34: SIM | O34: =J34 -> 7500 | P34: 0 | Q34: 6500 | R34: 8500 | S34: 0 | T34: 0
B35: Analista de Negócios | C35: =B35& " " &D35 -> Analista de Negócios Especialista | D35: Especialista | E35: =F35-G35 -> 8400 | F35: 10500 | G35: =F35*$G$9 -> 2100 | H35: =F35+(F35*IF(D35<>"",IF(D35<>"",VLOOKUP(D35,$D$3:$F$9,2,0)),"")) -> 13650 | I35: =_xlfn.MINIFS(Q35:T35,Q35:T35,">0",Q35:T35,"<>"&"") -> #NAME? | J35: =IF(SUM(Q35:T35)>0, AVERAGEIFS(Q35:T35, Q35:T35,">0",Q35:T35,"<>"&""), 0) -> 9323.5 | K35: =_xlfn.MAXIFS(Q35:T35,Q35:T35,">0",Q35:T35,"<>"&"") -> #NAME? | L35: =(K35-I35)/I35 -> #NAME? | M35: {=_xlfn.IFS(L35>=70%,"Alta",L35>20%,"Média",L35<=20%,"Baixa")} -> #NAME? | N35: SIM | O35: =J35 -> 9323.5 | P35: 0 | Q35: 10647 | R35: 8000 | S35: 0 | T35: 0
B36: Analista de Negócios | C36: =B36& " " &D36 -> Analista de Negócios Júnior | D36: Júnior | E36: =F36-G36 -> 3840 | F36: 4800 | G36: =F36*$G$9 -> 960 | H36: =F36+(F36*IF(D36<>"",IF(D36<>"",VLOOKUP(D36,$D$3:$F$9,2,0)),"")) -> 6240 | I36: =_xlfn.MINIFS(Q36:T36,Q36:T36,">0",Q36:T36,"<>"&"") -> #NAME? | J36: =IF(SUM(Q36:T36)>0, AVERAGEIFS(Q36:T36, Q36:T36,">0",Q36:T36,"<>"&""), 0) -> 4550 | K36: =_xlfn.MAXIFS(Q36:T36,Q36:T36,">0",Q36:T36,"<>"&"") -> #NAME? | L36: =(K36-I36)/I36 -> #NAME? | M36: {=_xlfn.IFS(L36>=70%,"Alta",L36>20%,"Média",L36<=20%,"Baixa")} -> #NAME? | N36: SIM | O36: =J36 -> 4550 | P36: 0 | Q36: 5600 | R36: 3500 | S36: 0 | T36: 0
B37: Analista de Negócios | C37: =B37& " " &D37 -> Analista de Negócios Pleno | D37: Pleno | E37: =F37-G37 -> 6000 | F37: 7500 | G37: =F37*$G$9 -> 1500 | H37: =F37+(F37*IF(D37<>"",IF(D37<>"",VLOOKUP(D37,$D$3:$F$9,2,0)),"")) -> 9750 | I37: =_xlfn.MINIFS(Q37:T37,Q37:T37,">0",Q37:T37,"<>"&"") -> #NAME? | J37: =IF(SUM(Q37:T37)>0, AVERAGEIFS(Q37:T37, Q37:T37,">0",Q37:T37,"<>"&""), 0) -> 6540 | K37: =_xlfn.MAXIFS(Q37:T37,Q37:T37,">0",Q37:T37,"<>"&"") -> #NAME? | L37: =(K37-I37)/I37 -> #NAME? | M37: {=_xlfn.IFS(L37>=70%,"Alta",L37>20%,"Média",L37<=20%,"Baixa")} -> #NAME? | N37: SIM | O37: =J37 -> 6540 | P37: 0 | Q37: 7280 | R37: 5800 | S37: 0 | T37: 0
B38: Analista de Negócios | C38: =B38& " " &D38 -> Analista de Negócios Sênior | D38: Sênior | E38: =F38-G38 -> 8400 | F38: 10500 | G38: =F38*$G$9 -> 2100 | H38: =F38+(F38*IF(D38<>"",IF(D38<>"",VLOOKUP(D38,$D$3:$F$9,2,0)),"")) -> 13650 | I38: =_xlfn.MINIFS(Q38:T38,Q38:T38,">0",Q38:T38,"<>"&"") -> #NAME? | J38: =IF(SUM(Q38:T38)>0, AVERAGEIFS(Q38:T38, Q38:T38,">0",Q38:T38,"<>"&""), 0) -> 8050 | K38: =_xlfn.MAXIFS(Q38:T38,Q38:T38,">0",Q38:T38,"<>"&"") -> #NAME? | L38: =(K38-I38)/I38 -> #NAME? | M38: {=_xlfn.IFS(L38>=70%,"Alta",L38>20%,"Média",L38<=20%,"Baixa")} -> #NAME? | N38: SIM | O38: =J38 -> 8050 | P38: 0 | Q38: 9100 | R38: 7000 | S38: 0 | T38: 0
B39: Analista de redes/infraestrutura | C39: =B39& " " &D39 -> Analista de redes/infraestrutura Especialista | D39: Especialista | E39: =F39-G39 -> 8800 | F39: 11000 | G39: =F39*$G$9 -> 2200 | H39: =F39+(F39*IF(D39<>"",IF(D39<>"",VLOOKUP(D39,$D$3:$F$9,2,0)),"")) -> 14300 | N39: SIM | O39: =J39 -> 0 | Q39: 0 | R39: 0
B40: Analista de redes/infraestrutura | C40: =B40& " " &D40 -> Analista de redes/infraestrutura Júnior | D40: Júnior | E40: =F40-G40 -> 3200 | F40: 4000 | G40: =F40*$G$9 -> 800 | H40: =F40+(F40*IF(D40<>"",IF(D40<>"",VLOOKUP(D40,$D$3:$F$9,2,0)),"")) -> 5200 | N40: SIM | O40: =J40 -> 0 | Q40: 0 | R40: 0
B41: Analista de redes/infraestrutura | C41: =B41& " " &D41 -> Analista de redes/infraestrutura Pleno | D41: Pleno | E41: =F41-G41 -> 4800 | F41: 6000 | G41: =F41*$G$9 -> 1200 | H41: =F41+(F41*IF(D41<>"",IF(D41<>"",VLOOKUP(D41,$D$3:$F$9,2,0)),"")) -> 7800 | N41: SIM | O41: =J41 -> 0 | Q41: 0 | R41: 0
B42: Analista de redes/infraestrutura | C42: =B42& " " &D42 -> Analista de redes/infraestrutura Sênior | D42: Sênior | E42: =F42-G42 -> 6400 | F42: 8000 | G42: =F42*$G$9 -> 1600 | H42: =F42+(F42*IF(D42<>"",IF(D42<>"",VLOOKUP(D42,$D$3:$F$9,2,0)),"")) -> 10400 | N42: SIM | O42: =J42 -> 0 | Q42: 0 | R42: 0
B43: Analista de Suporte (N1) | C43: =B43& " " &D43 -> Analista de Suporte (N1) Júnior | D43: Júnior | E43: =F43-G43 -> 1840 | F43: 2300 | G43: =F43*$G$9 -> 460 | H43: =F43+(F43*IF(D43<>"",IF(D43<>"",VLOOKUP(D43,$D$3:$F$9,2,0)),"")) -> 2990 | N43: SIM | O43: =J43 -> 0 | Q43: 0 | R43: 0
B44: Analista de Suporte (N1) | C44: =B44& " " &D44 -> Analista de Suporte (N1) Pleno | D44: Pleno | E44: =F44-G44 -> 2720 | F44: 3400 | G44: =F44*$G$9 -> 680 | H44: =F44+(F44*IF(D44<>"",IF(D44<>"",VLOOKUP(D44,$D$3:$F$9,2,0)),"")) -> 4420 | N44: SIM | O44: =J44 -> 0 | Q44: 0 | R44: 0
B45: Analista de Suporte (N1) | C45: =B45& " " &D45 -> Analista de Suporte (N1) Sênior | D45: Sênior | E45: =F45-G45 -> 4200 | F45: 5250 | G45: =F45*$G$9 -> 1050 | H45: =F45+(F45*IF(D45<>"",IF(D45<>"",VLOOKUP(D45,$D$3:$F$9,2,0)),"")) -> 6825 | N45: SIM | O45: =J45 -> 0 | Q45: 0 | R45: 0
B46: Analista de Suporte (N2) | C46: =B46& " " &D46 -> Analista de Suporte (N2) Especialista | D46: Especialista | E46: =F46-G46 -> 5600 | F46: 7000 | G46: =F46*$G$9 -> 1400 | H46: =E46+(E46*IF(D46<>"",IF(D46<>"",VLOOKUP(D46,$D$3:$E$9,2,0)),"")) -> 7280 | I46: =_xlfn.MINIFS(Q46:T46,Q46:T46,">0",Q46:T46,"<>"&"") -> #NAME? | J46: =IF(SUM(Q46:T46)>0, AVERAGEIFS(Q46:T46, Q46:T46,">0",Q46:T46,"<>"&""), 0) -> 6232.125 | K46: =_xlfn.MAXIFS(Q46:T46,Q46:T46,">0",Q46:T46,"<>"&"") -> #NAME? | L46: =(K46-I46)/I46 -> #NAME? | M46: {=_xlfn.IFS(L46>=70%,"Alta",L46>20%,"Média",L46<=20%,"Baixa")} -> #NAME? | O46: =J46 -> 6232.125 | P46: 0 | Q46: 6464.25 | R46: 6000 | S46: 0 | T46: 0
B47: Analista de Suporte (N2) | C47: =B47& " " &D47 -> Analista de Suporte (N2) Júnior | D47: Júnior | E47: =F47-G47 -> 2400 | F47: 3000 | G47: =F47*$G$9 -> 600 | H47: =F47+(F47*IF(D47<>"",IF(D47<>"",VLOOKUP(D47,$D$3:$F$9,2,0)),"")) -> 3900 | I47: =_xlfn.MINIFS(Q47:T47,Q47:T47,">0",Q47:T47,"<>"&"") -> #NAME? | J47: =IF(SUM(Q47:T47)>0, AVERAGEIFS(Q47:T47, Q47:T47,">0",Q47:T47,"<>"&""), 0) -> 2700 | K47: =_xlfn.MAXIFS(Q47:T47,Q47:T47,">0",Q47:T47,"<>"&"") -> #NAME? | L47: =(K47-I47)/I47 -> #NAME? | M47: {=_xlfn.IFS(L47>=70%,"Alta",L47>20%,"Média",L47<=20%,"Baixa")} -> #NAME? | N47: SIM | O47: 1970 | P47: 0 | Q47: 3400 | R47: 2000 | S47: 0 | T47: 0
B48: Analista de Suporte (N2) | C48: =B48& " " &D48 -> Analista de Suporte (N2) Pleno | D48: Pleno | E48: =F48-G48 -> 3200 | F48: 4000 | G48: =F48*$G$9 -> 800 | H48: =F48+(F48*IF(D48<>"",IF(D48<>"",VLOOKUP(D48,$D$3:$F$9,2,0)),"")) -> 5200 | I48: =_xlfn.MINIFS(Q48:T48,Q48:T48,">0",Q48:T48,"<>"&"") -> #NAME? | J48: =IF(SUM(Q48:T48)>0, AVERAGEIFS(Q48:T48, Q48:T48,">0",Q48:T48,"<>"&""), 0) -> 3710 | K48: =_xlfn.MAXIFS(Q48:T48,Q48:T48,">0",Q48:T48,"<>"&"") -> #NAME? | L48: =(K48-I48)/I48 -> #NAME? | M48: {=_xlfn.IFS(L48>=70%,"Alta",L48>20%,"Média",L48<=20%,"Baixa")} -> #NAME? | N48: SIM | O48: =J48 -> 3710 | P48: 0 | Q48: 4420 | R48: 3000 | S48: 0 | T48: 0
B49: Analista de Suporte (N2) | C49: =B49& " " &D49 -> Analista de Suporte (N2) Sênior | D49: Sênior | E49: =F49-G49 -> 4400 | F49: 5500 | G49: =F49*$G$9 -> 1100 | H49: =F49+(F49*IF(D49<>"",IF(D49<>"",VLOOKUP(D49,$D$3:$F$9,2,0)),"")) -> 7150 | I49: =_xlfn.MINIFS(Q49:T49,Q49:T49,">0",Q49:T49,"<>"&"") -> #NAME? | J49: =IF(SUM(Q49:T49)>0, AVERAGEIFS(Q49:T49, Q49:T49,">0",Q49:T49,"<>"&""), 0) -> 4762.5 | K49: =_xlfn.MAXIFS(Q49:T49,Q49:T49,">0",Q49:T49,"<>"&"") -> #NAME? | L49: =(K49-I49)/I49 -> #NAME? | M49: {=_xlfn.IFS(L49>=70%,"Alta",L49>20%,"Média",L49<=20%,"Baixa")} -> #NAME? | N49: SIM | O49: =J49 -> 4762.5 | P49: 0 | Q49: 5525 | R49: 4000 | S49: 0 | T49: 0
B50: Analista de Testes de Performance - Especialista | C50: =B50& " " &D50 -> Analista de Testes de Performance - Especialista Especialista | D50: Especialista | E50: =F50-G50 -> 6800 | F50: 8500 | G50: =F50*$G$9 -> 1700 | H50: =E50+(E50*IF(D50<>"",IF(D50<>"",VLOOKUP(D50,$D$3:$E$9,2,0)),"")) -> 8840 | I50: =_xlfn.MINIFS(Q50:T50,Q50:T50,">0",Q50:T50,"<>"&"") -> #NAME? | J50: =IF(SUM(Q50:T50)>0, AVERAGEIFS(Q50:T50, Q50:T50,">0",Q50:T50,"<>"&""), 0) -> 9313 | K50: =_xlfn.MAXIFS(Q50:T50,Q50:T50,">0",Q50:T50,"<>"&"") -> #NAME? | L50: =(K50-I50)/I50 -> #NAME? | M50: {=_xlfn.IFS(L50>=70%,"Alta",L50>20%,"Média",L50<=20%,"Baixa")} -> #NAME? | O50: 5280 | P50: 0 | Q50: 9126 | R50: 9500 | S50: 0 | T50: 0
B51: Analista de Testes de Performance - Junior | C51: =B51& " " &D51 -> Analista de Testes de Performance - Junior Júnior | D51: Júnior | E51: =F51-G51 -> 3040 | F51: 3800 | G51: =F51*$G$9 -> 760 | H51: =E51+(E51*IF(D51<>"",IF(D51<>"",VLOOKUP(D51,$D$3:$E$9,2,0)),"")) -> 3952 | I51: =_xlfn.MINIFS(Q51:T51,Q51:T51,">0",Q51:T51,"<>"&"") -> #NAME? | J51: =IF(SUM(Q51:T51)>0, AVERAGEIFS(Q51:T51, Q51:T51,">0",Q51:T51,"<>"&""), 0) -> 3900 | K51: =_xlfn.MAXIFS(Q51:T51,Q51:T51,">0",Q51:T51,"<>"&"") -> #NAME? | L51: =(K51-I51)/I51 -> #NAME? | M51: {=_xlfn.IFS(L51>=70%,"Alta",L51>20%,"Média",L51<=20%,"Baixa")} -> #NAME? | O51: 3000 | P51: 0 | Q51: 4800 | R51: 3000 | S51: 0 | T51: 0
B52: Analista de Testes de Performance - Pleno | C52: =B52& " " &D52 -> Analista de Testes de Performance - Pleno Pleno | D52: Pleno | E52: =F52-G52 -> 4720 | F52: 5900 | G52: =F52*$G$9 -> 1180 | H52: =E52+(E52*IF(D52<>"",IF(D52<>"",VLOOKUP(D52,$D$3:$E$9,2,0)),"")) -> 6136 | I52: =_xlfn.MINIFS(Q52:T52,Q52:T52,">0",Q52:T52,"<>"&"") -> #NAME? | J52: =IF(SUM(Q52:T52)>0, AVERAGEIFS(Q52:T52, Q52:T52,">0",Q52:T52,"<>"&""), 0) -> 5620 | K52: =_xlfn.MAXIFS(Q52:T52,Q52:T52,">0",Q52:T52,"<>"&"") -> #NAME? | L52: =(K52-I52)/I52 -> #NAME? | M52: {=_xlfn.IFS(L52>=70%,"Alta",L52>20%,"Média",L52<=20%,"Baixa")} -> #NAME? | O52: 3750 | P52: 0 | Q52: 6240 | R52: 5000 | S52: 0 | T52: 0
B53: Analista de Testes de Performance - Senior | C53: =B53& " " &D53 -> Analista de Testes de Performance - Senior Sênior | D53: Sênior | E53: =F53-G53 -> 5920 | F53: 7400 | G53: =F53*$G$9 -> 1480 | H53: =E53+(E53*IF(D53<>"",IF(D53<>"",VLOOKUP(D53,$D$3:$E$9,2,0)),"")) -> 7696 | I53: =_xlfn.MINIFS(Q53:T53,Q53:T53,">0",Q53:T53,"<>"&"") -> #NAME? | J53: =IF(SUM(Q53:T53)>0, AVERAGEIFS(Q53:T53, Q53:T53,">0",Q53:T53,"<>"&""), 0) -> 7400 | K53: =_xlfn.MAXIFS(Q53:T53,Q53:T53,">0",Q53:T53,"<>"&"") -> #NAME? | L53: =(K53-I53)/I53 -> #NAME? | M53: {=_xlfn.IFS(L53>=70%,"Alta",L53>20%,"Média",L53<=20%,"Baixa")} -> #NAME? | O53: 4520 | P53: 0 | Q53: 7800 | R53: 7000 | S53: 0 | T53: 0
B54: Analista de Web Analytics - Especialista | C54: =B54 -> Analista de Web Analytics - Especialista | D54: Pleno | E54: =F54-G54 -> 9200 | F54: 11500 | G54: =F54*$G$9 -> 2300 | H54: =E54+(E54*IF(D54<>"",IF(D54<>"",VLOOKUP(D54,$D$3:$E$9,2,0)),"")) -> 11960 | I54: =_xlfn.MINIFS(Q54:T54,Q54:T54,">0",Q54:T54,"<>"&"") -> #NAME? | J54: =IF(SUM(Q54:T54)>0, AVERAGEIFS(Q54:T54, Q54:T54,">0",Q54:T54,"<>"&""), 0) -> 7577.1875 | K54: =_xlfn.MAXIFS(Q54:T54,Q54:T54,">0",Q54:T54,"<>"&"") -> #NAME? | L54: =(K54-I54)/I54 -> #NAME? | M54: {=_xlfn.IFS(L54>=70%,"Alta",L54>20%,"Média",L54<=20%,"Baixa")} -> #NAME? | O54: =J54 -> 7577.1875 | P54: 0 | Q54: 6654.375 | R54: 8500 | S54: 0 | T54: 0
B55: Analista de Web Analytics - Junior | C55: =B55 -> Analista de Web Analytics - Junior | D55: Pleno | E55: =F55-G55 -> 2800 | F55: 3500 | G55: =F55*$G$9 -> 700 | H55: =E55+(E55*IF(D55<>"",IF(D55<>"",VLOOKUP(D55,$D$3:$E$9,2,0)),"")) -> 3640 | I55: =_xlfn.MINIFS(Q55:T55,Q55:T55,">0",Q55:T55,"<>"&"") -> #NAME? | J55: =IF(SUM(Q55:T55)>0, AVERAGEIFS(Q55:T55, Q55:T55,">0",Q55:T55,"<>"&""), 0) -> 3250 | K55: =_xlfn.MAXIFS(Q55:T55,Q55:T55,">0",Q55:T55,"<>"&"") -> #NAME? | L55: =(K55-I55)/I55 -> #NAME? | M55: {=_xlfn.IFS(L55>=70%,"Alta",L55>20%,"Média",L55<=20%,"Baixa")} -> #NAME? | O55: =J55 -> 3250 | P55: 0 | Q55: 3500 | R55: 3000 | S55: 0 | T55: 0
B56: Analista de Web Analytics - Pleno | C56: =B56 -> Analista de Web Analytics - Pleno | D56: Pleno | E56: =F56-G56 -> 5600 | F56: 7000 | G56: =F56*$G$9 -> 1400 | H56: =E56+(E56*IF(D56<>"",IF(D56<>"",VLOOKUP(D56,$D$3:$E$9,2,0)),"")) -> 7280 | I56: =_xlfn.MINIFS(Q56:T56,Q56:T56,">0",Q56:T56,"<>"&"") -> #NAME? | J56: =IF(SUM(Q56:T56)>0, AVERAGEIFS(Q56:T56, Q56:T56,">0",Q56:T56,"<>"&""), 0) -> 4525 | K56: =_xlfn.MAXIFS(Q56:T56,Q56:T56,">0",Q56:T56,"<>"&"") -> #NAME? | L56: =(K56-I56)/I56 -> #NAME? | M56: {=_xlfn.IFS(L56>=70%,"Alta",L56>20%,"Média",L56<=20%,"Baixa")} -> #NAME? | O56: =J56 -> 4525 | P56: 0 | Q56: 4550 | R56: 4500 | S56: 0 | T56: 0
B57: Analista de Web Analytics - Senior | C57: =B57 -> Analista de Web Analytics - Senior | D57: Pleno | E57: =F57-G57 -> 7600 | F57: 9500 | G57: =F57*$G$9 -> 1900 | H57: =E57+(E57*IF(D57<>"",IF(D57<>"",VLOOKUP(D57,$D$3:$E$9,2,0)),"")) -> 9880 | I57: =_xlfn.MINIFS(Q57:T57,Q57:T57,">0",Q57:T57,"<>"&"") -> #NAME? | J57: =IF(SUM(Q57:T57)>0, AVERAGEIFS(Q57:T57, Q57:T57,">0",Q57:T57,"<>"&""), 0) -> 6093.75 | K57: =_xlfn.MAXIFS(Q57:T57,Q57:T57,">0",Q57:T57,"<>"&"") -> #NAME? | L57: =(K57-I57)/I57 -> #NAME? | M57: {=_xlfn.IFS(L57>=70%,"Alta",L57>20%,"Média",L57<=20%,"Baixa")} -> #NAME? | O57: =J57 -> 6093.75 | P57: 0 | Q57: 5687.5 | R57: 6500 | S57: 0 | T57: 0
B58: Analista Funcional de Suporte (N2) - Especialista | C58: =B58 -> Analista Funcional de Suporte (N2) - Especialista | D58: Pleno | E58: =F58-G58 -> 9200 | F58: 11500 | G58: =F58*$G$9 -> 2300 | H58: =E58+(E58*IF(D58<>"",IF(D58<>"",VLOOKUP(D58,$D$3:$E$9,2,0)),"")) -> 11960 | I58: =_xlfn.MINIFS(Q58:T58,Q58:T58,">0",Q58:T58,"<>"&"") -> #NAME? | J58: =IF(SUM(Q58:T58)>0, AVERAGEIFS(Q58:T58, Q58:T58,">0",Q58:T58,"<>"&""), 0) -> 7337.6875 | K58: =_xlfn.MAXIFS(Q58:T58,Q58:T58,">0",Q58:T58,"<>"&"") -> #NAME? | L58: =(K58-I58)/I58 -> #NAME? | M58: {=_xlfn.IFS(L58>=70%,"Alta",L58>20%,"Média",L58<=20%,"Baixa")} -> #NAME? | O58: =J58 -> 7337.6875 | P58: 0 | Q58: 8175.375 | R58: 6500 | S58: 0 | T58: 0
B59: Analista Funcional de Suporte (N2) - Junior | C59: =B59 -> Analista Funcional de Suporte (N2) - Junior | D59: Pleno | E59: =F59-G59 -> 3200 | F59: 4000 | G59: =F59*$G$9 -> 800 | H59: =E59+(E59*IF(D59<>"",IF(D59<>"",VLOOKUP(D59,$D$3:$E$9,2,0)),"")) -> 4160 | I59: =_xlfn.MINIFS(Q59:T59,Q59:T59,">0",Q59:T59,"<>"&"") -> #NAME? | J59: =IF(SUM(Q59:T59)>0, AVERAGEIFS(Q59:T59, Q59:T59,">0",Q59:T59,"<>"&""), 0) -> 3150 | K59: =_xlfn.MAXIFS(Q59:T59,Q59:T59,">0",Q59:T59,"<>"&"") -> #NAME? | L59: =(K59-I59)/I59 -> #NAME? | M59: {=_xlfn.IFS(L59>=70%,"Alta",L59>20%,"Média",L59<=20%,"Baixa")} -> #NAME? | O59: =J59 -> 3150 | P59: 0 | Q59: 4300 | R59: 2000 | S59: 0 | T59: 0
B60: Analista Funcional de Suporte (N2) - Pleno | C60: =B60 -> Analista Funcional de Suporte (N2) - Pleno | D60: Pleno | E60: =F60-G60 -> 5600 | F60: 7000 | G60: =F60*$G$9 -> 1400 | H60: =E60+(E60*IF(D60<>"",IF(D60<>"",VLOOKUP(D60,$D$3:$E$9,2,0)),"")) -> 7280 | I60: =_xlfn.MINIFS(Q60:T60,Q60:T60,">0",Q60:T60,"<>"&"") -> #NAME? | J60: =IF(SUM(Q60:T60)>0, AVERAGEIFS(Q60:T60, Q60:T60,">0",Q60:T60,"<>"&""), 0) -> 4295 | K60: =_xlfn.MAXIFS(Q60:T60,Q60:T60,">0",Q60:T60,"<>"&"") -> #NAME? | L60: =(K60-I60)/I60 -> #NAME? | M60: {=_xlfn.IFS(L60>=70%,"Alta",L60>20%,"Média",L60<=20%,"Baixa")} -> #NAME? | O60: =J60 -> 4295 | P60: 0 | Q60: 5590 | R60: 3000 | S60: 0 | T60: 0
B61: Analista Funcional de Suporte (N2) - Senior | C61: =B61 -> Analista Funcional de Suporte (N2) - Senior | D61: Pleno | E61: =F61-G61 -> 7600 | F61: 9500 | G61: =F61*$G$9 -> 1900 | H61: =E61+(E61*IF(D61<>"",IF(D61<>"",VLOOKUP(D61,$D$3:$E$9,2,0)),"")) -> 9880 | I61: =_xlfn.MINIFS(Q61:T61,Q61:T61,">0",Q61:T61,"<>"&"") -> #NAME? | J61: =IF(SUM(Q61:T61)>0, AVERAGEIFS(Q61:T61, Q61:T61,">0",Q61:T61,"<>"&""), 0) -> 5743.75 | K61: =_xlfn.MAXIFS(Q61:T61,Q61:T61,">0",Q61:T61,"<>"&"") -> #NAME? | L61: =(K61-I61)/I61 -> #NAME? | M61: {=_xlfn.IFS(L61>=70%,"Alta",L61>20%,"Média",L61<=20%,"Baixa")} -> #NAME? | O61: =J61 -> 5743.75 | P61: 0 | Q61: 6987.5 | R61: 4500 | S61: 0 | T61: 0
B62: Analista UX | C62: =B62& " " &D62 -> Analista UX Especialista | D62: Especialista | E62: =F62-G62 -> 7600 | F62: 9500 | G62: =F62*$G$9 -> 1900 | H62: =F62+(F62*IF(D62<>"",IF(D62<>"",VLOOKUP(D62,$D$3:$F$9,2,0)),"")) -> 12350 | I62: =_xlfn.MINIFS(Q62:T62,Q62:T62,">0",Q62:T62,"<>"&"") -> #NAME? | J62: =IF(SUM(Q62:T62)>0, AVERAGEIFS(Q62:T62, Q62:T62,">0",Q62:T62,"<>"&""), 0) -> 9943.25 | K62: =_xlfn.MAXIFS(Q62:T62,Q62:T62,">0",Q62:T62,"<>"&"") -> #NAME? | L62: =(K62-I62)/I62 -> #NAME? | M62: {=_xlfn.IFS(L62>=70%,"Alta",L62>20%,"Média",L62<=20%,"Baixa")} -> #NAME? | N62: SIM | O62: =J62 -> 9943.25 | P62: 0 | Q62: 9886.5 | R62: 10000 | S62: 0 | T62: 0
B63: Analista UX | C63: =B63& " " &D63 -> Analista UX Júnior | D63: Júnior | E63: =F63-G63 -> 3200 | F63: 4000 | G63: =F63*$G$9 -> 800 | H63: =F63+(F63*IF(D63<>"",IF(D63<>"",VLOOKUP(D63,$D$3:$F$9,2,0)),"")) -> 5200 | I63: =_xlfn.MINIFS(Q63:T63,Q63:T63,">0",Q63:T63,"<>"&"") -> #NAME? | J63: =IF(SUM(Q63:T63)>0, AVERAGEIFS(Q63:T63, Q63:T63,">0",Q63:T63,"<>"&""), 0) -> 4100 | K63: =_xlfn.MAXIFS(Q63:T63,Q63:T63,">0",Q63:T63,"<>"&"") -> #NAME? | L63: =(K63-I63)/I63 -> #NAME? | M63: {=_xlfn.IFS(L63>=70%,"Alta",L63>20%,"Média",L63<=20%,"Baixa")} -> #NAME? | N63: SIM | O63: =J63 -> 4100 | P63: 0 | Q63: 5200 | R63: 3000 | S63: 0 | T63: 0
B64: Analista UX | C64: =B64& " " &D64 -> Analista UX Pleno | D64: Pleno | E64: =F64-G64 -> 4400 | F64: 5500 | G64: =F64*$G$9 -> 1100 | H64: =F64+(F64*IF(D64<>"",IF(D64<>"",VLOOKUP(D64,$D$3:$F$9,2,0)),"")) -> 7150 | I64: =_xlfn.MINIFS(Q64:T64,Q64:T64,">0",Q64:T64,"<>"&"") -> #NAME? | J64: =IF(SUM(Q64:T64)>0, AVERAGEIFS(Q64:T64, Q64:T64,">0",Q64:T64,"<>"&""), 0) -> 6130 | K64: =_xlfn.MAXIFS(Q64:T64,Q64:T64,">0",Q64:T64,"<>"&"") -> #NAME? | L64: =(K64-I64)/I64 -> #NAME? | M64: {=_xlfn.IFS(L64>=70%,"Alta",L64>20%,"Média",L64<=20%,"Baixa")} -> #NAME? | N64: SIM | O64: =J64 -> 6130 | P64: 0 | Q64: 6760 | R64: 5500 | S64: 0 | T64: 0
B65: Analista UX | C65: =B65& " " &D65 -> Analista UX Sênior | D65: Sênior | E65: =F65-G65 -> 5760 | F65: 7200 | G65: =F65*$G$9 -> 1440 | H65: =F65+(F65*IF(D65<>"",IF(D65<>"",VLOOKUP(D65,$D$3:$F$9,2,0)),"")) -> 9360 | I65: =_xlfn.MINIFS(Q65:T65,Q65:T65,">0",Q65:T65,"<>"&"") -> #NAME? | J65: =IF(SUM(Q65:T65)>0, AVERAGEIFS(Q65:T65, Q65:T65,">0",Q65:T65,"<>"&""), 0) -> 7725 | K65: =_xlfn.MAXIFS(Q65:T65,Q65:T65,">0",Q65:T65,"<>"&"") -> #NAME? | L65: =(K65-I65)/I65 -> #NAME? | M65: {=_xlfn.IFS(L65>=70%,"Alta",L65>20%,"Média",L65<=20%,"Baixa")} -> #NAME? | N65: SIM | O65: =J65 -> 7725 | P65: 0 | Q65: 8450 | R65: 7000 | S65: 0 | T65: 0
B66: Arquiteto de infraestrutura | C66: =B66& " " &D66 -> Arquiteto de infraestrutura Especialista | D66: Especialista | E66: =F66-G66 -> 11600 | F66: 14500 | G66: =F66*$G$9 -> 2900 | H66: =F66+(F66*IF(D66<>"",IF(D66<>"",VLOOKUP(D66,$D$3:$F$9,2,0)),"")) -> 18850 | I66: =_xlfn.MINIFS(Q66:T66,Q66:T66,">0",Q66:T66,"<>"&"") -> #NAME? | J66: =IF(SUM(Q66:T66)>0, AVERAGEIFS(Q66:T66, Q66:T66,">0",Q66:T66,"<>"&""), 0) -> 13464.25 | K66: =_xlfn.MAXIFS(Q66:T66,Q66:T66,">0",Q66:T66,"<>"&"") -> #NAME? | L66: =(K66-I66)/I66 -> #NAME? | M66: {=_xlfn.IFS(L66>=70%,"Alta",L66>20%,"Média",L66<=20%,"Baixa")} -> #NAME? | N66: SIM | O66: =J66 -> 13464.25 | P66: 0 | Q66: 12928.5 | R66: 14000 | S66: 0 | T66: 0
B67: Arquiteto de infraestrutura | C67: =B67& " " &D67 -> Arquiteto de infraestrutura Júnior | D67: Júnior | E67: =F67-G67 -> 3200 | F67: 4000 | G67: =F67*$G$9 -> 800 | H67: =E67+(E67*IF(D67<>"",IF(D67<>"",VLOOKUP(D67,$D$3:$E$9,2,0)),"")) -> 4160 | I67: =_xlfn.MINIFS(Q67:T67,Q67:T67,">0",Q67:T67,"<>"&"") -> #NAME? | J67: =IF(SUM(Q67:T67)>0, AVERAGEIFS(Q67:T67, Q67:T67,">0",Q67:T67,"<>"&""), 0) -> 6150 | K67: =_xlfn.MAXIFS(Q67:T67,Q67:T67,">0",Q67:T67,"<>"&"") -> #NAME? | L67: =(K67-I67)/I67 -> #NAME? | M67: {=_xlfn.IFS(L67>=70%,"Alta",L67>20%,"Média",L67<=20%,"Baixa")} -> #NAME? | O67: 5250 | P67: 0 | Q67: 6800 | R67: 5500 | S67: 0 | T67: 0
B68: Arquiteto de infraestrutura | C68: =B68& " " &D68 -> Arquiteto de infraestrutura Pleno | D68: Pleno | E68: =F68-G68 -> 7200 | F68: 9000 | G68: =F68*$G$9 -> 1800 | H68: =F68+(F68*IF(D68<>"",IF(D68<>"",VLOOKUP(D68,$D$3:$F$9,2,0)),"")) -> 11700 | I68: =_xlfn.MINIFS(Q68:T68,Q68:T68,">0",Q68:T68,"<>"&"") -> #NAME? | J68: =IF(SUM(Q68:T68)>0, AVERAGEIFS(Q68:T68, Q68:T68,">0",Q68:T68,"<>"&""), 0) -> 8020 | K68: =_xlfn.MAXIFS(Q68:T68,Q68:T68,">0",Q68:T68,"<>"&"") -> #NAME? | L68: =(K68-I68)/I68 -> #NAME? | M68: {=_xlfn.IFS(L68>=70%,"Alta",L68>20%,"Média",L68<=20%,"Baixa")} -> #NAME? | N68: SIM | O68: =J68 -> 8020 | P68: 0 | Q68: 8840 | R68: 7200 | S68: 0 | T68: 0
B69: Arquiteto de infraestrutura | C69: =B69& " " &D69 -> Arquiteto de infraestrutura Sênior | D69: Sênior | E69: =F69-G69 -> 10080 | F69: 12600 | G69: =F69*$G$9 -> 2520 | H69: =F69+(F69*IF(D69<>"",IF(D69<>"",VLOOKUP(D69,$D$3:$F$9,2,0)),"")) -> 16380 | I69: =_xlfn.MINIFS(Q69:T69,Q69:T69,">0",Q69:T69,"<>"&"") -> #NAME? | J69: =IF(SUM(Q69:T69)>0, AVERAGEIFS(Q69:T69, Q69:T69,">0",Q69:T69,"<>"&""), 0) -> 11525 | K69: =_xlfn.MAXIFS(Q69:T69,Q69:T69,">0",Q69:T69,"<>"&"") -> #NAME? | L69: =(K69-I69)/I69 -> #NAME? | M69: {=_xlfn.IFS(L69>=70%,"Alta",L69>20%,"Média",L69<=20%,"Baixa")} -> #NAME? | N69: SIM | O69: =J69 -> 11525 | P69: 0 | Q69: 11050 | R69: 12000 | S69: 0 | T69: 0
B70: Arquiteto de Soluções BI Especialista/Líder | C70: =B70 -> Arquiteto de Soluções BI Especialista/Líder | D70: Pleno | E70: =F70-G70 -> 9600 | F70: 12000 | G70: =F70*$G$9 -> 2400 | H70: =E70+(E70*IF(D70<>"",IF(D70<>"",VLOOKUP(D70,$D$3:$E$9,2,0)),"")) -> 12480 | I70: =_xlfn.MINIFS(Q70:T70,Q70:T70,">0",Q70:T70,"<>"&"") -> #NAME? | J70: =IF(SUM(Q70:T70)>0, AVERAGEIFS(Q70:T70, Q70:T70,">0",Q70:T70,"<>"&""), 0) -> 8900 | K70: =_xlfn.MAXIFS(Q70:T70,Q70:T70,">0",Q70:T70,"<>"&"") -> #NAME? | L70: =(K70-I70)/I70 -> #NAME? | M70: {=_xlfn.IFS(L70>=70%,"Alta",L70>20%,"Média",L70<=20%,"Baixa")} -> #NAME? | O70: =J70 -> 8900 | P70: 0 | Q70: 5500 | R70: 12300 | S70: 0 | T70: 0
B71: Arquiteto de Soluções BI Junior | C71: =B71 -> Arquiteto de Soluções BI Junior | D71: Pleno | E71: =F71-G71 -> 3920 | F71: 4900 | G71: =F71*$G$9 -> 980 | H71: =E71+(E71*IF(D71<>"",IF(D71<>"",VLOOKUP(D71,$D$3:$E$9,2,0)),"")) -> 5096 | I71: =_xlfn.MINIFS(Q71:T71,Q71:T71,">0",Q71:T71,"<>"&"") -> #NAME? | J71: =IF(SUM(Q71:T71)>0, AVERAGEIFS(Q71:T71, Q71:T71,">0",Q71:T71,"<>"&""), 0) -> 5825 | K71: =_xlfn.MAXIFS(Q71:T71,Q71:T71,">0",Q71:T71,"<>"&"") -> #NAME? | L71: =(K71-I71)/I71 -> #NAME? | M71: {=_xlfn.IFS(L71>=70%,"Alta",L71>20%,"Média",L71<=20%,"Baixa")} -> #NAME? | O71: =J71 -> 5825 | P71: 0 | Q71: 7150 | R71: 4500 | S71: 0 | T71: 0
B72: Arquiteto de Soluções BI Pleno | C72: =B72 -> Arquiteto de Soluções BI Pleno | D72: Pleno | E72: =F72-G72 -> 6800 | F72: 8500 | G72: =F72*$G$9 -> 1700 | H72: =E72+(E72*IF(D72<>"",IF(D72<>"",VLOOKUP(D72,$D$3:$E$9,2,0)),"")) -> 8840 | I72: =_xlfn.MINIFS(Q72:T72,Q72:T72,">0",Q72:T72,"<>"&"") -> #NAME? | J72: =IF(SUM(Q72:T72)>0, AVERAGEIFS(Q72:T72, Q72:T72,">0",Q72:T72,"<>"&""), 0) -> 7868.75 | K72: =_xlfn.MAXIFS(Q72:T72,Q72:T72,">0",Q72:T72,"<>"&"") -> #NAME? | L72: =(K72-I72)/I72 -> #NAME? | M72: {=_xlfn.IFS(L72>=70%,"Alta",L72>20%,"Média",L72<=20%,"Baixa")} -> #NAME? | O72: =J72 -> 7868.75 | P72: 0 | Q72: 8937.5 | R72: 6800 | S72: 0 | T72: 0
B73: Arquiteto de Soluções BI Senior | C73: =B73 -> Arquiteto de Soluções BI Senior | D73: Pleno | E73: =F73-G73 -> 9200 | F73: 11500 | G73: =F73*$G$9 -> 2300 | H73: =E73+(E73*IF(D73<>"",IF(D73<>"",VLOOKUP(D73,$D$3:$E$9,2,0)),"")) -> 11960 | I73: =_xlfn.MINIFS(Q73:T73,Q73:T73,">0",Q73:T73,"<>"&"") -> #NAME? | J73: =IF(SUM(Q73:T73)>0, AVERAGEIFS(Q73:T73, Q73:T73,">0",Q73:T73,"<>"&""), 0) -> 9728.4375 | K73: =_xlfn.MAXIFS(Q73:T73,Q73:T73,">0",Q73:T73,"<>"&"") -> #NAME? | L73: =(K73-I73)/I73 -> #NAME? | M73: {=_xlfn.IFS(L73>=70%,"Alta",L73>20%,"Média",L73<=20%,"Baixa")} -> #NAME? | O73: =J73 -> 9728.4375 | P73: 0 | Q73: 10456.875 | R73: 9000 | S73: 0 | T73: 0
B74: Arquiteto OutSystems Senior | C74: =B74& " " &D74 -> Arquiteto OutSystems Senior Pleno | D74: Pleno | E74: =F74-G74 -> 14800 | F74: 18500 | G74: =F74*$G$9 -> 3700 | H74: =E74+(E74*IF(D74<>"",IF(D74<>"",VLOOKUP(D74,$D$3:$E$9,2,0)),"")) -> 19240 | I74: =_xlfn.MINIFS(Q74:T74,Q74:T74,">0",Q74:T74,"<>"&"") -> #NAME? | J74: =IF(SUM(Q74:T74)>0, AVERAGEIFS(Q74:T74, Q74:T74,">0",Q74:T74,"<>"&""), 0) -> 13000 | K74: =_xlfn.MAXIFS(Q74:T74,Q74:T74,">0",Q74:T74,"<>"&"") -> #NAME? | L74: =(K74-I74)/I74 -> #NAME? | M74: {=_xlfn.IFS(L74>=70%,"Alta",L74>20%,"Média",L74<=20%,"Baixa")} -> #NAME? | O74: =J74 -> 13000 | P74: 0 | Q74: 17000 | R74: 9000 | S74: 0 | T74: 0
B75: Arquiteto SalesForce Senior | C75: =B75& " " &D75 -> Arquiteto SalesForce Senior Pleno | D75: Pleno | E75: =F75-G75 -> 10080 | F75: 12600 | G75: =F75*$G$9 -> 2520 | H75: =E75+(E75*IF(D75<>"",IF(D75<>"",VLOOKUP(D75,$D$3:$E$9,2,0)),"")) -> 13104 | I75: =_xlfn.MINIFS(Q75:T75,Q75:T75,">0",Q75:T75,"<>"&"") -> #NAME? | J75: =IF(SUM(Q75:T75)>0, AVERAGEIFS(Q75:T75, Q75:T75,">0",Q75:T75,"<>"&""), 0) -> 11025.985 | K75: =_xlfn.MAXIFS(Q75:T75,Q75:T75,">0",Q75:T75,"<>"&"") -> #NAME? | L75: =(K75-I75)/I75 -> #NAME? | M75: {=_xlfn.IFS(L75>=70%,"Alta",L75>20%,"Média",L75<=20%,"Baixa")} -> #NAME? | O75: =J75 -> 11025.985 | P75: 0 | Q75: 11051.97 | R75: 11000 | S75: 0 | T75: 0
B76: Arquiteto de Soluções | C76: =B76& " " &D76 -> Arquiteto de Soluções Especialista | D76: Especialista | E76: =F76-G76 -> 11600 | F76: 14500 | G76: =F76*$G$9 -> 2900 | H76: =F76+(F76*IF(D76<>"",IF(D76<>"",VLOOKUP(D76,$D$3:$F$9,2,0)),"")) -> 18850 | I76: =_xlfn.MINIFS(Q76:T76,Q76:T76,">0",Q76:T76,"<>"&"") -> #NAME? | J76: =IF(SUM(Q76:T76)>0, AVERAGEIFS(Q76:T76, Q76:T76,">0",Q76:T76,"<>"&""), 0) -> 6150 | K76: =_xlfn.MAXIFS(Q76:T76,Q76:T76,">0",Q76:T76,"<>"&"") -> #NAME? | L76: =(K76-I76)/I76 -> #NAME? | M76: {=_xlfn.IFS(L76>=70%,"Alta",L76>20%,"Média",L76<=20%,"Baixa")} -> #NAME? | N76: SIM | O76: =J76 -> 6150 | P76: 0 | Q76: 6800 | R76: 5500 | S76: 0 | T76: 0
B77: Arquiteto de Soluções | C77: =B77& " " &D77 -> Arquiteto de Soluções Júnior | D77: Júnior | E77: =F77-G77 -> 3920 | F77: 4900 | G77: =F77*$G$9 -> 980 | H77: =E77+(E77*IF(D77<>"",IF(D77<>"",VLOOKUP(D77,$D$3:$E$9,2,0)),"")) -> 5096 | I77: =_xlfn.MINIFS(Q77:T77,Q77:T77,">0",Q77:T77,"<>"&"") -> #NAME? | J77: =IF(SUM(Q77:T77)>0, AVERAGEIFS(Q77:T77, Q77:T77,">0",Q77:T77,"<>"&""), 0) -> 13964.25 | K77: =_xlfn.MAXIFS(Q77:T77,Q77:T77,">0",Q77:T77,"<>"&"") -> #NAME? | L77: =(K77-I77)/I77 -> #NAME? | M77: {=_xlfn.IFS(L77>=70%,"Alta",L77>20%,"Média",L77<=20%,"Baixa")} -> #NAME? | O77: =J77 -> 13964.25 | P77: 0 | Q77: 12928.5 | R77: 15000 | S77: 0 | T77: 0
B78: Arquiteto de Soluções | C78: =B78& " " &D78 -> Arquiteto de Soluções Pleno | D78: Pleno | E78: =F78-G78 -> 7200 | F78: 9000 | G78: =F78*$G$9 -> 1800 | H78: =F78+(F78*IF(D78<>"",IF(D78<>"",VLOOKUP(D78,$D$3:$F$9,2,0)),"")) -> 11700 | I78: =_xlfn.MINIFS(Q78:T78,Q78:T78,">0",Q78:T78,"<>"&"") -> #NAME? | J78: =IF(SUM(Q78:T78)>0, AVERAGEIFS(Q78:T78, Q78:T78,">0",Q78:T78,"<>"&""), 0) -> 7920 | K78: =_xlfn.MAXIFS(Q78:T78,Q78:T78,">0",Q78:T78,"<>"&"") -> #NAME? | L78: =(K78-I78)/I78 -> #NAME? | M78: {=_xlfn.IFS(L78>=70%,"Alta",L78>20%,"Média",L78<=20%,"Baixa")} -> #NAME? | N78: SIM | O78: =J78 -> 7920 | P78: 0 | Q78: 8840 | R78: 7000 | S78: 0 | T78: 0
B79: Arquiteto de Soluções | C79: =B79& " " &D79 -> Arquiteto de Soluções Sênior | D79: Sênior | E79: =F79-G79 -> 10080 | F79: 12600 | G79: =F79*$G$9 -> 2520 | H79: =F79+(F79*IF(D79<>"",IF(D79<>"",VLOOKUP(D79,$D$3:$F$9,2,0)),"")) -> 16380 | I79: =_xlfn.MINIFS(Q79:T79,Q79:T79,">0",Q79:T79,"<>"&"") -> #NAME? | J79: =IF(SUM(Q79:T79)>0, AVERAGEIFS(Q79:T79, Q79:T79,">0",Q79:T79,"<>"&""), 0) -> 11775 | K79: =_xlfn.MAXIFS(Q79:T79,Q79:T79,">0",Q79:T79,"<>"&"") -> #NAME? | L79: =(K79-I79)/I79 -> #NAME? | M79: {=_xlfn.IFS(L79>=70%,"Alta",L79>20%,"Média",L79<=20%,"Baixa")} -> #NAME? | N79: SIM | O79: =J79 -> 11775 | P79: 0 | Q79: 11050 | R79: 12500 | S79: 0 | T79: 0
B80: Cientista de Dados | C80: =B80& " " &D80 -> Cientista de Dados Especialista | D80: Especialista | E80: =F80-G80 -> 11360 | F80: 14200 | G80: =F80*$G$9 -> 2840 | H80: =F80+(F80*IF(D80<>"",IF(D80<>"",VLOOKUP(D80,$D$3:$F$9,2,0)),"")) -> 18460 | I80: =_xlfn.MINIFS(Q80:T80,Q80:T80,">0",Q80:T80,"<>"&"") -> #NAME? | J80: =IF(SUM(Q80:T80)>0, AVERAGEIFS(Q80:T80, Q80:T80,">0",Q80:T80,"<>"&""), 0) -> 11348.188 | K80: =_xlfn.MAXIFS(Q80:T80,Q80:T80,">0",Q80:T80,"<>"&"") -> #NAME? | L80: =(K80-I80)/I80 -> #NAME? | M80: {=_xlfn.IFS(L80>=70%,"Alta",L80>20%,"Média",L80<=20%,"Baixa")} -> #NAME? | N80: SIM | O80: =J80 -> 11348.188 | P80: 0 | Q80: 9696.375 | R80: 13000 | S80: 0 | T80: 0
B81: Cientista de Dados | C81: =B81& " " &D81 -> Cientista de Dados Júnior | D81: Júnior | E81: =F81-G81 -> 4160 | F81: 5200 | G81: =F81*$G$9 -> 1040 | H81: =F81+(F81*IF(D81<>"",IF(D81<>"",VLOOKUP(D81,$D$3:$F$9,2,0)),"")) -> 6760 | I81: =_xlfn.MINIFS(Q81:T81,Q81:T81,">0",Q81:T81,"<>"&"") -> #NAME? | J81: =IF(SUM(Q81:T81)>0, AVERAGEIFS(Q81:T81, Q81:T81,">0",Q81:T81,"<>"&""), 0) -> 4700 | K81: =_xlfn.MAXIFS(Q81:T81,Q81:T81,">0",Q81:T81,"<>"&"") -> #NAME? | L81: =(K81-I81)/I81 -> #NAME? | M81: {=_xlfn.IFS(L81>=70%,"Alta",L81>20%,"Média",L81<=20%,"Baixa")} -> #NAME? | N81: SIM | O81: =J81 -> 4700 | P81: 0 | Q81: 5100 | R81: 4300 | S81: 0 | T81: 0
B82: Cientista de Dados | C82: =B82& " " &D82 -> Cientista de Dados Pleno | D82: Pleno | E82: =F82-G82 -> 6560 | F82: 8200 | G82: =F82*$G$9 -> 1640 | H82: =F82+(F82*IF(D82<>"",IF(D82<>"",VLOOKUP(D82,$D$3:$F$9,2,0)),"")) -> 10660 | I82: =_xlfn.MINIFS(Q82:T82,Q82:T82,">0",Q82:T82,"<>"&"") -> #NAME? | J82: =IF(SUM(Q82:T82)>0, AVERAGEIFS(Q82:T82, Q82:T82,">0",Q82:T82,"<>"&""), 0) -> 7315 | K82: =_xlfn.MAXIFS(Q82:T82,Q82:T82,">0",Q82:T82,"<>"&"") -> #NAME? | L82: =(K82-I82)/I82 -> #NAME? | M82: {=_xlfn.IFS(L82>=70%,"Alta",L82>20%,"Média",L82<=20%,"Baixa")} -> #NAME? | N82: SIM | O82: =J82 -> 7315 | P82: 0 | Q82: 6630 | R82: 8000 | S82: 0 | T82: 0
B83: Cientista de Dados | C83: =B83& " " &D83 -> Cientista de Dados Sênior | D83: Sênior | E83: =F83-G83 -> 10000 | F83: 12500 | G83: =F83*$G$9 -> 2500 | H83: =F83+(F83*IF(D83<>"",IF(D83<>"",VLOOKUP(D83,$D$3:$F$9,2,0)),"")) -> 16250 | I83: =_xlfn.MINIFS(Q83:T83,Q83:T83,">0",Q83:T83,"<>"&"") -> #NAME? | J83: =IF(SUM(Q83:T83)>0, AVERAGEIFS(Q83:T83, Q83:T83,">0",Q83:T83,"<>"&""), 0) -> 9143.75 | K83: =_xlfn.MAXIFS(Q83:T83,Q83:T83,">0",Q83:T83,"<>"&"") -> #NAME? | L83: =(K83-I83)/I83 -> #NAME? | M83: {=_xlfn.IFS(L83>=70%,"Alta",L83>20%,"Média",L83<=20%,"Baixa")} -> #NAME? | N83: SIM | O83: =J83 -> 9143.75 | P83: 0 | Q83: 8287.5 | R83: 10000 | S83: 0 | T83: 0
B84: Desenvolvedor - PL-SQL/C#/Delphi - Especialista | C84: =B84 -> Desenvolvedor - PL-SQL/C#/Delphi - Especialista | D84: Pleno | E84: =F84-G84 -> 9200 | F84: 11500 | G84: =F84*$G$9 -> 2300 | H84: =E84+(E84*IF(D84<>"",IF(D84<>"",VLOOKUP(D84,$D$3:$E$9,2,0)),"")) -> 11960 | I84: =_xlfn.MINIFS(Q84:T84,Q84:T84,">0",Q84:T84,"<>"&"") -> #NAME? | J84: =IF(SUM(Q84:T84)>0, AVERAGEIFS(Q84:T84, Q84:T84,">0",Q84:T84,"<>"&""), 0) -> 10823.5 | K84: =_xlfn.MAXIFS(Q84:T84,Q84:T84,">0",Q84:T84,"<>"&"") -> #NAME? | L84: =(K84-I84)/I84 -> #NAME? | M84: {=_xlfn.IFS(L84>=70%,"Alta",L84>20%,"Média",L84<=20%,"Baixa")} -> #NAME? | O84: =J84 -> 10823.5 | P84: 0 | Q84: 10647 | R84: 11000 | S84: 0 | T84: 0
B85: Desenvolvedor - PL-SQL/C#/Delphi - Junior | C85: =B85 -> Desenvolvedor - PL-SQL/C#/Delphi - Junior | D85: Pleno | E85: =F85-G85 -> 3920 | F85: 4900 | G85: =F85*$G$9 -> 980 | H85: =E85+(E85*IF(D85<>"",IF(D85<>"",VLOOKUP(D85,$D$3:$E$9,2,0)),"")) -> 5096 | I85: =_xlfn.MINIFS(Q85:T85,Q85:T85,">0",Q85:T85,"<>"&"") -> #NAME? | J85: =IF(SUM(Q85:T85)>0, AVERAGEIFS(Q85:T85, Q85:T85,">0",Q85:T85,"<>"&""), 0) -> 4550 | K85: =_xlfn.MAXIFS(Q85:T85,Q85:T85,">0",Q85:T85,"<>"&"") -> #NAME? | L85: =(K85-I85)/I85 -> #NAME? | M85: {=_xlfn.IFS(L85>=70%,"Alta",L85>20%,"Média",L85<=20%,"Baixa")} -> #NAME? | O85: =J85 -> 4550 | P85: 0 | Q85: 5600 | R85: 3500 | S85: 0 | T85: 0
B86: Desenvolvedor - PL-SQL/C#/Delphi - Pleno | C86: =B86 -> Desenvolvedor - PL-SQL/C#/Delphi - Pleno | D86: Pleno | E86: =F86-G86 -> 6400 | F86: 8000 | G86: =F86*$G$9 -> 1600 | H86: =E86+(E86*IF(D86<>"",IF(D86<>"",VLOOKUP(D86,$D$3:$E$9,2,0)),"")) -> 8320 | I86: =_xlfn.MINIFS(Q86:T86,Q86:T86,">0",Q86:T86,"<>"&"") -> #NAME? | J86: =IF(SUM(Q86:T86)>0, AVERAGEIFS(Q86:T86, Q86:T86,">0",Q86:T86,"<>"&""), 0) -> 6240 | K86: =_xlfn.MAXIFS(Q86:T86,Q86:T86,">0",Q86:T86,"<>"&"") -> #NAME? | L86: =(K86-I86)/I86 -> #NAME? | M86: {=_xlfn.IFS(L86>=70%,"Alta",L86>20%,"Média",L86<=20%,"Baixa")} -> #NAME? | O86: =J86 -> 6240 | P86: 0 | Q86: 7280 | R86: 5200 | S86: 0 | T86: 0
B87: Desenvolvedor - PL-SQL/C#/Delphi - Senior | C87: =B87 -> Desenvolvedor - PL-SQL/C#/Delphi - Senior | D87: Pleno | E87: =F87-G87 -> 8000 | F87: 10000 | G87: =F87*$G$9 -> 2000 | H87: =E87+(E87*IF(D87<>"",IF(D87<>"",VLOOKUP(D87,$D$3:$E$9,2,0)),"")) -> 10400 | I87: =_xlfn.MINIFS(Q87:T87,Q87:T87,">0",Q87:T87,"<>"&"") -> #NAME? | J87: =IF(SUM(Q87:T87)>0, AVERAGEIFS(Q87:T87, Q87:T87,">0",Q87:T87,"<>"&""), 0) -> 9000 | K87: =_xlfn.MAXIFS(Q87:T87,Q87:T87,">0",Q87:T87,"<>"&"") -> #NAME? | L87: =(K87-I87)/I87 -> #NAME? | M87: {=_xlfn.IFS(L87>=70%,"Alta",L87>20%,"Média",L87<=20%,"Baixa")} -> #NAME? | O87: =J87 -> 9000 | P87: 0 | Q87: 9100 | R87: 8900 | S87: 0 | T87: 0
B88: Desenvolvedor ANDROID - Especialista | C88: =B88 -> Desenvolvedor ANDROID - Especialista | D88: Pleno | E88: =F88-G88 -> 10400 | F88: 13000 | G88: =F88*$G$9 -> 2600 | H88: =E88+(E88*IF(D88<>"",IF(D88<>"",VLOOKUP(D88,$D$3:$E$9,2,0)),"")) -> 13520 | I88: =_xlfn.MINIFS(Q88:T88,Q88:T88,">0",Q88:T88,"<>"&"") -> #NAME? | J88: =IF(SUM(Q88:T88)>0, AVERAGEIFS(Q88:T88, Q88:T88,">0",Q88:T88,"<>"&""), 0) -> 10788.312 | K88: =_xlfn.MAXIFS(Q88:T88,Q88:T88,">0",Q88:T88,"<>"&"") -> #NAME? | L88: =(K88-I88)/I88 -> #NAME? | M88: {=_xlfn.IFS(L88>=70%,"Alta",L88>20%,"Média",L88<=20%,"Baixa")} -> #NAME? | O88: =J88 -> 10788.312 | P88: 0 | Q88: 10076.625 | R88: 11500 | S88: 0 | T88: 0
B89: Desenvolvedor ANDROID - Junior | C89: =B89 -> Desenvolvedor ANDROID - Junior | D89: Pleno | E89: =F89-G89 -> 3920 | F89: 4900 | G89: =F89*$G$9 -> 980 | H89: =E89+(E89*IF(D89<>"",IF(D89<>"",VLOOKUP(D89,$D$3:$E$9,2,0)),"")) -> 5096 | I89: =_xlfn.MINIFS(Q89:T89,Q89:T89,">0",Q89:T89,"<>"&"") -> #NAME? | J89: =IF(SUM(Q89:T89)>0, AVERAGEIFS(Q89:T89, Q89:T89,">0",Q89:T89,"<>"&""), 0) -> 4400 | K89: =_xlfn.MAXIFS(Q89:T89,Q89:T89,">0",Q89:T89,"<>"&"") -> #NAME? | L89: =(K89-I89)/I89 -> #NAME? | M89: {=_xlfn.IFS(L89>=70%,"Alta",L89>20%,"Média",L89<=20%,"Baixa")} -> #NAME? | O89: =J89 -> 4400 | P89: 0 | Q89: 5300 | R89: 3500 | S89: 0 | T89: 0
B90: Desenvolvedor ANDROID - Pleno | C90: =B90 -> Desenvolvedor ANDROID - Pleno | D90: Pleno | E90: =F90-G90 -> 7200 | F90: 9000 | G90: =F90*$G$9 -> 1800 | H90: =E90+(E90*IF(D90<>"",IF(D90<>"",VLOOKUP(D90,$D$3:$E$9,2,0)),"")) -> 9360 | I90: =_xlfn.MINIFS(Q90:T90,Q90:T90,">0",Q90:T90,"<>"&"") -> #NAME? | J90: =IF(SUM(Q90:T90)>0, AVERAGEIFS(Q90:T90, Q90:T90,">0",Q90:T90,"<>"&""), 0) -> 6545 | K90: =_xlfn.MAXIFS(Q90:T90,Q90:T90,">0",Q90:T90,"<>"&"") -> #NAME? | L90: =(K90-I90)/I90 -> #NAME? | M90: {=_xlfn.IFS(L90>=70%,"Alta",L90>20%,"Média",L90<=20%,"Baixa")} -> #NAME? | O90: =J90 -> 6545 | P90: 0 | Q90: 6890 | R90: 6200 | S90: 0 | T90: 0
B91: Desenvolvedor ANDROID - Senior | C91: =B91 -> Desenvolvedor ANDROID - Senior | D91: Pleno | E91: =F91-G91 -> 9200 | F91: 11500 | G91: =F91*$G$9 -> 2300 | H91: =E91+(E91*IF(D91<>"",IF(D91<>"",VLOOKUP(D91,$D$3:$E$9,2,0)),"")) -> 11960 | I91: =_xlfn.MINIFS(Q91:T91,Q91:T91,">0",Q91:T91,"<>"&"") -> #NAME? | J91: =IF(SUM(Q91:T91)>0, AVERAGEIFS(Q91:T91, Q91:T91,">0",Q91:T91,"<>"&""), 0) -> 8906.25 | K91: =_xlfn.MAXIFS(Q91:T91,Q91:T91,">0",Q91:T91,"<>"&"") -> #NAME? | L91: =(K91-I91)/I91 -> #NAME? | M91: {=_xlfn.IFS(L91>=70%,"Alta",L91>20%,"Média",L91<=20%,"Baixa")} -> #NAME? | O91: =J91 -> 8906.25 | P91: 0 | Q91: 8612.5 | R91: 9200 | S91: 0 | T91: 0
B92: DBA - Administrador de Banco de Dados | C92: =B92& " " &D92 -> DBA - Administrador de Banco de Dados Especialista | D92: Especialista | E92: =F92-G92 -> 11200 | F92: 14000 | G92: =F92*$G$9 -> 2800 | H92: =F92+(F92*IF(D92<>"",IF(D92<>"",VLOOKUP(D92,$D$3:$F$9,2,0)),"")) -> 18200 | N92: SIM | O92: =J92 -> 0 | Q92: 0 | R92: 0
B93: DBA - Administrador de Banco de Dados | C93: =B93& " " &D93 -> DBA - Administrador de Banco de Dados Júnior | D93: Júnior | E93: =F93-G93 -> 3200 | F93: 4000 | G93: =F93*$G$9 -> 800 | H93: =F93+(F93*IF(D93<>"",IF(D93<>"",VLOOKUP(D93,$D$3:$F$9,2,0)),"")) -> 5200 | N93: SIM | O93: =J93 -> 0 | Q93: 0 | R93: 0
B94: DBA - Administrador de Banco de Dados | C94: =B94& " " &D94 -> DBA - Administrador de Banco de Dados Pleno | D94: Pleno | E94: =F94-G94 -> 5200 | F94: 6500 | G94: =F94*$G$9 -> 1300 | H94: =F94+(F94*IF(D94<>"",IF(D94<>"",VLOOKUP(D94,$D$3:$F$9,2,0)),"")) -> 8450 | N94: SIM | O94: =J94 -> 0 | Q94: 0 | R94: 0
B95: DBA - Administrador de Banco de Dados | C95: =B95& " " &D95 -> DBA - Administrador de Banco de Dados Sênior | D95: Sênior | E95: =F95-G95 -> 7200 | F95: 9000 | G95: =F95*$G$9 -> 1800 | H95: =F95+(F95*IF(D95<>"",IF(D95<>"",VLOOKUP(D95,$D$3:$F$9,2,0)),"")) -> 11700 | N95: SIM | O95: =J95 -> 0 | Q95: 0 | R95: 0
B96: Desenvolvedor BackEnd | C96: =B96& " " &D96 -> Desenvolvedor BackEnd Especialista | D96: Especialista | E96: =F96-G96 -> 10400 | F96: 13000 | G96: =F96*$G$9 -> 2600 | H96: =F96+(F96*IF(D96<>"",IF(D96<>"",VLOOKUP(D96,$D$3:$F$9,2,0)),"")) -> 16900 | I96: =_xlfn.MINIFS(Q96:T96,Q96:T96,">0",Q96:T96,"<>"&"") -> #NAME? | J96: =IF(SUM(Q96:T96)>0, AVERAGEIFS(Q96:T96, Q96:T96,">0",Q96:T96,"<>"&""), 0) -> 11703.75 | K96: =_xlfn.MAXIFS(Q96:T96,Q96:T96,">0",Q96:T96,"<>"&"") -> #NAME? | L96: =(K96-I96)/I96 -> #NAME? | M96: {=_xlfn.IFS(L96>=70%,"Alta",L96>20%,"Média",L96<=20%,"Baixa")} -> #NAME? | N96: SIM | O96: =J96 -> 11703.75 | P96: 0 | Q96: 11407.5 | R96: 12000 | S96: 0 | T96: 0
B97: Desenvolvedor BackEnd | C97: =B97& " " &D97 -> Desenvolvedor BackEnd Júnior | D97: Júnior | E97: =F97-G97 -> 3920 | F97: 4900 | G97: =F97*$G$9 -> 980 | H97: =F97+(F97*IF(D97<>"",IF(D97<>"",VLOOKUP(D97,$D$3:$F$9,2,0)),"")) -> 6370 | I97: =_xlfn.MINIFS(Q97:T97,Q97:T97,">0",Q97:T97,"<>"&"") -> #NAME? | J97: =IF(SUM(Q97:T97)>0, AVERAGEIFS(Q97:T97, Q97:T97,">0",Q97:T97,"<>"&""), 0) -> 4750 | K97: =_xlfn.MAXIFS(Q97:T97,Q97:T97,">0",Q97:T97,"<>"&"") -> #NAME? | L97: =(K97-I97)/I97 -> #NAME? | M97: {=_xlfn.IFS(L97>=70%,"Alta",L97>20%,"Média",L97<=20%,"Baixa")} -> #NAME? | N97: SIM | O97: =J97 -> 4750 | P97: 0 | Q97: 6000 | R97: 3500 | S97: 0 | T97: 0
B98: Desenvolvedor BackEnd | C98: =B98& " " &D98 -> Desenvolvedor BackEnd Pleno | D98: Pleno | E98: =F98-G98 -> 7200 | F98: 9000 | G98: =F98*$G$9 -> 1800 | H98: =F98+(F98*IF(D98<>"",IF(D98<>"",VLOOKUP(D98,$D$3:$F$9,2,0)),"")) -> 11700 | I98: =_xlfn.MINIFS(Q98:T98,Q98:T98,">0",Q98:T98,"<>"&"") -> #NAME? | J98: =IF(SUM(Q98:T98)>0, AVERAGEIFS(Q98:T98, Q98:T98,">0",Q98:T98,"<>"&""), 0) -> 7000 | K98: =_xlfn.MAXIFS(Q98:T98,Q98:T98,">0",Q98:T98,"<>"&"") -> #NAME? | L98: =(K98-I98)/I98 -> #NAME? | M98: {=_xlfn.IFS(L98>=70%,"Alta",L98>20%,"Média",L98<=20%,"Baixa")} -> #NAME? | N98: SIM | O98: =J98 -> 7000 | P98: 0 | Q98: 7800 | R98: 6200 | S98: 0 | T98: 0
B99: Desenvolvedor BackEnd | C99: =B99& " " &D99 -> Desenvolvedor BackEnd Sênior | D99: Sênior | E99: =F99-G99 -> 8800 | F99: 11000 | G99: =F99*$G$9 -> 2200 | H99: =F99+(F99*IF(D99<>"",IF(D99<>"",VLOOKUP(D99,$D$3:$F$9,2,0)),"")) -> 14300 | I99: =_xlfn.MINIFS(Q99:T99,Q99:T99,">0",Q99:T99,"<>"&"") -> #NAME? | J99: =IF(SUM(Q99:T99)>0, AVERAGEIFS(Q99:T99, Q99:T99,">0",Q99:T99,"<>"&""), 0) -> 9625 | K99: =_xlfn.MAXIFS(Q99:T99,Q99:T99,">0",Q99:T99,"<>"&"") -> #NAME? | L99: =(K99-I99)/I99 -> #NAME? | M99: {=_xlfn.IFS(L99>=70%,"Alta",L99>20%,"Média",L99<=20%,"Baixa")} -> #NAME? | N99: SIM | O99: =J99 -> 9625 | P99: 0 | Q99: 9750 | R99: 9500 | S99: 0 | T99: 0
B100: Desenvolvedor FrontEnd | C100: =B100& " " &D100 -> Desenvolvedor FrontEnd Especialista | D100: Especialista | E100: =F100-G100 -> 10400 | F100: 13000 | G100: =F100*$G$9 -> 2600 | H100: =F100+(F100*IF(D100<>"",IF(D100<>"",VLOOKUP(D100,$D$3:$F$9,2,0)),"")) -> 16900 | I100: =_xlfn.MINIFS(Q100:T100,Q100:T100,">0",Q100:T100,"<>"&"") -> #NAME? | J100: =IF(SUM(Q100:T100)>0, AVERAGEIFS(Q100:T100, Q100:T100,">0",Q100:T100,"<>"&""), 0) -> 11038.312 | K100: =_xlfn.MAXIFS(Q100:T100,Q100:T100,">0",Q100:T100,"<>"&"") -> #NAME? | L100: =(K100-I100)/I100 -> #NAME? | M100: {=_xlfn.IFS(L100>=70%,"Alta",L100>20%,"Média",L100<=20%,"Baixa")} -> #NAME? | N100: SIM | O100: =J100 -> 11038.312 | P100: 0 | Q100: 10076.625 | R100: 12000 | S100: 0 | T100: 0
B101: Desenvolvedor FrontEnd | C101: =B101& " " &D101 -> Desenvolvedor FrontEnd Júnior | D101: Júnior | E101: =F101-G101 -> 3920 | F101: 4900 | G101: =F101*$G$9 -> 980 | H101: =F101+(F101*IF(D101<>"",IF(D101<>"",VLOOKUP(D101,$D$3:$F$9,2,0)),"")) -> 6370 | I101: =_xlfn.MINIFS(Q101:T101,Q101:T101,">0",Q101:T101,"<>"&"") -> #NAME? | J101: =IF(SUM(Q101:T101)>0, AVERAGEIFS(Q101:T101, Q101:T101,">0",Q101:T101,"<>"&""), 0) -> 4400 | K101: =_xlfn.MAXIFS(Q101:T101,Q101:T101,">0",Q101:T101,"<>"&"") -> #NAME? | L101: =(K101-I101)/I101 -> #NAME? | M101: {=_xlfn.IFS(L101>=70%,"Alta",L101>20%,"Média",L101<=20%,"Baixa")} -> #NAME? | N101: SIM | O101: =J101 -> 4400 | P101: 0 | Q101: 5300 | R101: 3500 | S101: 0 | T101: 0
B102: Desenvolvedor FrontEnd | C102: =B102& " " &D102 -> Desenvolvedor FrontEnd Pleno | D102: Pleno | E102: =F102-G102 -> 7200 | F102: 9000 | G102: =F102*$G$9 -> 1800 | H102: =F102+(F102*IF(D102<>"",IF(D102<>"",VLOOKUP(D102,$D$3:$F$9,2,0)),"")) -> 11700 | I102: =_xlfn.MINIFS(Q102:T102,Q102:T102,">0",Q102:T102,"<>"&"") -> #NAME? | J102: =IF(SUM(Q102:T102)>0, AVERAGEIFS(Q102:T102, Q102:T102,">0",Q102:T102,"<>"&""), 0) -> 6545 | K102: =_xlfn.MAXIFS(Q102:T102,Q102:T102,">0",Q102:T102,"<>"&"") -> #NAME? | L102: =(K102-I102)/I102 -> #NAME? | M102: {=_xlfn.IFS(L102>=70%,"Alta",L102>20%,"Média",L102<=20%,"Baixa")} -> #NAME? | N102: SIM | O102: =J102 -> 6545 | P102: 0 | Q102: 6890 | R102: 6200 | S102: 0 | T102: 0
B103: Desenvolvedor FrontEnd | C103: =B103& " " &D103 -> Desenvolvedor FrontEnd Sênior | D103: Sênior | E103: =F103-G103 -> 8800 | F103: 11000 | G103: =F103*$G$9 -> 2200 | H103: =F103+(F103*IF(D103<>"",IF(D103<>"",VLOOKUP(D103,$D$3:$F$9,2,0)),"")) -> 14300 | I103: =_xlfn.MINIFS(Q103:T103,Q103:T103,">0",Q103:T103,"<>"&"") -> #NAME? | J103: =IF(SUM(Q103:T103)>0, AVERAGEIFS(Q103:T103, Q103:T103,">0",Q103:T103,"<>"&""), 0) -> 9056.25 | K103: =_xlfn.MAXIFS(Q103:T103,Q103:T103,">0",Q103:T103,"<>"&"") -> #NAME? | L103: =(K103-I103)/I103 -> #NAME? | M103: {=_xlfn.IFS(L103>=70%,"Alta",L103>20%,"Média",L103<=20%,"Baixa")} -> #NAME? | N103: SIM | O103: =J103 -> 9056.25 | P103: 0 | Q103: 8612.5 | R103: 9500 | S103: 0 | T103: 0
B104: Desenvolvedor FullStack | C104: =B104& " " &D104 -> Desenvolvedor FullStack Especialista | D104: Especialista | E104: =F104-G104 -> 10880 | F104: 13600 | G104: =F104*$G$9 -> 2720 | H104: =F104+(F104*IF(D104<>"",IF(D104<>"",VLOOKUP(D104,$D$3:$F$9,2,0)),"")) -> 17680 | I104: =_xlfn.MINIFS(Q104:T104,Q104:T104,">0",Q104:T104,"<>"&"") -> #NAME? | J104: =IF(SUM(Q104:T104)>0, AVERAGEIFS(Q104:T104, Q104:T104,">0",Q104:T104,"<>"&""), 0) -> 12274.125 | K104: =_xlfn.MAXIFS(Q104:T104,Q104:T104,">0",Q104:T104,"<>"&"") -> #NAME? | L104: =(K104-I104)/I104 -> #NAME? | M104: {=_xlfn.IFS(L104>=70%,"Alta",L104>20%,"Média",L104<=20%,"Baixa")} -> #NAME? | N104: SIM | O104: =J104 -> 12274.125 | P104: 0 | Q104: 12548.25 | R104: 12000 | S104: 0 | T104: 0
...

Sheet Rate Card CLT
E2: RESUMO | F2: Base horas mês | G2: 176 | I2: $ salários + encargos | J2: =SUBTOTAL(9,J9:J50012) -> 2773439.8 | L2: FGTS | M2: 0.08 | N2: Nº colab bilable | O2: =COUNTIF(E9:E5012, "Sim") -> 151 | P2: Valor convênio | Q2: 600 | R2: INSS+RAT+TERC | S2: 0.275 | W2: Ajustes do cálculo CLT que precisamos ajustar em todas tabelas
C3: modelo | D3: CLT | F3: % Comissão vend. | G3: 0.03 | I3: $ faturamento | J3: =SUBTOTAL(9,T9:T50012) -> 5284789.6 | L3: FGTS Multa | M3: 0.4 | N3: Nº colab no bilable | O3: =COUNTIF(E9:E5012, "Não") -> 0 | P3: Valor comissão | Q3: =SUM(R9:R54) -> 36444.547 | W3: Ok
C4: Híbrido | D4: Não | F4: % Imposto NF | G4: 0.23 | I4: $ Custos | J4: =SUBTOTAL(9,K9:K5012)+Q3 -> 4025386 | L4: INSS | M4: 0.09 | N4: % Rateio no Bilable | O4: 0 | P4: Soma de horas | Q4: =SUM(D9:D5012) -> 26576 | W4: Incluídos
C5: Perc.Hib. | D5: 0 | G5: 0.85 | I5: $ lucratividade | J5: =J3-J4 -> 1259403.6 | L5: Ticket Rest. Dia | M5: 25 | N5: Total Billable | O5: =L12 -> 113.61332 | P5: hora média | Q5: =J3/Q4 -> 198.85572 | W5: Alterados
F6: Taxa de risco | G6: 0 | I6: % lucro real | J6: =J5/J3 -> 0.23830724 | L6: Tarifa média hr. | M6: =SUM(T9:T5012)/SUM(D9:D5012) -> 198.85572 | N6: Total No Bilable | O6: =SUMIF(E9:E5012,"Não",Q9:Q5012) -> 0 | W6: Remover
B7: CONFIGURAÇÃO EQUIPE | C7: CONFIG RECURSO | F7: C U S T O S C O M C O L A B O R A D O R E S | M7: T A R I F A / F A T U R A M E N T O | V7: C U S T O S C L T | AI7: IMPOSTOS | AJ7: LUCRATIVIDADE
B8: Necessidade cliente | C8: Reg | D8: H.trab | E8: Billable | F8: $ Negociado/salário | G8: $ salário cheio | H8: Vale Refeição/Alimentação | I8: $ Salário real | J8: $ Custo Colab | K8: $ Custo colab + Imp | L8: Custo hora | M8: $ Tarifa negociada | N8: Markup | O8: $ Risco | P8: $ Tarifa | Q8: $ Tar. calculada | R8: $ Comissão | S8: Loc. Equip. | T8: $ Tarifa bilable | U8: Valor hora | V8: FGTS | W8: FGTS multa | X8: Férias | Y8: 1/3 férias | Z8: 13º salário | AA8: INSS+RAT+TERC | AB8: FGTS sobre 13º e Férias | AC8: INSS+RAT+Terc (13º e Fér) | AD8: Aviso Remuner | AE8: FGTS Sobre Aviso | AF8: INSS | AG8: Convênio | AH8: $ Total Encargos | AI8: Imposto Nota | AJ8: $ lucro | AK8: % Lucro | AL8: Marg Contrib
B9: Agilista Especialista | C9: CLT | D9: 176 | E9: Sim | F9: 0 | G9: =IF(F9>0,F9, IF(B9<>"", IF(C9="CLT",VLOOKUP(B9,'Lista Profissionais'!$C$11:$H$348,3,0), VLOOKUP(B9,'Lista Profissionais'!$C$11:$H$348,6,0)), 0)) -> 10800 | H9: =IF(B9<>"", IF(C9="CLT", 22*$M$5 + (G9*'Lista Profissionais'!$G$9),0),0) -> 2710 | I9: =(G9/$G$2)*D9 -> 10800 | J9: =I9+AH9 -> 23273.5 | K9: =J9+S9+AI9 -> 33473.46 | L9: =IF(D9>0,J9/D9,0) -> 132.2358 | N9: 0 | O9: =J9*$G$6 -> 0 | P9: =IF(M9>0,M9, J9*(1+$G$5)) -> 43055.975 | Q9: =(P9+O9) -> 43055.975 | R9: =IF(E9="Sim", Q9*$G$3,0) -> 1291.6792 | S9: 0 | T9: =IF($D$4="Sim",(IF(E9="Não",0,(Q9+(Q9*$O$4)+R9+S9)*$D$5)+Q9), IF(E9="Não",0,Q9+(Q9*$O$4)+R9+S9 )) -> 44347.654 | U9: =IF(D9>0,T9/D9,0) -> 251.97531 | V9: =IF(C9="CLT", I9*$M$2, 0) -> 864 | W9: =IF(C9="CLT", V9*$M$3, 0) -> 345.6 | X9: =IF(C9="CLT", I9/12, 0) -> 900 | Y9: =IF(C9="CLT", X9/3, 0) -> 300 | Z9: =IF(C9="CLT", I9/12, 0) -> 900 | AA9: =IF(C9="CLT", I9*$S$2,0) -> 2970 | AB9: =IF(C9="CLT", SUM(X9:Z9) * $M$2,0) -> 168 | AC9: =IF(C9="CLT", SUM(X9:Z9)*$S$2,0) -> 577.5 | AD9: =IF(C9="CLT", I9/30*3, 0) -> 1080 | AE9: =IF(C9="CLT", AD9*$M$2, 0) -> 86.4 | AF9: =IF(C9="CLT", I9*$M$4, 0) -> 972 | AG9: =IF(B9<>"", IF(C9="CLT", $Q$2, 0),0) -> 600 | AH9: =SUM(V9:AG9)+H9 -> 12473.5 | AI9: =IF(E9="Sim", T9*$G$4, 0) -> 10199.96 | AJ9: =T9-AI9-J9-R9 -> 9582.5145 | AK9: =(IF(AJ9>0,AJ9/T9,0)) -> 0.21607715 | AL9: =(IF(AJ9>0,AJ9/(T9-AI9),0)) -> 0.28061967
B10: Agilista - Junior Júnior | C10: CLT | D10: 176 | E10: Sim | F10: 0 | G10: =IF(F10>0,F10, IF(B10<>"", IF(C10="CLT",VLOOKUP(B10,'Lista Profissionais'!$C$11:$H$348,3,0), VLOOKUP(B10,'Lista Profissionais'!$C$11:$H$348,6,0)), 0)) -> 3920 | H10: =IF(B10<>"", IF(C10="CLT", 22*$M$5 + (G10*'Lista Profissionais'!$G$9),0),0) -> 1334 | I10: =(G10/$G$2)*D10 -> 3920 | J10: =I10+AH10 -> 9180.0111 | K10: =J10+S10+AI10 -> 13203.289 | L10: =IF(D10>0,J10/D10,0) -> 52.159154 | N10: 0 | O10: =J10*$G$6 -> 0 | P10: =IF(M10>0,M10, J10*(1+$G$5)) -> 16983.021 | Q10: =(P10+O10) -> 16983.021 | R10: =IF(E10="Sim", Q10*$G$3,0) -> 509.49062 | S10: 0 | T10: =IF($D$4="Sim",(IF(E10="Não",0,(Q10+(Q10*$O$4)+R10+S10)*$D$5)+Q10), IF(E10="Não",0,Q10+(Q10*$O$4)+R10+S10 )) -> 17492.511 | U10: =IF(D10>0,T10/D10,0) -> 99.389268 | V10: =IF(C10="CLT", I10*$M$2, 0) -> 313.6 | W10: =IF(C10="CLT", V10*$M$3, 0) -> 125.44 | X10: =IF(C10="CLT", I10/12, 0) -> 326.66667 | Y10: =IF(C10="CLT", X10/3, 0) -> 108.88889 | Z10: =IF(C10="CLT", I10/12, 0) -> 326.66667 | AA10: =IF(C10="CLT", I10*$S$2,0) -> 1078 | AB10: =IF(C10="CLT", SUM(X10:Z10) * $M$2,0) -> 60.977778 | AC10: =IF(C10="CLT", SUM(X10:Z10)*$S$2,0) -> 209.61111 | AD10: =IF(C10="CLT", I10/30*3, 0) -> 392 | AE10: =IF(C10="CLT", AD10*$M$2, 0) -> 31.36 | AF10: =IF(C10="CLT", I10*$M$4, 0) -> 352.8 | AG10: =IF(B10<>"", IF(C10="CLT", $Q$2, 0),0) -> 600 | AH10: =SUM(V10:AG10)+H10 -> 5260.0111 | AI10: =IF(E10="Sim", T10*$G$4, 0) -> 4023.2776 | AJ10: =T10-AI10-J10-R10 -> 3779.7319 | AK10: =(IF(AJ10>0,AJ10/T10,0)) -> 0.21607715 | AL10: =(IF(AJ10>0,AJ10/(T10-AI10),0)) -> 0.28061967
B11: Agilista Pleno | C11: CLT | D11: 176 | E11: Sim | F11: 0 | G11: =IF(F11>0,F11, IF(B11<>"", IF(C11="CLT",VLOOKUP(B11,'Lista Profissionais'!$C$11:$H$348,3,0), VLOOKUP(B11,'Lista Profissionais'!$C$11:$H$348,6,0)), 0)) -> 6320 | H11: =IF(B11<>"", IF(C11="CLT", 22*$M$5 + (G11*'Lista Profissionais'!$G$9),0),0) -> 1814 | I11: =(G11/$G$2)*D11 -> 6320 | J11: =I11+AH11 -> 14096.344 | K11: =J11+S11+AI11 -> 20274.279 | L11: =IF(D11>0,J11/D11,0) -> 80.092866 | N11: 0 | O11: =J11*$G$6 -> 0 | P11: =IF(M11>0,M11, J11*(1+$G$5)) -> 26078.237 | Q11: =(P11+O11) -> 26078.237 | R11: =IF(E11="Sim", Q11*$G$3,0) -> 782.34712 | S11: 0 | T11: =IF($D$4="Sim",(IF(E11="Não",0,(Q11+(Q11*$O$4)+R11+S11)*$D$5)+Q11), IF(E11="Não",0,Q11+(Q11*$O$4)+R11+S11 )) -> 26860.584 | U11: =IF(D11>0,T11/D11,0) -> 152.61696 | V11: =IF(C11="CLT", I11*$M$2, 0) -> 505.6 | W11: =IF(C11="CLT", V11*$M$3, 0) -> 202.24 | X11: =IF(C11="CLT", I11/12, 0) -> 526.66667 | Y11: =IF(C11="CLT", X11/3, 0) -> 175.55556 | Z11: =IF(C11="CLT", I11/12, 0) -> 526.66667 | AA11: =IF(C11="CLT", I11*$S$2,0) -> 1738 | AB11: =IF(C11="CLT", SUM(X11:Z11) * $M$2,0) -> 98.311111 | AC11: =IF(C11="CLT", SUM(X11:Z11)*$S$2,0) -> 337.94444 | AD11: =IF(C11="CLT", I11/30*3, 0) -> 632 | AE11: =IF(C11="CLT", AD11*$M$2, 0) -> 50.56 | AF11: =IF(C11="CLT", I11*$M$4, 0) -> 568.8 | AG11: =IF(B11<>"", IF(C11="CLT", $Q$2, 0),0) -> 600 | AH11: =SUM(V11:AG11)+H11 -> 7776.3444 | AI11: =IF(E11="Sim", T11*$G$4, 0) -> 6177.9344 | AJ11: =T11-AI11-J11-R11 -> 5803.9584 | AK11: =(IF(AJ11>0,AJ11/T11,0)) -> 0.21607715 | AL11: =(IF(AJ11>0,AJ11/(T11-AI11),0)) -> 0.28061967
B12: Agilista Sênior | C12: CLT | D12: 176 | E12: Sim | F12: 0 | G12: =IF(F12>0,F12, IF(B12<>"", IF(C12="CLT",VLOOKUP(B12,'Lista Profissionais'!$C$11:$H$348,3,0), VLOOKUP(B12,'Lista Profissionais'!$C$11:$H$348,6,0)), 0)) -> 9200 | H12: =IF(B12<>"", IF(C12="CLT", 22*$M$5 + (G12*'Lista Profissionais'!$G$9),0),0) -> 2390 | I12: =(G12/$G$2)*D12 -> 9200 | J12: =I12+AH12 -> 19995.944 | K12: =J12+S12+AI12 -> 28759.467 | L12: =IF(D12>0,J12/D12,0) -> 113.61332 | N12: 0 | O12: =J12*$G$6 -> 0 | P12: =IF(M12>0,M12, J12*(1+$G$5)) -> 36992.497 | Q12: =(P12+O12) -> 36992.497 | R12: =IF(E12="Sim", Q12*$G$3,0) -> 1109.7749 | S12: 0 | T12: =IF($D$4="Sim",(IF(E12="Não",0,(Q12+(Q12*$O$4)+R12+S12)*$D$5)+Q12), IF(E12="Não",0,Q12+(Q12*$O$4)+R12+S12 )) -> 38102.272 | U12: =IF(D12>0,T12/D12,0) -> 216.49018 | V12: =IF(C12="CLT", I12*$M$2, 0) -> 736 | W12: =IF(C12="CLT", V12*$M$3, 0) -> 294.4 | X12: =IF(C12="CLT", I12/12, 0) -> 766.66667 | Y12: =IF(C12="CLT", X12/3, 0) -> 255.55556 | Z12: =IF(C12="CLT", I12/12, 0) -> 766.66667 | AA12: =IF(C12="CLT", I12*$S$2,0) -> 2530 | AB12: =IF(C12="CLT", SUM(X12:Z12) * $M$2,0) -> 143.11111 | AC12: =IF(C12="CLT", SUM(X12:Z12)*$S$2,0) -> 491.94444 | AD12: =IF(C12="CLT", I12/30*3, 0) -> 920 | AE12: =IF(C12="CLT", AD12*$M$2, 0) -> 73.6 | AF12: =IF(C12="CLT", I12*$M$4, 0) -> 828 | AG12: =IF(B12<>"", IF(C12="CLT", $Q$2, 0),0) -> 600 | AH12: =SUM(V12:AG12)+H12 -> 10795.944 | AI12: =IF(E12="Sim", T12*$G$4, 0) -> 8763.5226 | AJ12: =T12-AI12-J12-R12 -> 8233.0302 | AK12: =(IF(AJ12>0,AJ12/T12,0)) -> 0.21607715 | AL12: =(IF(AJ12>0,AJ12/(T12-AI12),0)) -> 0.28061967
B13: Analista de Dados/ BI Especialista | C13: CLT | D13: 176 | E13: Sim | F13: 0 | G13: =IF(F13>0,F13, IF(B13<>"", IF(C13="CLT",VLOOKUP(B13,'Lista Profissionais'!$C$11:$H$348,3,0), VLOOKUP(B13,'Lista Profissionais'!$C$11:$H$348,6,0)), 0)) -> 8800 | H13: =IF(B13<>"", IF(C13="CLT", 22*$M$5 + (G13*'Lista Profissionais'!$G$9),0),0) -> 2310 | I13: =(G13/$G$2)*D13 -> 8800 | J13: =I13+AH13 -> 19176.556 | K13: =J13+S13+AI13 -> 27580.969 | L13: =IF(D13>0,J13/D13,0) -> 108.9577 | N13: 0 | O13: =J13*$G$6 -> 0 | P13: =IF(M13>0,M13, J13*(1+$G$5)) -> 35476.628 | Q13: =(P13+O13) -> 35476.628 | R13: =IF(E13="Sim", Q13*$G$3,0) -> 1064.2988 | S13: 0 | T13: =IF($D$4="Sim",(IF(E13="Não",0,(Q13+(Q13*$O$4)+R13+S13)*$D$5)+Q13), IF(E13="Não",0,Q13+(Q13*$O$4)+R13+S13 )) -> 36540.927 | U13: =IF(D13>0,T13/D13,0) -> 207.6189 | V13: =IF(C13="CLT", I13*$M$2, 0) -> 704 | W13: =IF(C13="CLT", V13*$M$3, 0) -> 281.6 | X13: =IF(C13="CLT", I13/12, 0) -> 733.33333 | Y13: =IF(C13="CLT", X13/3, 0) -> 244.44444 | Z13: =IF(C13="CLT", I13/12, 0) -> 733.33333 | AA13: =IF(C13="CLT", I13*$S$2,0) -> 2420 | AB13: =IF(C13="CLT", SUM(X13:Z13) * $M$2,0) -> 136.88889 | AC13: =IF(C13="CLT", SUM(X13:Z13)*$S$2,0) -> 470.55556 | AD13: =IF(C13="CLT", I13/30*3, 0) -> 880 | AE13: =IF(C13="CLT", AD13*$M$2, 0) -> 70.4 | AF13: =IF(C13="CLT", I13*$M$4, 0) -> 792 | AG13: =IF(B13<>"", IF(C13="CLT", $Q$2, 0),0) -> 600 | AH13: =SUM(V13:AG13)+H13 -> 10376.556 | AI13: =IF(E13="Sim", T13*$G$4, 0) -> 8404.4131 | AJ13: =T13-AI13-J13-R13 -> 7895.6591 | AK13: =(IF(AJ13>0,AJ13/T13,0)) -> 0.21607715 | AL13: =(IF(AJ13>0,AJ13/(T13-AI13),0)) -> 0.28061967
B14: Analista de Dados/ BI Júnior | C14: CLT | D14: 176 | E14: Sim | F14: 0 | G14: =IF(F14>0,F14, IF(B14<>"", IF(C14="CLT",VLOOKUP(B14,'Lista Profissionais'!$C$11:$H$348,3,0), VLOOKUP(B14,'Lista Profissionais'!$C$11:$H$348,6,0)), 0)) -> 3360 | H14: =IF(B14<>"", IF(C14="CLT", 22*$M$5 + (G14*'Lista Profissionais'!$G$9),0),0) -> 1222 | I14: =(G14/$G$2)*D14 -> 3360 | J14: =I14+AH14 -> 8032.8667 | K14: =J14+S14+AI14 -> 11553.391 | L14: =IF(D14>0,J14/D14,0) -> 45.641288 | N14: 0 | O14: =J14*$G$6 -> 0 | P14: =IF(M14>0,M14, J14*(1+$G$5)) -> 14860.803 | Q14: =(P14+O14) -> 14860.803 | R14: =IF(E14="Sim", Q14*$G$3,0) -> 445.8241 | S14: 0 | T14: =IF($D$4="Sim",(IF(E14="Não",0,(Q14+(Q14*$O$4)+R14+S14)*$D$5)+Q14), IF(E14="Não",0,Q14+(Q14*$O$4)+R14+S14 )) -> 15306.627 | U14: =IF(D14>0,T14/D14,0) -> 86.969474 | V14: =IF(C14="CLT", I14*$M$2, 0) -> 268.8 | W14: =IF(C14="CLT", V14*$M$3, 0) -> 107.52 | X14: =IF(C14="CLT", I14/12, 0) -> 280 | Y14: =IF(C14="CLT", X14/3, 0) -> 93.333333 | Z14: =IF(C14="CLT", I14/12, 0) -> 280 | AA14: =IF(C14="CLT", I14*$S$2,0) -> 924 | AB14: =IF(C14="CLT", SUM(X14:Z14) * $M$2,0) -> 52.266667 | AC14: =IF(C14="CLT", SUM(X14:Z14)*$S$2,0) -> 179.66667 | AD14: =IF(C14="CLT", I14/30*3, 0) -> 336 | AE14: =IF(C14="CLT", AD14*$M$2, 0) -> 26.88 | AF14: =IF(C14="CLT", I14*$M$4, 0) -> 302.4 | AG14: =IF(B14<>"", IF(C14="CLT", $Q$2, 0),0) -> 600 | AH14: =SUM(V14:AG14)+H14 -> 4672.8667 | AI14: =IF(E14="Sim", T14*$G$4, 0) -> 3520.5243 | AJ14: =T14-AI14-J14-R14 -> 3307.4124 | AK14: =(IF(AJ14>0,AJ14/T14,0)) -> 0.21607715 | AL14: =(IF(AJ14>0,AJ14/(T14-AI14),0)) -> 0.28061967
B15: Analista de Dados/ BI Pleno | C15: CLT | D15: 176 | E15: Sim | F15: 0 | G15: =IF(F15>0,F15, IF(B15<>"", IF(C15="CLT",VLOOKUP(B15,'Lista Profissionais'!$C$11:$H$348,3,0), VLOOKUP(B15,'Lista Profissionais'!$C$11:$H$348,6,0)), 0)) -> 6000 | H15: =IF(B15<>"", IF(C15="CLT", 22*$M$5 + (G15*'Lista Profissionais'!$G$9),0),0) -> 1750 | I15: =(G15/$G$2)*D15 -> 6000 | J15: =I15+AH15 -> 13440.833 | K15: =J15+S15+AI15 -> 19331.48 | L15: =IF(D15>0,J15/D15,0) -> 76.368371 | N15: 0 | O15: =J15*$G$6 -> 0 | P15: =IF(M15>0,M15, J15*(1+$G$5)) -> 24865.542 | Q15: =(P15+O15) -> 24865.542 | R15: =IF(E15="Sim", Q15*$G$3,0) -> 745.96625 | S15: 0 | T15: =IF($D$4="Sim",(IF(E15="Não",0,(Q15+(Q15*$O$4)+R15+S15)*$D$5)+Q15), IF(E15="Não",0,Q15+(Q15*$O$4)+R15+S15 )) -> 25611.508 | U15: =IF(D15>0,T15/D15,0) -> 145.51993 | V15: =IF(C15="CLT", I15*$M$2, 0) -> 480 | W15: =IF(C15="CLT", V15*$M$3, 0) -> 192 | X15: =IF(C15="CLT", I15/12, 0) -> 500 | Y15: =IF(C15="CLT", X15/3, 0) -> 166.66667 | Z15: =IF(C15="CLT", I15/12, 0) -> 500 | AA15: =IF(C15="CLT", I15*$S$2,0) -> 1650 | AB15: =IF(C15="CLT", SUM(X15:Z15) * $M$2,0) -> 93.333333 | AC15: =IF(C15="CLT", SUM(X15:Z15)*$S$2,0) -> 320.83333 | AD15: =IF(C15="CLT", I15/30*3, 0) -> 600 | AE15: =IF(C15="CLT", AD15*$M$2, 0) -> 48 | AF15: =IF(C15="CLT", I15*$M$4, 0) -> 540 | AG15: =IF(B15<>"", IF(C15="CLT", $Q$2, 0),0) -> 600 | AH15: =SUM(V15:AG15)+H15 -> 7440.8333 | AI15: =IF(E15="Sim", T15*$G$4, 0) -> 5890.6468 | AJ15: =T15-AI15-J15-R15 -> 5534.0615 | AK15: =(IF(AJ15>0,AJ15/T15,0)) -> 0.21607715 | AL15: =(IF(AJ15>0,AJ15/(T15-AI15),0)) -> 0.28061967
B16: Analista de Dados/ BI Sênior | C16: CLT | D16: 176 | E16: Sim | F16: 0 | G16: =IF(F16>0,F16, IF(B16<>"", IF(C16="CLT",VLOOKUP(B16,'Lista Profissionais'!$C$11:$H$348,3,0), VLOOKUP(B16,'Lista Profissionais'!$C$11:$H$348,6,0)), 0)) -> 7600 | H16: =IF(B16<>"", IF(C16="CLT", 22*$M$5 + (G16*'Lista Profissionais'!$G$9),0),0) -> 2070 | I16: =(G16/$G$2)*D16 -> 7600 | J16: =I16+AH16 -> 16718.389 | K16: =J16+S16+AI16 -> 24045.474 | L16: =IF(D16>0,J16/D16,0) -> 94.990846 | N16: 0 | O16: =J16*$G$6 -> 0 | P16: =IF(M16>0,M16, J16*(1+$G$5)) -> 30929.019 | Q16: =(P16+O16) -> 30929.019 | R16: =IF(E16="Sim", Q16*$G$3,0) -> 927.87058 | S16: 0 | T16: =IF($D$4="Sim",(IF(E16="Não",0,(Q16+(Q16*$O$4)+R16+S16)*$D$5)+Q16), IF(E16="Não",0,Q16+(Q16*$O$4)+R16+S16 )) -> 31856.89 | U16: =IF(D16>0,T16/D16,0) -> 181.00506 | V16: =IF(C16="CLT", I16*$M$2, 0) -> 608 | W16: =IF(C16="CLT", V16*$M$3, 0) -> 243.2 | X16: =IF(C16="CLT", I16/12, 0) -> 633.33333 | Y16: =IF(C16="CLT", X16/3, 0) -> 211.11111 | Z16: =IF(C16="CLT", I16/12, 0) -> 633.33333 | AA16: =IF(C16="CLT", I16*$S$2,0) -> 2090 | AB16: =IF(C16="CLT", SUM(X16:Z16) * $M$2,0) -> 118.22222 | AC16: =IF(C16="CLT", SUM(X16:Z16)*$S$2,0) -> 406.38889 | AD16: =IF(C16="CLT", I16/30*3, 0) -> 760 | AE16: =IF(C16="CLT", AD16*$M$2, 0) -> 60.8 | AF16: =IF(C16="CLT", I16*$M$4, 0) -> 684 | AG16: =IF(B16<>"", IF(C16="CLT", $Q$2, 0),0) -> 600 | AH16: =SUM(V16:AG16)+H16 -> 9118.3889 | AI16: =IF(E16="Sim", T16*$G$4, 0) -> 7327.0847 | AJ16: =T16-AI16-J16-R16 -> 6883.5458 | AK16: =(IF(AJ16>0,AJ16/T16,0)) -> 0.21607715 | AL16: =(IF(AJ16>0,AJ16/(T16-AI16),0)) -> 0.28061967
B17: Analista de Inteligência Artificial Especialista | C17: CLT | D17: 176 | E17: Sim | F17: 0 | G17: =IF(F17>0,F17, IF(B17<>"", IF(C17="CLT",VLOOKUP(B17,'Lista Profissionais'!$C$11:$H$348,3,0), VLOOKUP(B17,'Lista Profissionais'!$C$11:$H$348,6,0)), 0)) -> 10800 | H17: =IF(B17<>"", IF(C17="CLT", 22*$M$5 + (G17*'Lista Profissionais'!$G$9),0),0) -> 2710 | I17: =(G17/$G$2)*D17 -> 10800 | J17: =I17+AH17 -> 23273.5 | K17: =J17+S17+AI17 -> 33473.46 | L17: =IF(D17>0,J17/D17,0) -> 132.2358 | N17: 0 | O17: =J17*$G$6 -> 0 | P17: =IF(M17>0,M17, J17*(1+$G$5)) -> 43055.975 | Q17: =(P17+O17) -> 43055.975 | R17: =IF(E17="Sim", Q17*$G$3,0) -> 1291.6792 | S17: 0 | T17: =IF($D$4="Sim",(IF(E17="Não",0,(Q17+(Q17*$O$4)+R17+S17)*$D$5)+Q17), IF(E17="Não",0,Q17+(Q17*$O$4)+R17+S17 )) -> 44347.654 | U17: =IF(D17>0,T17/D17,0) -> 251.97531 | V17: =IF(C17="CLT", I17*$M$2, 0) -> 864 | W17: =IF(C17="CLT", V17*$M$3, 0) -> 345.6 | X17: =IF(C17="CLT", I17/12, 0) -> 900 | Y17: =IF(C17="CLT", X17/3, 0) -> 300 | Z17: =IF(C17="CLT", I17/12, 0) -> 900 | AA17: =IF(C17="CLT", I17*$S$2,0) -> 2970 | AB17: =IF(C17="CLT", SUM(X17:Z17) * $M$2,0) -> 168 | AC17: =IF(C17="CLT", SUM(X17:Z17)*$S$2,0) -> 577.5 | AD17: =IF(C17="CLT", I17/30*3, 0) -> 1080 | AE17: =IF(C17="CLT", AD17*$M$2, 0) -> 86.4 | AF17: =IF(C17="CLT", I17*$M$4, 0) -> 972 | AG17: =IF(B17<>"", IF(C17="CLT", $Q$2, 0),0) -> 600 | AH17: =SUM(V17:AG17)+H17 -> 12473.5 | AI17: =IF(E17="Sim", T17*$G$4, 0) -> 10199.96 | AJ17: =T17-AI17-J17-R17 -> 9582.5145 | AK17: =(IF(AJ17>0,AJ17/T17,0)) -> 0.21607715 | AL17: =(IF(AJ17>0,AJ17/(T17-AI17),0)) -> 0.28061967
B18: Analista de Inteligência Artificial Júnior | C18: CLT | D18: 176 | E18: Sim | F18: 0 | G18: =IF(F18>0,F18, IF(B18<>"", IF(C18="CLT",VLOOKUP(B18,'Lista Profissionais'!$C$11:$H$348,3,0), VLOOKUP(B18,'Lista Profissionais'!$C$11:$H$348,6,0)), 0)) -> 3920 | H18: =IF(B18<>"", IF(C18="CLT", 22*$M$5 + (G18*'Lista Profissionais'!$G$9),0),0) -> 1334 | I18: =(G18/$G$2)*D18 -> 3920 | J18: =I18+AH18 -> 9180.0111 | K18: =J18+S18+AI18 -> 13203.289 | L18: =IF(D18>0,J18/D18,0) -> 52.159154 | N18: 0 | O18: =J18*$G$6 -> 0 | P18: =IF(M18>0,M18, J18*(1+$G$5)) -> 16983.021 | Q18: =(P18+O18) -> 16983.021 | R18: =IF(E18="Sim", Q18*$G$3,0) -> 509.49062 | S18: 0 | T18: =IF($D$4="Sim",(IF(E18="Não",0,(Q18+(Q18*$O$4)+R18+S18)*$D$5)+Q18), IF(E18="Não",0,Q18+(Q18*$O$4)+R18+S18 )) -> 17492.511 | U18: =IF(D18>0,T18/D18,0) -> 99.389268 | V18: =IF(C18="CLT", I18*$M$2, 0) -> 313.6 | W18: =IF(C18="CLT", V18*$M$3, 0) -> 125.44 | X18: =IF(C18="CLT", I18/12, 0) -> 326.66667 | Y18: =IF(C18="CLT", X18/3, 0) -> 108.88889 | Z18: =IF(C18="CLT", I18/12, 0) -> 326.66667 | AA18: =IF(C18="CLT", I18*$S$2,0) -> 1078 | AB18: =IF(C18="CLT", SUM(X18:Z18) * $M$2,0) -> 60.977778 | AC18: =IF(C18="CLT", SUM(X18:Z18)*$S$2,0) -> 209.61111 | AD18: =IF(C18="CLT", I18/30*3, 0) -> 392 | AE18: =IF(C18="CLT", AD18*$M$2, 0) -> 31.36 | AF18: =IF(C18="CLT", I18*$M$4, 0) -> 352.8 | AG18: =IF(B18<>"", IF(C18="CLT", $Q$2, 0),0) -> 600 | AH18: =SUM(V18:AG18)+H18 -> 5260.0111 | AI18: =IF(E18="Sim", T18*$G$4, 0) -> 4023.2776 | AJ18: =T18-AI18-J18-R18 -> 3779.7319 | AK18: =(IF(AJ18>0,AJ18/T18,0)) -> 0.21607715 | AL18: =(IF(AJ18>0,AJ18/(T18-AI18),0)) -> 0.28061967
B19: Analista de Inteligência Artificial Pleno | C19: CLT | D19: 176 | E19: Sim | F19: 0 | G19: =IF(F19>0,F19, IF(B19<>"", IF(C19="CLT",VLOOKUP(B19,'Lista Profissionais'!$C$11:$H$348,3,0), VLOOKUP(B19,'Lista Profissionais'!$C$11:$H$348,6,0)), 0)) -> 6000 | H19: =IF(B19<>"", IF(C19="CLT", 22*$M$5 + (G19*'Lista Profissionais'!$G$9),0),0) -> 1750 | I19: =(G19/$G$2)*D19 -> 6000 | J19: =I19+AH19 -> 13440.833 | K19: =J19+S19+AI19 -> 19331.48 | L19: =IF(D19>0,J19/D19,0) -> 76.368371 | N19: 0 | O19: =J19*$G$6 -> 0 | P19: =IF(M19>0,M19, J19*(1+$G$5)) -> 24865.542 | Q19: =(P19+O19) -> 24865.542 | R19: =IF(E19="Sim", Q19*$G$3,0) -> 745.96625 | S19: 0 | T19: =IF($D$4="Sim",(IF(E19="Não",0,(Q19+(Q19*$O$4)+R19+S19)*$D$5)+Q19), IF(E19="Não",0,Q19+(Q19*$O$4)+R19+S19 )) -> 25611.508 | U19: =IF(D19>0,T19/D19,0) -> 145.51993 | V19: =IF(C19="CLT", I19*$M$2, 0) -> 480 | W19: =IF(C19="CLT", V19*$M$3, 0) -> 192 | X19: =IF(C19="CLT", I19/12, 0) -> 500 | Y19: =IF(C19="CLT", X19/3, 0) -> 166.66667 | Z19: =IF(C19="CLT", I19/12, 0) -> 500 | AA19: =IF(C19="CLT", I19*$S$2,0) -> 1650 | AB19: =IF(C19="CLT", SUM(X19:Z19) * $M$2,0) -> 93.333333 | AC19: =IF(C19="CLT", SUM(X19:Z19)*$S$2,0) -> 320.83333 | AD19: =IF(C19="CLT", I19/30*3, 0) -> 600 | AE19: =IF(C19="CLT", AD19*$M$2, 0) -> 48 | AF19: =IF(C19="CLT", I19*$M$4, 0) -> 540 | AG19: =IF(B19<>"", IF(C19="CLT", $Q$2, 0),0) -> 600 | AH19: =SUM(V19:AG19)+H19 -> 7440.8333 | AI19: =IF(E19="Sim", T19*$G$4, 0) -> 5890.6468 | AJ19: =T19-AI19-J19-R19 -> 5534.0615 | AK19: =(IF(AJ19>0,AJ19/T19,0)) -> 0.21607715 | AL19: =(IF(AJ19>0,AJ19/(T19-AI19),0)) -> 0.28061967
B20: Analista de Inteligência Artificial Sênior | C20: CLT | D20: 176 | E20: Sim | F20: 0 | G20: =IF(F20>0,F20, IF(B20<>"", IF(C20="CLT",VLOOKUP(B20,'Lista Profissionais'!$C$11:$H$348,3,0), VLOOKUP(B20,'Lista Profissionais'!$C$11:$H$348,6,0)), 0)) -> 8800 | H20: =IF(B20<>"", IF(C20="CLT", 22*$M$5 + (G20*'Lista Profissionais'!$G$9),0),0) -> 2310 | I20: =(G20/$G$2)*D20 -> 8800 | J20: =I20+AH20 -> 19176.556 | K20: =J20+S20+AI20 -> 27580.969 | L20: =IF(D20>0,J20/D20,0) -> 108.9577 | N20: 0 | O20: =J20*$G$6 -> 0 | P20: =IF(M20>0,M20, J20*(1+$G$5)) -> 35476.628 | Q20: =(P20+O20) -> 35476.628 | R20: =IF(E20="Sim", Q20*$G$3,0) -> 1064.2988 | S20: 0 | T20: =IF($D$4="Sim",(IF(E20="Não",0,(Q20+(Q20*$O$4)+R20+S20)*$D$5)+Q20), IF(E20="Não",0,Q20+(Q20*$O$4)+R20+S20 )) -> 36540.927 | U20: =IF(D20>0,T20/D20,0) -> 207.6189 | V20: =IF(C20="CLT", I20*$M$2, 0) -> 704 | W20: =IF(C20="CLT", V20*$M$3, 0) -> 281.6 | X20: =IF(C20="CLT", I20/12, 0) -> 733.33333 | Y20: =IF(C20="CLT", X20/3, 0) -> 244.44444 | Z20: =IF(C20="CLT", I20/12, 0) -> 733.33333 | AA20: =IF(C20="CLT", I20*$S$2,0) -> 2420 | AB20: =IF(C20="CLT", SUM(X20:Z20) * $M$2,0) -> 136.88889 | AC20: =IF(C20="CLT", SUM(X20:Z20)*$S$2,0) -> 470.55556 | AD20: =IF(C20="CLT", I20/30*3, 0) -> 880 | AE20: =IF(C20="CLT", AD20*$M$2, 0) -> 70.4 | AF20: =IF(C20="CLT", I20*$M$4, 0) -> 792 | AG20: =IF(B20<>"", IF(C20="CLT", $Q$2, 0),0) -> 600 | AH20: =SUM(V20:AG20)+H20 -> 10376.556 | AI20: =IF(E20="Sim", T20*$G$4, 0) -> 8404.4131 | AJ20: =T20-AI20-J20-R20 -> 7895.6591 | AK20: =(IF(AJ20>0,AJ20/T20,0)) -> 0.21607715 | AL20: =(IF(AJ20>0,AJ20/(T20-AI20),0)) -> 0.28061967
... B159: Especialista DQ / DQA Especialista | C159: CLT | D159: 176 | E159: Sim | F159: 0 | G159: =IF(F159>0,F159, IF(B159<>"", IF(C159="CLT",VLOOKUP(B159,'Lista Profissionais'!$C$11:$H$348,3,0), VLOOKUP(B159,'Lista Profissionais'!$C$11:$H$348,6,0)), 0)) -> 19200 | H159: =IF(B159<>"", IF(C159="CLT", 22*$M$5 + (G159*'Lista Profissionais'!$G$9),0),0) -> 4390 | I159: =(G159/$G$2)*D159 -> 19200 | J159: =I159+AH159 -> 40480.667 | K159: =J159+S159+AI159 -> 58221.926 | L159: =IF(D159>0,J159/D159,0) -> 230.00379 | N159: 0 | O159: =J159*$G$6 -> 0 | P159: =IF(M159>0,M159, J159*(1+$G$5)) -> 74889.233 | Q159: =(P159+O159) -> 74889.233 | R159: =IF(E159="Sim", Q159*$G$3,0) -> 2246.677 | S159: 0 | T159: =IF($D$4="Sim",(IF(E159="Não",0,(Q159+(Q159*$O$4)+R159+S159)*$D$5)+Q159), IF(E159="Não",0,Q159+(Q159*$O$4)+R159+S159 )) -> 77135.91 | U159: =IF(D159>0,T159/D159,0) -> 438.27222 | V159: =IF(C159="CLT", I159*$M$2, 0) -> 1536 | W159: =IF(C159="CLT", V159*$M$3, 0) -> 614.4 | X159: =IF(C159="CLT", I159/12, 0) -> 1600 | Y159: =IF(C159="CLT", X159/3, 0) -> 533.33333 | Z159: =IF(C159="CLT", I159/12, 0) -> 1600 | AA159: =IF(C159="CLT", I159*$S$2,0) -> 5280 | AB159: =IF(C159="CLT", SUM(X159:Z159) * $M$2,0) -> 298.66667 | AC159: =IF(C159="CLT", SUM(X159:Z159)*$S$2,0) -> 1026.6667 | AD159: =IF(C159="CLT", I159/30*3, 0) -> 1920 | AE159: =IF(C159="CLT", AD159*$M$2, 0) -> 153.6 | AF159: =IF(C159="CLT", I159*$M$4, 0) -> 1728 | AG159: =IF(B159<>"", IF(C159="CLT", $Q$2, 0),0) -> 600 | AH159: =SUM(V159:AG159)+H159 -> 21280.667 | AI159: =IF(E159="Sim", T159*$G$4, 0) -> 17741.259 | AJ159: =T159-AI159-J159-R159 -> 16667.307 | AK159: =(IF(AJ159>0,AJ159/T159,0)) -> 0.21607715 | AL159: =(IF(AJ159>0,AJ159/(T159-AI159),0)) -> 0.28061967

Sheet Rate Card Exercícios não oficia
E2: RESUMO | F2: Base horas mês | G2: 176 | I2: $ salários + encargos | J2: =SUBTOTAL(9,J9:J50013) -> 17500 | L2: FGTS | M2: 0.08 | N2: Nº colab bilable | O2: =COUNTIF(E9:E5013, "Sim") -> 120 | P2: Valor convênio | Q2: 600 | R2: INSS+RAT+TERC | S2: 0.275 | W2: Ajustes do cálculo CLT que precisamos ajustar em todas tabelas
C3: modelo | D3: CLT | F3: % Comissão vend. | G3: 0 | I3: $ faturamento | J3: =SUBTOTAL(9,T9:T50013) -> 44722 | L3: FGTS Multa | M3: 0.4 | N3: Nº colab no bilable | O3: =COUNTIF(E9:E5013, "Não") -> 0 | P3: Valor comissão | Q3: =SUM(R9:R54) -> 0 | W3: Ok
C4: Híbrido | D4: Não | F4: % Imposto NF | G4: 0.23 | I4: $ Custos | J4: =SUBTOTAL(9,K9:K5013)+Q3 -> 25044 | L4: INSS | M4: 0.09 | N4: % Rateio no Bilable | O4: 0 | P4: Soma de horas | Q4: =SUM(D9:D5013) -> 20184 | W4: Incluídos
C5: Perc.Hib. | D5: 0 | G5: 0.85 | I5: $ lucratividade | J5: =J3-J4 -> 19678 | L5: Ticket Rest. Dia | M5: 50 | N5: Total Billable | O5: =L12 -> 117.69611 | P5: hora média | Q5: =J3/Q4 -> 2.2157154 | W5: Alterados
F6: Taxa de risco | G6: 0 | I6: % lucro real | J6: =J5/J3 -> 0.44000716 | L6: Tarifa média hr. | M6: =SUM(T9:T5013)/SUM(D9:D5013) -> #N/A | N6: Total No Bilable | O6: =SUMIF(E9:E5013,"Não",Q9:Q5013) -> 0 | W6: Remover
B7: CONFIGURAÇÃO EQUIPE | C7: CONFIG RECURSO | F7: C U S T O S C O M C O L A B O R A D O R E S | M7: T A R I F A / F A T U R A M E N T O | V7: C U S T O S C L T | AJ7: IMPOSTOS | AK7: LUCRATIVIDADE
B8: Necessidade cliente | C8: Reg | D8: H.trab | E8: Billable | F8: $ Negociado/salário | G8: $ salário cheio | H8: Vale Refeição/Alimentação | I8: $ Salário real | J8: $ Custo Colab | K8: $ Custo colab + Imp | L8: Custo hora | M8: $ Tarifa negociada | N8: Markup | O8: $ Risco | P8: $ Tarifa | Q8: $ Tar. calculada | R8: $ Comissão | S8: Loc. Equip. | T8: $ Tarifa bilable | U8: Valor hora | V8: FGTS | W8: FGTS multa | X8: Férias | Y8: 1/3 férias | Z8: 13º salário | AA8: INSS+RAT+TERC | AB8: FGTS sobre 13º e Férias | AC8: INSS+RAT+Terc (13º e Fér) | AD8: Aviso Remuner | AE8: FGTS Sobre Aviso | AF8: INSS | AG8: Transporte | AH8: Convênio | AI8: $ Total Encargos | AJ8: Imposto Nota | AK8: $ lucro | AL8: % Lucro | AM8: Marg Contrib
B9: Agilista Especialista | C9: CLT | D9: 168 | E9: Sim | F9: 0 | G9: =IF(F9>0,F9, IF(B9<>"", IF(C9="CLT",VLOOKUP(B9,'Lista Profissionais'!$C$11:$H$348,3,0), VLOOKUP(B9,'Lista Profissionais'!$C$11:$H$348,6,0)), 0)) -> 10800 | H9: =IF(B9<>"", IF(C9="CLT", 22*$M$5 + (G9*'Lista Profissionais'!$G$9),0),0) -> 3260 | I9: =(G9/$G$2)*D9 -> 10309.091 | J9: =I9+AI9 -> 22916.068 | K9: =J9+S9+AJ9 -> 32666.855 | L9: =IF(D9>0,J9/D9,0) -> 136.40517 | N9: 0 | O9: =J9*$G$6 -> 0 | P9: =IF(M9>0,M9, J9*(1+$G$5)) -> 42394.726 | Q9: =(P9+O9) -> 42394.726 | R9: =IF(E9="Sim", Q9*$G$3,0) -> 0 | S9: 0 | T9: =IF($D$4="Sim",(IF(E9="Não",0,(Q9+(Q9*$O$4)+R9+S9)*$D$5)+Q9), IF(E9="Não",0,Q9+(Q9*$O$4)+R9+S9 )) -> 42394.726 | U9: =IF(D9>0,T9/D9,0) -> 252.34956 | V9: =IF(C9="CLT", I9*$M$2, 0) -> 824.72727 | W9: =IF(C9="CLT", V9*$M$3, 0) -> 329.89091 | X9: =IF(C9="CLT", I9/12, 0) -> 859.09091 | Y9: =IF(C9="CLT", X9/3, 0) -> 286.36364 | Z9: =IF(C9="CLT", I9/12, 0) -> 859.09091 | AA9: =IF(C9="CLT", I9*$S$2,0) -> 2835 | AB9: =IF(C9="CLT", SUM(X9:Z9) * $M$2,0) -> 160.36364 | AC9: =IF(C9="CLT", SUM(X9:Z9)*$S$2,0) -> 551.25 | AD9: =IF(C9="CLT", I9/30*3, 0) -> 1030.9091 | AE9: =IF(C9="CLT", AD9*$M$2, 0) -> 82.472727 | AF9: =IF(C9="CLT", I9*$M$4, 0) -> 927.81818 | AH9: =IF(B9<>"", IF(C9="CLT", $Q$2, 0),0) -> 600 | AI9: =SUM(V9:AH9)+H9 -> 12606.977 | AJ9: =IF(E9="Sim", T9*$G$4, 0) -> 9750.787 | AK9: =T9-AJ9-J9-R9 -> 9727.8709 | AL9: =(IF(AK9>0,AK9/T9,0)) -> 0.22945946 | AM9: =(IF(AK9>0,AK9/(T9-AJ9),0)) -> 0.2979993
B10: Agilista - Junior Júnior | C10: CLT | D10: 168 | E10: Sim | F10: 0 | G10: =IF(F10>0,F10, IF(B10<>"", IF(C10="CLT",VLOOKUP(B10,'Lista Profissionais'!$C$11:$H$348,3,0), VLOOKUP(B10,'Lista Profissionais'!$C$11:$H$348,6,0)), 0)) -> 3920 | H10: =IF(B10<>"", IF(C10="CLT", 22*$M$5 + (G10*'Lista Profissionais'!$G$9),0),0) -> 1884 | I10: =(G10/$G$2)*D10 -> 3741.8182 | J10: =I10+AI10 -> 9400.647 | K10: =J10+S10+AJ10 -> 13400.622 | L10: =IF(D10>0,J10/D10,0) -> 55.956232 | N10: 0 | O10: =J10*$G$6 -> 0 | P10: =IF(M10>0,M10, J10*(1+$G$5)) -> 17391.197 | Q10: =(P10+O10) -> 17391.197 | R10: =IF(E10="Sim", Q10*$G$3,0) -> 0 | S10: 0 | T10: =IF($D$4="Sim",(IF(E10="Não",0,(Q10+(Q10*$O$4)+R10+S10)*$D$5)+Q10), IF(E10="Não",0,Q10+(Q10*$O$4)+R10+S10 )) -> 17391.197 | U10: =IF(D10>0,T10/D10,0) -> 103.51903 | V10: =IF(C10="CLT", I10*$M$2, 0) -> 299.34545 | W10: =IF(C10="CLT", V10*$M$3, 0) -> 119.73818 | X10: =IF(C10="CLT", I10/12, 0) -> 311.81818 | Y10: =IF(C10="CLT", X10/3, 0) -> 103.93939 | Z10: =IF(C10="CLT", I10/12, 0) -> 311.81818 | AA10: =IF(C10="CLT", I10*$S$2,0) -> 1029 | AB10: =IF(C10="CLT", SUM(X10:Z10) * $M$2,0) -> 58.206061 | AC10: =IF(C10="CLT", SUM(X10:Z10)*$S$2,0) -> 200.08333 | AD10: =IF(C10="CLT", I10/30*3, 0) -> 374.18182 | AE10: =IF(C10="CLT", AD10*$M$2, 0) -> 29.934545 | AF10: =IF(C10="CLT", I10*$M$4, 0) -> 336.76364 | AH10: =IF(B10<>"", IF(C10="CLT", $Q$2, 0),0) -> 600 | AI10: =SUM(V10:AH10)+H10 -> 5658.8288 | AJ10: =IF(E10="Sim", T10*$G$4, 0) -> 3999.9753 | AK10: =T10-AJ10-J10-R10 -> 3990.5746 | AL10: =(IF(AK10>0,AK10/T10,0)) -> 0.22945946 | AM10: =(IF(AK10>0,AK10/(T10-AJ10),0)) -> 0.2979993
B11: Agilista Pleno | C11: CLT | D11: 168 | E11: Sim | F11: 0 | G11: =IF(F11>0,F11, IF(B11<>"", IF(C11="CLT",VLOOKUP(B11,'Lista Profissionais'!$C$11:$H$348,3,0), VLOOKUP(B11,'Lista Profissionais'!$C$11:$H$348,6,0)), 0)) -> 6320 | H11: =IF(B11<>"", IF(C11="CLT", 22*$M$5 + (G11*'Lista Profissionais'!$G$9),0),0) -> 2364 | I11: =(G11/$G$2)*D11 -> 6032.7273 | J11: =I11+AI11 -> 14115.329 | K11: =J11+S11+AJ11 -> 20121.401 | L11: =IF(D11>0,J11/D11,0) -> 84.019814 | N11: 0 | O11: =J11*$G$6 -> 0 | P11: =IF(M11>0,M11, J11*(1+$G$5)) -> 26113.358 | Q11: =(P11+O11) -> 26113.358 | R11: =IF(E11="Sim", Q11*$G$3,0) -> 0 | S11: 0 | T11: =IF($D$4="Sim",(IF(E11="Não",0,(Q11+(Q11*$O$4)+R11+S11)*$D$5)+Q11), IF(E11="Não",0,Q11+(Q11*$O$4)+R11+S11 )) -> 26113.358 | U11: =IF(D11>0,T11/D11,0) -> 155.43666 | V11: =IF(C11="CLT", I11*$M$2, 0) -> 482.61818 | W11: =IF(C11="CLT", V11*$M$3, 0) -> 193.04727 | X11: =IF(C11="CLT", I11/12, 0) -> 502.72727 | Y11: =IF(C11="CLT", X11/3, 0) -> 167.57576 | Z11: =IF(C11="CLT", I11/12, 0) -> 502.72727 | AA11: =IF(C11="CLT", I11*$S$2,0) -> 1659 | AB11: =IF(C11="CLT", SUM(X11:Z11) * $M$2,0) -> 93.842424 | AC11: =IF(C11="CLT", SUM(X11:Z11)*$S$2,0) -> 322.58333 | AD11: =IF(C11="CLT", I11/30*3, 0) -> 603.27273 | AE11: =IF(C11="CLT", AD11*$M$2, 0) -> 48.261818 | AF11: =IF(C11="CLT", I11*$M$4, 0) -> 542.94545 | AH11: =IF(B11<>"", IF(C11="CLT", $Q$2, 0),0) -> 600 | AI11: =SUM(V11:AH11)+H11 -> 8082.6015 | AJ11: =IF(E11="Sim", T11*$G$4, 0) -> 6006.0724 | AK11: =T11-AJ11-J11-R11 -> 5991.9571 | AL11: =(IF(AK11>0,AK11/T11,0)) -> 0.22945946 | AM11: =(IF(AK11>0,AK11/(T11-AJ11),0)) -> 0.2979993
B12: Agilista Sênior | C12: CLT | D12: 168 | E12: Sim | F12: 0 | G12: =IF(F12>0,F12, IF(B12<>"", IF(C12="CLT",VLOOKUP(B12,'Lista Profissionais'!$C$11:$H$348,3,0), VLOOKUP(B12,'Lista Profissionais'!$C$11:$H$348,6,0)), 0)) -> 9200 | H12: =IF(B12<>"", IF(C12="CLT", 22*$M$5 + (G12*'Lista Profissionais'!$G$9),0),0) -> 2940 | I12: =(G12/$G$2)*D12 -> 8781.8182 | J12: =I12+AI12 -> 19772.947 | K12: =J12+S12+AJ12 -> 28186.336 | L12: =IF(D12>0,J12/D12,0) -> 117.69611 | N12: 0 | O12: =J12*$G$6 -> 0 | P12: =IF(M12>0,M12, J12*(1+$G$5)) -> 36579.952 | Q12: =(P12+O12) -> 36579.952 | R12: =IF(E12="Sim", Q12*$G$3,0) -> 0 | S12: 0 | T12: =IF($D$4="Sim",(IF(E12="Não",0,(Q12+(Q12*$O$4)+R12+S12)*$D$5)+Q12), IF(E12="Não",0,Q12+(Q12*$O$4)+R12+S12 )) -> 36579.952 | U12: =IF(D12>0,T12/D12,0) -> 217.73781 | V12: =IF(C12="CLT", I12*$M$2, 0) -> 702.54545 | W12: =IF(C12="CLT", V12*$M$3, 0) -> 281.01818 | X12: =IF(C12="CLT", I12/12, 0) -> 731.81818 | Y12: =IF(C12="CLT", X12/3, 0) -> 243.93939 | Z12: =IF(C12="CLT", I12/12, 0) -> 731.81818 | AA12: =IF(C12="CLT", I12*$S$2,0) -> 2415 | AB12: =IF(C12="CLT", SUM(X12:Z12) * $M$2,0) -> 136.60606 | AC12: =IF(C12="CLT", SUM(X12:Z12)*$S$2,0) -> 469.58333 | AD12: =IF(C12="CLT", I12/30*3, 0) -> 878.18182 | AE12: =IF(C12="CLT", AD12*$M$2, 0) -> 70.254545 | AF12: =IF(C12="CLT", I12*$M$4, 0) -> 790.36364 | AH12: =IF(B12<>"", IF(C12="CLT", $Q$2, 0),0) -> 600 | AI12: =SUM(V12:AH12)+H12 -> 10991.129 | AJ12: =IF(E12="Sim", T12*$G$4, 0) -> 8413.3889 | AK12: =T12-AJ12-J12-R12 -> 8393.616 | AL12: =(IF(AK12>0,AK12/T12,0)) -> 0.22945946 | AM12: =(IF(AK12>0,AK12/(T12-AJ12),0)) -> 0.2979993
B13: Analista de Dados/ BI Especialista | C13: CLT | D13: 168 | E13: Sim | F13: 0 | G13: =IF(F13>0,F13, IF(B13<>"", IF(C13="CLT",VLOOKUP(B13,'Lista Profissionais'!$C$11:$H$348,3,0), VLOOKUP(B13,'Lista Profissionais'!$C$11:$H$348,6,0)), 0)) -> 8800 | H13: =IF(B13<>"", IF(C13="CLT", 22*$M$5 + (G13*'Lista Profissionais'!$G$9),0),0) -> 2860 | I13: =(G13/$G$2)*D13 -> 8400 | J13: =I13+AI13 -> 18987.167 | K13: =J13+S13+AJ13 -> 27066.206 | L13: =IF(D13>0,J13/D13,0) -> 113.01885 | N13: 0 | O13: =J13*$G$6 -> 0 | P13: =IF(M13>0,M13, J13*(1+$G$5)) -> 35126.258 | Q13: =(P13+O13) -> 35126.258 | R13: =IF(E13="Sim", Q13*$G$3,0) -> 0 | S13: 0 | T13: =IF($D$4="Sim",(IF(E13="Não",0,(Q13+(Q13*$O$4)+R13+S13)*$D$5)+Q13), IF(E13="Não",0,Q13+(Q13*$O$4)+R13+S13 )) -> 35126.258 | U13: =IF(D13>0,T13/D13,0) -> 209.08487 | V13: =IF(C13="CLT", I13*$M$2, 0) -> 672 | W13: =IF(C13="CLT", V13*$M$3, 0) -> 268.8 | X13: =IF(C13="CLT", I13/12, 0) -> 700 | Y13: =IF(C13="CLT", X13/3, 0) -> 233.33333 | Z13: =IF(C13="CLT", I13/12, 0) -> 700 | AA13: =IF(C13="CLT", I13*$S$2,0) -> 2310 | AB13: =IF(C13="CLT", SUM(X13:Z13) * $M$2,0) -> 130.66667 | AC13: =IF(C13="CLT", SUM(X13:Z13)*$S$2,0) -> 449.16667 | AD13: =IF(C13="CLT", I13/30*3, 0) -> 840 | AE13: =IF(C13="CLT", AD13*$M$2, 0) -> 67.2 | AF13: =IF(C13="CLT", I13*$M$4, 0) -> 756 | AH13: =IF(B13<>"", IF(C13="CLT", $Q$2, 0),0) -> 600 | AI13: =SUM(V13:AH13)+H13 -> 10587.167 | AJ13: =IF(E13="Sim", T13*$G$4, 0) -> 8079.0394 | AK13: =T13-AJ13-J13-R13 -> 8060.0523 | AL13: =(IF(AK13>0,AK13/T13,0)) -> 0.22945946 | AM13: =(IF(AK13>0,AK13/(T13-AJ13),0)) -> 0.2979993
B14: Analista de Dados/ BI Júnior | C14: CLT | D14: 168 | E14: Sim | F14: 0 | G14: =IF(F14>0,F14, IF(B14<>"", IF(C14="CLT",VLOOKUP(B14,'Lista Profissionais'!$C$11:$H$348,3,0), VLOOKUP(B14,'Lista Profissionais'!$C$11:$H$348,6,0)), 0)) -> 3360 | H14: =IF(B14<>"", IF(C14="CLT", 22*$M$5 + (G14*'Lista Profissionais'!$G$9),0),0) -> 1772 | I14: =(G14/$G$2)*D14 -> 3207.2727 | J14: =I14+AI14 -> 8300.5545 | K14: =J14+S14+AJ14 -> 11832.441 | L14: =IF(D14>0,J14/D14,0) -> 49.408063 | N14: 0 | O14: =J14*$G$6 -> 0 | P14: =IF(M14>0,M14, J14*(1+$G$5)) -> 15356.026 | Q14: =(P14+O14) -> 15356.026 | R14: =IF(E14="Sim", Q14*$G$3,0) -> 0 | S14: 0 | T14: =IF($D$4="Sim",(IF(E14="Não",0,(Q14+(Q14*$O$4)+R14+S14)*$D$5)+Q14), IF(E14="Não",0,Q14+(Q14*$O$4)+R14+S14 )) -> 15356.026 | U14: =IF(D14>0,T14/D14,0) -> 91.404916 | V14: =IF(C14="CLT", I14*$M$2, 0) -> 256.58182 | W14: =IF(C14="CLT", V14*$M$3, 0) -> 102.63273 | X14: =IF(C14="CLT", I14/12, 0) -> 267.27273 | Y14: =IF(C14="CLT", X14/3, 0) -> 89.090909 | Z14: =IF(C14="CLT", I14/12, 0) -> 267.27273 | AA14: =IF(C14="CLT", I14*$S$2,0) -> 882 | AB14: =IF(C14="CLT", SUM(X14:Z14) * $M$2,0) -> 49.890909 | AC14: =IF(C14="CLT", SUM(X14:Z14)*$S$2,0) -> 171.5 | AD14: =IF(C14="CLT", I14/30*3, 0) -> 320.72727 | AE14: =IF(C14="CLT", AD14*$M$2, 0) -> 25.658182 | AF14: =IF(C14="CLT", I14*$M$4, 0) -> 288.65455 | AH14: =IF(B14<>"", IF(C14="CLT", $Q$2, 0),0) -> 600 | AI14: =SUM(V14:AH14)+H14 -> 5093.2818 | AJ14: =IF(E14="Sim", T14*$G$4, 0) -> 3531.886 | AK14: =T14-AJ14-J14-R14 -> 3523.5854 | AL14: =(IF(AK14>0,AK14/T14,0)) -> 0.22945946 | AM14: =(IF(AK14>0,AK14/(T14-AJ14),0)) -> 0.2979993
B15: Analista de Dados/ BI Pleno | C15: CLT | D15: 168 | E15: Sim | F15: 0 | G15: =IF(F15>0,F15, IF(B15<>"", IF(C15="CLT",VLOOKUP(B15,'Lista Profissionais'!$C$11:$H$348,3,0), VLOOKUP(B15,'Lista Profissionais'!$C$11:$H$348,6,0)), 0)) -> 6000 | H15: =IF(B15<>"", IF(C15="CLT", 22*$M$5 + (G15*'Lista Profissionais'!$G$9),0),0) -> 2300 | I15: =(G15/$G$2)*D15 -> 5727.2727 | J15: =I15+AI15 -> 13486.705 | K15: =J15+S15+AJ15 -> 19225.297 | L15: =IF(D15>0,J15/D15,0) -> 80.278003 | N15: 0 | O15: =J15*$G$6 -> 0 | P15: =IF(M15>0,M15, J15*(1+$G$5)) -> 24950.403 | Q15: =(P15+O15) -> 24950.403 | R15: =IF(E15="Sim", Q15*$G$3,0) -> 0 | S15: 0 | T15: =IF($D$4="Sim",(IF(E15="Não",0,(Q15+(Q15*$O$4)+R15+S15)*$D$5)+Q15), IF(E15="Não",0,Q15+(Q15*$O$4)+R15+S15 )) -> 24950.403 | U15: =IF(D15>0,T15/D15,0) -> 148.51431 | V15: =IF(C15="CLT", I15*$M$2, 0) -> 458.18182 | W15: =IF(C15="CLT", V15*$M$3, 0) -> 183.27273 | X15: =IF(C15="CLT", I15/12, 0) -> 477.27273 | Y15: =IF(C15="CLT", X15/3, 0) -> 159.09091 | Z15: =IF(C15="CLT", I15/12, 0) -> 477.27273 | AA15: =IF(C15="CLT", I15*$S$2,0) -> 1575 | AB15: =IF(C15="CLT", SUM(X15:Z15) * $M$2,0) -> 89.090909 | AC15: =IF(C15="CLT", SUM(X15:Z15)*$S$2,0) -> 306.25 | AD15: =IF(C15="CLT", I15/30*3, 0) -> 572.72727 | AE15: =IF(C15="CLT", AD15*$M$2, 0) -> 45.818182 | AF15: =IF(C15="CLT", I15*$M$4, 0) -> 515.45455 | AH15: =IF(B15<>"", IF(C15="CLT", $Q$2, 0),0) -> 600 | AI15: =SUM(V15:AH15)+H15 -> 7759.4318 | AJ15: =IF(E15="Sim", T15*$G$4, 0) -> 5738.5928 | AK15: =T15-AJ15-J15-R15 -> 5725.1061 | AL15: =(IF(AK15>0,AK15/T15,0)) -> 0.22945946 | AM15: =(IF(AK15>0,AK15/(T15-AJ15),0)) -> 0.2979993
B16: Analista de Dados/ BI Sênior | C16: CLT | D16: 168 | E16: Sim | F16: 0 | G16: =IF(F16>0,F16, IF(B16<>"", IF(C16="CLT",VLOOKUP(B16,'Lista Profissionais'!$C$11:$H$348,3,0), VLOOKUP(B16,'Lista Profissionais'!$C$11:$H$348,6,0)), 0)) -> 7600 | H16: =IF(B16<>"", IF(C16="CLT", 22*$M$5 + (G16*'Lista Profissionais'!$G$9),0),0) -> 2620 | I16: =(G16/$G$2)*D16 -> 7254.5455 | J16: =I16+AI16 -> 16629.826 | K16: =J16+S16+AJ16 -> 23705.817 | L16: =IF(D16>0,J16/D16,0) -> 98.987058 | N16: 0 | O16: =J16*$G$6 -> 0 | P16: =IF(M16>0,M16, J16*(1+$G$5)) -> 30765.178 | Q16: =(P16+O16) -> 30765.178 | R16: =IF(E16="Sim", Q16*$G$3,0) -> 0 | S16: 0 | T16: =IF($D$4="Sim",(IF(E16="Não",0,(Q16+(Q16*$O$4)+R16+S16)*$D$5)+Q16), IF(E16="Não",0,Q16+(Q16*$O$4)+R16+S16 )) -> 30765.178 | U16: =IF(D16>0,T16/D16,0) -> 183.12606 | V16: =IF(C16="CLT", I16*$M$2, 0) -> 580.36364 | W16: =IF(C16="CLT", V16*$M$3, 0) -> 232.14545 | X16: =IF(C16="CLT", I16/12, 0) -> 604.54545 | Y16: =IF(C16="CLT", X16/3, 0) -> 201.51515 | Z16: =IF(C16="CLT", I16/12, 0) -> 604.54545 | AA16: =IF(C16="CLT", I16*$S$2,0) -> 1995 | AB16: =IF(C16="CLT", SUM(X16:Z16) * $M$2,0) -> 112.84848 | AC16: =IF(C16="CLT", SUM(X16:Z16)*$S$2,0) -> 387.91667 | AD16: =IF(C16="CLT", I16/30*3, 0) -> 725.45455 | AE16: =IF(C16="CLT", AD16*$M$2, 0) -> 58.036364 | AF16: =IF(C16="CLT", I16*$M$4, 0) -> 652.90909 | AH16: =IF(B16<>"", IF(C16="CLT", $Q$2, 0),0) -> 600 | AI16: =SUM(V16:AH16)+H16 -> 9375.2803 | AJ16: =IF(E16="Sim", T16*$G$4, 0) -> 7075.9909 | AK16: =T16-AJ16-J16-R16 -> 7059.361 | AL16: =(IF(AK16>0,AK16/T16,0)) -> 0.22945946 | AM16: =(IF(AK16>0,AK16/(T16-AJ16),0)) -> 0.2979993
B17: Analista de Inteligência Artificial Especialista | C17: CLT | D17: 168 | E17: Sim | F17: 0 | G17: =IF(F17>0,F17, IF(B17<>"", IF(C17="CLT",VLOOKUP(B17,'Lista Profissionais'!$C$11:$H$348,3,0), VLOOKUP(B17,'Lista Profissionais'!$C$11:$H$348,6,0)), 0)) -> 10800 | H17: =IF(B17<>"", IF(C17="CLT", 22*$M$5 + (G17*'Lista Profissionais'!$G$9),0),0) -> 3260 | I17: =(G17/$G$2)*D17 -> 10309.091 | J17: =I17+AI17 -> 22916.068 | K17: =J17+S17+AJ17 -> 32666.855 | L17: =IF(D17>0,J17/D17,0) -> 136.40517 | N17: 0 | O17: =J17*$G$6 -> 0 | P17: =IF(M17>0,M17, J17*(1+$G$5)) -> 42394.726 | Q17: =(P17+O17) -> 42394.726 | R17: =IF(E17="Sim", Q17*$G$3,0) -> 0 | S17: 0 | T17: =IF($D$4="Sim",(IF(E17="Não",0,(Q17+(Q17*$O$4)+R17+S17)*$D$5)+Q17), IF(E17="Não",0,Q17+(Q17*$O$4)+R17+S17 )) -> 42394.726 | U17: =IF(D17>0,T17/D17,0) -> 252.34956 | V17: =IF(C17="CLT", I17*$M$2, 0) -> 824.72727 | W17: =IF(C17="CLT", V17*$M$3, 0) -> 329.89091 | X17: =IF(C17="CLT", I17/12, 0) -> 859.09091 | Y17: =IF(C17="CLT", X17/3, 0) -> 286.36364 | Z17: =IF(C17="CLT", I17/12, 0) -> 859.09091 | AA17: =IF(C17="CLT", I17*$S$2,0) -> 2835 | AB17: =IF(C17="CLT", SUM(X17:Z17) * $M$2,0) -> 160.36364 | AC17: =IF(C17="CLT", SUM(X17:Z17)*$S$2,0) -> 551.25 | AD17: =IF(C17="CLT", I17/30*3, 0) -> 1030.9091 | AE17: =IF(C17="CLT", AD17*$M$2, 0) -> 82.472727 | AF17: =IF(C17="CLT", I17*$M$4, 0) -> 927.81818 | AH17: =IF(B17<>"", IF(C17="CLT", $Q$2, 0),0) -> 600 | AI17: =SUM(V17:AH17)+H17 -> 12606.977 | AJ17: =IF(E17="Sim", T17*$G$4, 0) -> 9750.787 | AK17: =T17-AJ17-J17-R17 -> 9727.8709 | AL17: =(IF(AK17>0,AK17/T17,0)) -> 0.22945946 | AM17: =(IF(AK17>0,AK17/(T17-AJ17),0)) -> 0.2979993
B18: Analista de Inteligência Artificial Júnior | C18: CLT | D18: 168 | E18: Sim | F18: 0 | G18: =IF(F18>0,F18, IF(B18<>"", IF(C18="CLT",VLOOKUP(B18,'Lista Profissionais'!$C$11:$H$348,3,0), VLOOKUP(B18,'Lista Profissionais'!$C$11:$H$348,6,0)), 0)) -> 3920 | H18: =IF(B18<>"", IF(C18="CLT", 22*$M$5 + (G18*'Lista Profissionais'!$G$9),0),0) -> 1884 | I18: =(G18/$G$2)*D18 -> 3741.8182 | J18: =I18+AI18 -> 9400.647 | K18: =J18+S18+AJ18 -> 13400.622 | L18: =IF(D18>0,J18/D18,0) -> 55.956232 | N18: 0 | O18: =J18*$G$6 -> 0 | P18: =IF(M18>0,M18, J18*(1+$G$5)) -> 17391.197 | Q18: =(P18+O18) -> 17391.197 | R18: =IF(E18="Sim", Q18*$G$3,0) -> 0 | S18: 0 | T18: =IF($D$4="Sim",(IF(E18="Não",0,(Q18+(Q18*$O$4)+R18+S18)*$D$5)+Q18), IF(E18="Não",0,Q18+(Q18*$O$4)+R18+S18 )) -> 17391.197 | U18: =IF(D18>0,T18/D18,0) -> 103.51903 | V18: =IF(C18="CLT", I18*$M$2, 0) -> 299.34545 | W18: =IF(C18="CLT", V18*$M$3, 0) -> 119.73818 | X18: =IF(C18="CLT", I18/12, 0) -> 311.81818 | Y18: =IF(C18="CLT", X18/3, 0) -> 103.93939 | Z18: =IF(C18="CLT", I18/12, 0) -> 311.81818 | AA18: =IF(C18="CLT", I18*$S$2,0) -> 1029 | AB18: =IF(C18="CLT", SUM(X18:Z18) * $M$2,0) -> 58.206061 | AC18: =IF(C18="CLT", SUM(X18:Z18)*$S$2,0) -> 200.08333 | AD18: =IF(C18="CLT", I18/30*3, 0) -> 374.18182 | AE18: =IF(C18="CLT", AD18*$M$2, 0) -> 29.934545 | AF18: =IF(C18="CLT", I18*$M$4, 0) -> 336.76364 | AH18: =IF(B18<>"", IF(C18="CLT", $Q$2, 0),0) -> 600 | AI18: =SUM(V18:AH18)+H18 -> 5658.8288 | AJ18: =IF(E18="Sim", T18*$G$4, 0) -> 3999.9753 | AK18: =T18-AJ18-J18-R18 -> 3990.5746 | AL18: =(IF(AK18>0,AK18/T18,0)) -> 0.22945946 | AM18: =(IF(AK18>0,AK18/(T18-AJ18),0)) -> 0.2979993
B19: Analista de Inteligência Artificial Pleno | C19: CLT | D19: 168 | E19: Sim | F19: 0 | G19: =IF(F19>0,F19, IF(B19<>"", IF(C19="CLT",VLOOKUP(B19,'Lista Profissionais'!$C$11:$H$348,3,0), VLOOKUP(B19,'Lista Profissionais'!$C$11:$H$348,6,0)), 0)) -> 6000 | H19: =IF(B19<>"", IF(C19="CLT", 22*$M$5 + (G19*'Lista Profissionais'!$G$9),0),0) -> 2300 | I19: =(G19/$G$2)*D19 -> 5727.2727 | J19: =I19+AI19 -> 13486.705 | K19: =J19+S19+AJ19 -> 19225.297 | L19: =IF(D19>0,J19/D19,0) -> 80.278003 | N19: 0 | O19: =J19*$G$6 -> 0 | P19: =IF(M19>0,M19, J19*(1+$G$5)) -> 24950.403 | Q19: =(P19+O19) -> 24950.403 | R19: =IF(E19="Sim", Q19*$G$3,0) -> 0 | S19: 0 | T19: =IF($D$4="Sim",(IF(E19="Não",0,(Q19+(Q19*$O$4)+R19+S19)*$D$5)+Q19), IF(E19="Não",0,Q19+(Q19*$O$4)+R19+S19 )) -> 24950.403 | U19: =IF(D19>0,T19/D19,0) -> 148.51431 | V19: =IF(C19="CLT", I19*$M$2, 0) -> 458.18182 | W19: =IF(C19="CLT", V19*$M$3, 0) -> 183.27273 | X19: =IF(C19="CLT", I19/12, 0) -> 477.27273 | Y19: =IF(C19="CLT", X19/3, 0) -> 159.09091 | Z19: =IF(C19="CLT", I19/12, 0) -> 477.27273 | AA19: =IF(C19="CLT", I19*$S$2,0) -> 1575 | AB19: =IF(C19="CLT", SUM(X19:Z19) * $M$2,0) -> 89.090909 | AC19: =IF(C19="CLT", SUM(X19:Z19)*$S$2,0) -> 306.25 | AD19: =IF(C19="CLT", I19/30*3, 0) -> 572.72727 | AE19: =IF(C19="CLT", AD19*$M$2, 0) -> 45.818182 | AF19: =IF(C19="CLT", I19*$M$4, 0) -> 515.45455 | AH19: =IF(B19<>"", IF(C19="CLT", $Q$2, 0),0) -> 600 | AI19: =SUM(V19:AH19)+H19 -> 7759.4318 | AJ19: =IF(E19="Sim", T19*$G$4, 0) -> 5738.5928 | AK19: =T19-AJ19-J19-R19 -> 5725.1061 | AL19: =(IF(AK19>0,AK19/T19,0)) -> 0.22945946 | AM19: =(IF(AK19>0,AK19/(T19-AJ19),0)) -> 0.2979993
B20: Analista de Inteligência Artificial Sênior | C20: CLT | D20: 168 | E20: Sim | F20: 0 | G20: =IF(F20>0,F20, IF(B20<>"", IF(C20="CLT",VLOOKUP(B20,'Lista Profissionais'!$C$11:$H$348,3,0), VLOOKUP(B20,'Lista Profissionais'!$C$11:$H$348,6,0)), 0)) -> 8800 | H20: =IF(B20<>"", IF(C20="CLT", 22*$M$5 + (G20*'Lista Profissionais'!$G$9),0),0) -> 2860 | I20: =(G20/$G$2)*D20 -> 8400 | J20: =I20+AI20 -> 18987.167 | K20: =J20+S20+AJ20 -> 27066.206 | L20: =IF(D20>0,J20/D20,0) -> 113.01885 | N20: 0 | O20: =J20*$G$6 -> 0 | P20: =IF(M20>0,M20, J20*(1+$G$5)) -> 35126.258 | Q20: =(P20+O20) -> 35126.258 | R20: =IF(E20="Sim", Q20*$G$3,0) -> 0 | S20: 0 | T20: =IF($D$4="Sim",(IF(E20="Não",0,(Q20+(Q20*$O$4)+R20+S20)*$D$5)+Q20), IF(E20="Não",0,Q20+(Q20*$O$4)+R20+S20 )) -> 35126.258 | U20: =IF(D20>0,T20/D20,0) -> 209.08487 | V20: =IF(C20="CLT", I20*$M$2, 0) -> 672 | W20: =IF(C20="CLT", V20*$M$3, 0) -> 268.8 | X20: =IF(C20="CLT", I20/12, 0) -> 700 | Y20: =IF(C20="CLT", X20/3, 0) -> 233.33333 | Z20: =IF(C20="CLT", I20/12, 0) -> 700 | AA20: =IF(C20="CLT", I20*$S$2,0) -> 2310 | AB20: =IF(C20="CLT", SUM(X20:Z20) * $M$2,0) -> 130.66667 | AC20: =IF(C20="CLT", SUM(X20:Z20)*$S$2,0) -> 449.16667 | AD20: =IF(C20="CLT", I20/30*3, 0) -> 840 | AE20: =IF(C20="CLT", AD20*$M$2, 0) -> 67.2 | AF20: =IF(C20="CLT", I20*$M$4, 0) -> 756 | AH20: =IF(B20<>"", IF(C20="CLT", $Q$2, 0),0) -> 600 | AI20: =SUM(V20:AH20)+H20 -> 10587.167 | AJ20: =IF(E20="Sim", T20*$G$4, 0) -> 8079.0394 | AK20: =T20-AJ20-J20-R20 -> 8060.0523 | AL20: =(IF(AK20>0,AK20/T20,0)) -> 0.22945946 | AM20: =(IF(AK20>0,AK20/(T20-AJ20),0)) -> 0.2979993
... B71: Desenvolvedor FullStack Pleno | C71: CLT | D71: 168 | E71: Sim | F71: 0 | G71: =IF(F71>0,F71, IF(B71<>"", IF(C71="CLT",VLOOKUP(B71,'Lista Profissionais'!$C$11:$H$348,3,0), VLOOKUP(B71,'Lista Profissionais'!$C$11:$H$348,6,0)), 0)) -> 7520 | H71: =IF(B71<>"", IF(C71="CLT", 22*$M$5 + (G71*'Lista Profissionais'!$G$9),0),0) -> 2604 | I71: =(G71/$G$2)*D71 -> 7178.1818 | J71: =I71+AI71 -> 16472.67 | K71: =J71+S71+AJ71 -> 23481.791 | L71: =IF(D71>0,J71/D71,0) -> 98.051605 | N71: 0 | O71: =J71*$G$6 -> 0 | P71: =IF(M71>0,M71, J71*(1+$G$5)) -> 30474.439 | Q71: =(P71+O71) -> 30474.439 | R71: =IF(E71="Sim", Q71*$G$3,0) -> 0 | S71: 0 | T71: =IF($D$4="Sim",(IF(E71="Não",0,(Q71+(Q71*$O$4)+R71+S71)*$D$5)+Q71), IF(E71="Não",0,Q71+(Q71*$O$4)+R71+S71 )) -> 30474.439 | U71: =IF(D71>0,T71/D71,0) -> 181.39547 | V71: =IF(C71="CLT", I71*$M$2, 0) -> 574.25455 | W71: =IF(C71="CLT", V71*$M$3, 0) -> 229.70182 | X71: =IF(C71="CLT", I71/12, 0) -> 598.18182 | Y71: =IF(C71="CLT", X71/3, 0) -> 199.39394 | Z71: =IF(C71="CLT", I71/12, 0) -> 598.18182 | AA71: =IF(C71="CLT", I71*$S$2,0) -> 1974 | AB71: =IF(C71="CLT", SUM(X71:Z71) * $M$2,0) -> 111.66061 | AC71: =IF(C71="CLT", SUM(X71:Z71)*$S$2,0) -> 383.83333 | AD71: =IF(C71="CLT", I71/30*3, 0) -> 717.81818 | AE71: =IF(C71="CLT", AD71*$M$2, 0) -> 57.425455 | AF71: =IF(C71="CLT", I71*$M$4, 0) -> 646.03636 | AH71: =IF(B71<>"", IF(C71="CLT", $Q$2, 0),0) -> 600 | AI71: =SUM(V71:AH71)+H71 -> 9294.4879 | AJ71: =IF(E71="Sim", T71*$G$4, 0) -> 7009.121 | AK71: =T71-AJ71-J71-R71 -> 6992.6483 | AL71: =(IF(AK71>0,AK71/T71,0)) -> 0.22945946 | AM71: =(IF(AK71>0,AK71/(T71-AJ71),0)) -> 0.2979993
B72: Desenvolvedor FullStack Sênior | C72: PJ | D72: 176 | E72: Sim | F72: 17500 | G72: =IF(F72>0,F72, IF(B72<>"", IF(C72="CLT",VLOOKUP(B72,'Lista Profissionais'!$C$11:$H$348,3,0), VLOOKUP(B72,'Lista Profissionais'!$C$11:$H$348,6,0)), 0)) -> 17500 | H72: =IF(B72<>"", IF(C72="CLT", 22*$M$5 + (G72*'Lista Profissionais'!$G$9),0),0) -> 0 | I72: =(G72/$G$2)*D72 -> 17500 | J72: =I72+AI72 -> 17500 | K72: =J72+S72+AJ72 -> 25044 | L72: =IF(D72>0,J72/D72,0) -> 99.431818 | M72: 32800 | N72: 0 | O72: =J72*$G$6 -> 0 | P72: =IF(M72>0,M72, J72*(1+$G$5)) -> 32800 | Q72: =(P72+O72) -> 32800 | R72: =IF(E72="Sim", Q72*$G$3,0) -> 0 | S72: 0 | T72: =IF($D$4="Sim",(IF(E72="Não",0,(Q72+(Q72*$O$4)+R72+S72)*$D$5)+Q72), IF(E72="Não",0,Q72+(Q72*$O$4)+R72+S72 )) -> 32800 | U72: =IF(D72>0,T72/D72,0) -> 186.36364 | V72: =IF(C72="CLT", I72*$M$2, 0) -> 0 | W72: =IF(C72="CLT", V72*$M$3, 0) -> 0 | X72: =IF(C72="CLT", I72/12, 0) -> 0 | Y72: =IF(C72="CLT", X72/3, 0) -> 0 | Z72: =IF(C72="CLT", I72/12, 0) -> 0 | AA72: =IF(C72="CLT", I72*$S$2,0) -> 0 | AB72: =IF(C72="CLT", SUM(X72:Z72) * $M$2,0) -> 0 | AC72: =IF(C72="CLT", SUM(X72:Z72)*$S$2,0) -> 0 | AD72: =IF(C72="CLT", I72/30*3, 0) -> 0 | AE72: =IF(C72="CLT", AD72*$M$2, 0) -> 0 | AF72: =IF(C72="CLT", I72*$M$4, 0) -> 0 | AH72: =IF(B72<>"", IF(C72="CLT", $Q$2, 0),0) -> 0 | AI72: =SUM(V72:AH72)+H72 -> 0 | AJ72: =IF(E72="Sim", T72*$G$4, 0) -> 7544 | AK72: =T72-AJ72-J72-R72 -> 7756 | AL72: =(IF(AK72>0,AK72/T72,0)) -> 0.23646341 | AM72: =(IF(AK72>0,AK72/(T72-AJ72),0)) -> 0.30709534
B73: Desenvolvedor Mobile Especialista | C73: CLT | D73: 168 | E73: Sim | F73: 0 | G73: =IF(F73>0,F73, IF(B73<>"", IF(C73="CLT",VLOOKUP(B73,'Lista Profissionais'!$C$11:$H$348,3,0), VLOOKUP(B73,'Lista Profissionais'!$C$11:$H$348,6,0)), 0)) -> 10880 | H73: =IF(B73<>"", IF(C73="CLT", 22*$M$5 + (G73*'Lista Profissionais'!$G$9),0),0) -> 3276 | I73: =(G73/$G$2)*D73 -> 10385.455 | J73: =I73+AI73 -> 23073.224 | K73: =J73+S73+AJ73 -> 32890.881 | L73: =IF(D73>0,J73/D73,0) -> 137.34062 | N73: 0 | O73: =J73*$G$6 -> 0 | P73: =IF(M73>0,M73, J73*(1+$G$5)) -> 42685.465 | Q73: =(P73+O73) -> 42685.465 | R73: =IF(E73="Sim", Q73*$G$3,0) -> 0 | S73: 0 | T73: =IF($D$4="Sim",(IF(E73="Não",0,(Q73+(Q73*$O$4)+R73+S73)*$D$5)+Q73), IF(E73="Não",0,Q73+(Q73*$O$4)+R73+S73 )) -> 42685.465 | U73: =IF(D73>0,T73/D73,0) -> 254.08015 | V73: =IF(C73="CLT", I73*$M$2, 0) -> 830.83636 | W73: =IF(C73="CLT", V73*$M$3, 0) -> 332.33455 | X73: =IF(C73="CLT", I73/12, 0) -> 865.45455 | Y73: =IF(C73="CLT", X73/3, 0) -> 288.48485 | Z73: =IF(C73="CLT", I73/12, 0) -> 865.45455 | AA73: =IF(C73="CLT", I73*$S$2,0) -> 2856 | AB73: =IF(C73="CLT", SUM(X73:Z73) * $M$2,0) -> 161.55152 | AC73: =IF(C73="CLT", SUM(X73:Z73)*$S$2,0) -> 555.33333 | AD73: =IF(C73="CLT", I73/30*3, 0) -> 1038.5455 | AE73: =IF(C73="CLT", AD73*$M$2, 0) -> 83.083636 | AF73: =IF(C73="CLT", I73*$M$4, 0) -> 934.69091 | AH73: =IF(B73<>"", IF(C73="CLT", $Q$2, 0),0) -> 600 | AI73: =SUM(V73:AH73)+H73 -> 12687.77 | AJ73: =IF(E73="Sim", T73*$G$4, 0) -> 9817.6569 | AK73: =T73-AJ73-J73-R73 -> 9794.5837 | AL73: =(IF(AK73>0,AK73/T73,0)) -> 0.22945946 | AM73: =(IF(AK73>0,AK73/(T73-AJ73),0)) -> 0.2979993
B74: Desenvolvedor Mobile Júnior | C74: CLT | D74: 168 | E74: Sim | F74: 0 | G74: =IF(F74>0,F74, IF(B74<>"", IF(C74="CLT",VLOOKUP(B74,'Lista Profissionais'!$C$11:$H$348,3,0), VLOOKUP(B74,'Lista Profissionais'!$C$11:$H$348,6,0)), 0)) -> 3920 | H74: =IF(B74<>"", IF(C74="CLT", 22*$M$5 + (G74*'Lista Profissionais'!$G$9),0),0) -> 1884 | I74: =(G74/$G$2)*D74 -> 3741.8182 | J74: =I74+AI74 -> 9400.647 | K74: =J74+S74+AJ74 -> 13400.622 | L74: =IF(D74>0,J74/D74,0) -> 55.956232 | N74: 0 | O74: =J74*$G$6 -> 0 | P74: =IF(M74>0,M74, J74*(1+$G$5)) -> 17391.197 | Q74: =(P74+O74) -> 17391.197 | R74: =IF(E74="Sim", Q74*$G$3,0) -> 0 | S74: 0 | T74: =IF($D$4="Sim",(IF(E74="Não",0,(Q74+(Q74*$O$4)+R74+S74)*$D$5)+Q74), IF(E74="Não",0,Q74+(Q74*$O$4)+R74+S74 )) -> 17391.197 | U74: =IF(D74>0,T74/D74,0) -> 103.51903 | V74: =IF(C74="CLT", I74*$M$2, 0) -> 299.34545 | W74: =IF(C74="CLT", V74*$M$3, 0) -> 119.73818 | X74: =IF(C74="CLT", I74/12, 0) -> 311.81818 | Y74: =IF(C74="CLT", X74/3, 0) -> 103.93939 | Z74: =IF(C74="CLT", I74/12, 0) -> 311.81818 | AA74: =IF(C74="CLT", I74*$S$2,0) -> 1029 | AB74: =IF(C74="CLT", SUM(X74:Z74) * $M$2,0) -> 58.206061 | AC74: =IF(C74="CLT", SUM(X74:Z74)*$S$2,0) -> 200.08333 | AD74: =IF(C74="CLT", I74/30*3, 0) -> 374.18182 | AE74: =IF(C74="CLT", AD74*$M$2, 0) -> 29.934545 | AF74: =IF(C74="CLT", I74*$M$4, 0) -> 336.76364 | AH74: =IF(B74<>"", IF(C74="CLT", $Q$2, 0),0) -> 600 | AI74: =SUM(V74:AH74)+H74 -> 5658.8288 | AJ74: =IF(E74="Sim", T74*$G$4, 0) -> 3999.9753 | AK74: =T74-AJ74-J74-R74 -> 3990.5746 | AL74: =(IF(AK74>0,AK74/T74,0)) -> 0.22945946 | AM74: =(IF(AK74>0,AK74/(T74-AJ74),0)) -> 0.2979993
B75: Desenvolvedor Mobile Pleno | C75: CLT | D75: 168 | E75: Sim | F75: 0 | G75: =IF(F75>0,F75, IF(B75<>"", IF(C75="CLT",VLOOKUP(B75,'Lista Profissionais'!$C$11:$H$348,3,0), VLOOKUP(B75,'Lista Profissionais'!$C$11:$H$348,6,0)), 0)) -> 7520 | H75: =IF(B75<>"", IF(C75="CLT", 22*$M$5 + (G75*'Lista Profissionais'!$G$9),0),0) -> 2604 | I75: =(G75/$G$2)*D75 -> 7178.1818 | J75: =I75+AI75 -> 16472.67 | K75: =J75+S75+AJ75 -> 23481.791 | L75: =IF(D75>0,J75/D75,0) -> 98.051605 | N75: 0 | O75: =J75*$G$6 -> 0 | P75: =IF(M75>0,M75, J75*(1+$G$5)) -> 30474.439 | Q75: =(P75+O75) -> 30474.439 | R75: =IF(E75="Sim", Q75*$G$3,0) -> 0 | S75: 0 | T75: =IF($D$4="Sim",(IF(E75="Não",0,(Q75+(Q75*$O$4)+R75+S75)*$D$5)+Q75), IF(E75="Não",0,Q75+(Q75*$O$4)+R75+S75 )) -> 30474.439 | U75: =IF(D75>0,T75/D75,0) -> 181.39547 | V75: =IF(C75="CLT", I75*$M$2, 0) -> 574.25455 | W75: =IF(C75="CLT", V75*$M$3, 0) -> 229.70182 | X75: =IF(C75="CLT", I75/12, 0) -> 598.18182 | Y75: =IF(C75="CLT", X75/3, 0) -> 199.39394 | Z75: =IF(C75="CLT", I75/12, 0) -> 598.18182 | AA75: =IF(C75="CLT", I75*$S$2,0) -> 1974 | AB75: =IF(C75="CLT", SUM(X75:Z75) * $M$2,0) -> 111.66061 | AC75: =IF(C75="CLT", SUM(X75:Z75)*$S$2,0) -> 383.83333 | AD75: =IF(C75="CLT", I75/30*3, 0) -> 717.81818 | AE75: =IF(C75="CLT", AD75*$M$2, 0) -> 57.425455 | AF75: =IF(C75="CLT", I75*$M$4, 0) -> 646.03636 | AH75: =IF(B75<>"", IF(C75="CLT", $Q$2, 0),0) -> 600 | AI75: =SUM(V75:AH75)+H75 -> 9294.4879 | AJ75: =IF(E75="Sim", T75*$G$4, 0) -> 7009.121 | AK75: =T75-AJ75-J75-R75 -> 6992.6483 | AL75: =(IF(AK75>0,AK75/T75,0)) -> 0.22945946 | AM75: =(IF(AK75>0,AK75/(T75-AJ75),0)) -> 0.2979993
B76: Desenvolvedor Mobile Sênior | C76: CLT | D76: 168 | E76: Sim | F76: 0 | G76: =IF(F76>0,F76, IF(B76<>"", IF(C76="CLT",VLOOKUP(B76,'Lista Profissionais'!$C$11:$H$348,3,0), VLOOKUP(B76,'Lista Profissionais'!$C$11:$H$348,6,0)), 0)) -> 9200 | H76: =IF(B76<>"", IF(C76="CLT", 22*$M$5 + (G76*'Lista Profissionais'!$G$9),0),0) -> 2940 | I76: =(G76/$G$2)*D76 -> 8781.8182 | J76: =I76+AI76 -> 19772.947 | K76: =J76+S76+AJ76 -> 28186.336 | L76: =IF(D76>0,J76/D76,0) -> 117.69611 | N76: 0 | O76: =J76*$G$6 -> 0 | P76: =IF(M76>0,M76, J76*(1+$G$5)) -> 36579.952 | Q76: =(P76+O76) -> 36579.952 | R76: =IF(E76="Sim", Q76*$G$3,0) -> 0 | S76: 0 | T76: =IF($D$4="Sim",(IF(E76="Não",0,(Q76+(Q76*$O$4)+R76+S76)*$D$5)+Q76), IF(E76="Não",0,Q76+(Q76*$O$4)+R76+S76 )) -> 36579.952 | U76: =IF(D76>0,T76/D76,0) -> 217.73781 | V76: =IF(C76="CLT", I76*$M$2, 0) -> 702.54545 | W76: =IF(C76="CLT", V76*$M$3, 0) -> 281.01818 | X76: =IF(C76="CLT", I76/12, 0) -> 731.81818 | Y76: =IF(C76="CLT", X76/3, 0) -> 243.93939 | Z76: =IF(C76="CLT", I76/12, 0) -> 731.81818 | AA76: =IF(C76="CLT", I76*$S$2,0) -> 2415 | AB76: =IF(C76="CLT", SUM(X76:Z76) * $M$2,0) -> 136.60606 | AC76: =IF(C76="CLT", SUM(X76:Z76)*$S$2,0) -> 469.58333 | AD76: =IF(C76="CLT", I76/30*3, 0) -> 878.18182 | AE76: =IF(C76="CLT", AD76*$M$2, 0) -> 70.254545 | AF76: =IF(C76="CLT", I76*$M$4, 0) -> 790.36364 | AH76: =IF(B76<>"", IF(C76="CLT", $Q$2, 0),0) -> 600 | AI76: =SUM(V76:AH76)+H76 -> 10991.129 | AJ76: =IF(E76="Sim", T76*$G$4, 0) -> 8413.3889 | AK76: =T76-AJ76-J76-R76 -> 8393.616 | AL76: =(IF(AK76>0,AK76/T76,0)) -> 0.22945946 | AM76: =(IF(AK76>0,AK76/(T76-AJ76),0)) -> 0.2979993
B77: Desenvolvedor Salesforce Especialista | C77: CLT | D77: 168 | E77: Sim | F77: 0 | G77: =IF(F77>0,F77, IF(B77<>"", IF(C77="CLT",VLOOKUP(B77,'Lista Profissionais'!$C$11:$H$348,3,0), VLOOKUP(B77,'Lista Profissionais'!$C$11:$H$348,6,0)), 0)) -> 8800 | H77: =IF(B77<>"", IF(C77="CLT", 22*$M$5 + (G77*'Lista Profissionais'!$G$9),0),0) -> 2860 | I77: =(G77/$G$2)*D77 -> 8400 | J77: =I77+AI77 -> 18987.167 | K77: =J77+S77+AJ77 -> 27066.206 | L77: =IF(D77>0,J77/D77,0) -> 113.01885 | N77: 0 | O77: =J77*$G$6 -> 0 | P77: =IF(M77>0,M77, J77*(1+$G$5)) -> 35126.258 | Q77: =(P77+O77) -> 35126.258 | R77: =IF(E77="Sim", Q77*$G$3,0) -> 0 | S77: 0 | T77: =IF($D$4="Sim",(IF(E77="Não",0,(Q77+(Q77*$O$4)+R77+S77)*$D$5)+Q77), IF(E77="Não",0,Q77+(Q77*$O$4)+R77+S77 )) -> 35126.258 | U77: =IF(D77>0,T77/D77,0) -> 209.08487 | V77: =IF(C77="CLT", I77*$M$2, 0) -> 672 | W77: =IF(C77="CLT", V77*$M$3, 0) -> 268.8 | X77: =IF(C77="CLT", I77/12, 0) -> 700 | Y77: =IF(C77="CLT", X77/3, 0) -> 233.33333 | Z77: =IF(C77="CLT", I77/12, 0) -> 700 | AA77: =IF(C77="CLT", I77*$S$2,0) -> 2310 | AB77: =IF(C77="CLT", SUM(X77:Z77) * $M$2,0) -> 130.66667 | AC77: =IF(C77="CLT", SUM(X77:Z77)*$S$2,0) -> 449.16667 | AD77: =IF(C77="CLT", I77/30*3, 0) -> 840 | AE77: =IF(C77="CLT", AD77*$M$2, 0) -> 67.2 | AF77: =IF(C77="CLT", I77*$M$4, 0) -> 756 | AH77: =IF(B77<>"", IF(C77="CLT", $Q$2, 0),0) -> 600 | AI77: =SUM(V77:AH77)+H77 -> 10587.167 | AJ77: =IF(E77="Sim", T77*$G$4, 0) -> 8079.0394 | AK77: =T77-AJ77-J77-R77 -> 8060.0523 | AL77: =(IF(AK77>0,AK77/T77,0)) -> 0.22945946 | AM77: =(IF(AK77>0,AK77/(T77-AJ77),0)) -> 0.2979993
B78: Desenvolvedor Salesforce Júnior | C78: CLT | D78: 168 | E78: Sim | F78: 0 | G78: =IF(F78>0,F78, IF(B78<>"", IF(C78="CLT",VLOOKUP(B78,'Lista Profissionais'!$C$11:$H$348,3,0), VLOOKUP(B78,'Lista Profissionais'!$C$11:$H$348,6,0)), 0)) -> 3600 | H78: =IF(B78<>"", IF(C78="CLT", 22*$M$5 + (G78*'Lista Profissionais'!$G$9),0),0) -> 1820 | I78: =(G78/$G$2)*D78 -> 3436.3636 | J78: =I78+AI78 -> 8772.0227 | K78: =J78+S78+AJ78 -> 12504.518 | L78: =IF(D78>0,J78/D78,0) -> 52.214421 | N78: 0 | O78: =J78*$G$6 -> 0 | P78: =IF(M78>0,M78, J78*(1+$G$5)) -> 16228.242 | Q78: =(P78+O78) -> 16228.242 | R78: =IF(E78="Sim", Q78*$G$3,0) -> 0 | S78: 0 | T78: =IF($D$4="Sim",(IF(E78="Não",0,(Q78+(Q78*$O$4)+R78+S78)*$D$5)+Q78), IF(E78="Não",0,Q78+(Q78*$O$4)+R78+S78 )) -> 16228.242 | U78: =IF(D78>0,T78/D78,0) -> 96.596679 | V78: =IF(C78="CLT", I78*$M$2, 0) -> 274.90909 | W78: =IF(C78="CLT", V78*$M$3, 0) -> 109.96364 | X78: =IF(C78="CLT", I78/12, 0) -> 286.36364 | Y78: =IF(C78="CLT", X78/3, 0) -> 95.454545 | Z78: =IF(C78="CLT", I78/12, 0) -> 286.36364 | AA78: =IF(C78="CLT", I78*$S$2,0) -> 945 | AB78: =IF(C78="CLT", SUM(X78:Z78) * $M$2,0) -> 53.454545 | AC78: =IF(C78="CLT", SUM(X78:Z78)*$S$2,0) -> 183.75 | AD78: =IF(C78="CLT", I78/30*3, 0) -> 343.63636 | AE78: =IF(C78="CLT", AD78*$M$2, 0) -> 27.490909 | AF78: =IF(C78="CLT", I78*$M$4, 0) -> 309.27273 | AH78: =IF(B78<>"", IF(C78="CLT", $Q$2, 0),0) -> 600 | AI78: =SUM(V78:AH78)+H78 -> 5335.6591 | AJ78: =IF(E78="Sim", T78*$G$4, 0) -> 3732.4957 | AK78: =T78-AJ78-J78-R78 -> 3723.7236 | AL78: =(IF(AK78>0,AK78/T78,0)) -> 0.22945946 | AM78: =(IF(AK78>0,AK78/(T78-AJ78),0)) -> 0.2979993
B79: Desenvolvedor Salesforce Pleno | C79: CLT | D79: 168 | E79: Sim | F79: 0 | G79: =IF(F79>0,F79, IF(B79<>"", IF(C79="CLT",VLOOKUP(B79,'Lista Profissionais'!$C$11:$H$348,3,0), VLOOKUP(B79,'Lista Profissionais'!$C$11:$H$348,6,0)), 0)) -> 5600 | H79: =IF(B79<>"", IF(C79="CLT", 22*$M$5 + (G79*'Lista Profissionais'!$G$9),0),0) -> 2220 | I79: =(G79/$G$2)*D79 -> 5345.4545 | J79: =I79+AI79 -> 12700.924 | K79: =J79+S79+AJ79 -> 18105.168 | L79: =IF(D79>0,J79/D79,0) -> 75.60074 | N79: 0 | O79: =J79*$G$6 -> 0 | P79: =IF(M79>0,M79, J79*(1+$G$5)) -> 23496.71 | Q79: =(P79+O79) -> 23496.71 | R79: =IF(E79="Sim", Q79*$G$3,0) -> 0 | S79: 0 | T79: =IF($D$4="Sim",(IF(E79="Não",0,(Q79+(Q79*$O$4)+R79+S79)*$D$5)+Q79), IF(E79="Não",0,Q79+(Q79*$O$4)+R79+S79 )) -> 23496.71 | U79: =IF(D79>0,T79/D79,0) -> 139.86137 | V79: =IF(C79="CLT", I79*$M$2, 0) -> 427.63636 | W79: =IF(C79="CLT", V79*$M$3, 0) -> 171.05455 | X79: =IF(C79="CLT", I79/12, 0) -> 445.45455 | Y79: =IF(C79="CLT", X79/3, 0) -> 148.48485 | Z79: =IF(C79="CLT", I79/12, 0) -> 445.45455 | AA79: =IF(C79="CLT", I79*$S$2,0) -> 1470 | AB79: =IF(C79="CLT", SUM(X79:Z79) * $M$2,0) -> 83.151515 | AC79: =IF(C79="CLT", SUM(X79:Z79)*$S$2,0) -> 285.83333 | AD79: =IF(C79="CLT", I79/30*3, 0) -> 534.54545 | AE79: =IF(C79="CLT", AD79*$M$2, 0) -> 42.763636 | AF79: =IF(C79="CLT", I79*$M$4, 0) -> 481.09091 | AH79: =IF(B79<>"", IF(C79="CLT", $Q$2, 0),0) -> 600 | AI79: =SUM(V79:AH79)+H79 -> 7355.4697 | AJ79: =IF(E79="Sim", T79*$G$4, 0) -> 5404.2433 | AK79: =T79-AJ79-J79-R79 -> 5391.5423 | AL79: =(IF(AK79>0,AK79/T79,0)) -> 0.22945946 | AM79: =(IF(AK79>0,AK79/(T79-AJ79),0)) -> 0.2979993
B80: Desenvolvedor Salesforce Sênior | C80: CLT | D80: 168 | E80: Sim | F80: 0 | G80: =IF(F80>0,F80, IF(B80<>"", IF(C80="CLT",VLOOKUP(B80,'Lista Profissionais'!$C$11:$H$348,3,0), VLOOKUP(B80,'Lista Profissionais'!$C$11:$H$348,6,0)), 0)) -> 7200 | H80: =IF(B80<>"", IF(C80="CLT", 22*$M$5 + (G80*'Lista Profissionais'!$G$9),0),0) -> 2540 | I80: =(G80/$G$2)*D80 -> 6872.7273 | J80: =I80+AI80 -> 15844.045 | K80: =J80+S80+AJ80 -> 22585.687 | L80: =IF(D80>0,J80/D80,0) -> 94.309794 | N80: 0 | O80: =J80*$G$6 -> 0 | P80: =IF(M80>0,M80, J80*(1+$G$5)) -> 29311.484 | Q80: =(P80+O80) -> 29311.484 | R80: =IF(E80="Sim", Q80*$G$3,0) -> 0 | S80: 0 | T80: =IF($D$4="Sim",(IF(E80="Não",0,(Q80+(Q80*$O$4)+R80+S80)*$D$5)+Q80), IF(E80="Não",0,Q80+(Q80*$O$4)+R80+S80 )) -> 29311.484 | U80: =IF(D80>0,T80/D80,0) -> 174.47312 | V80: =IF(C80="CLT", I80*$M$2, 0) -> 549.81818 | W80: =IF(C80="CLT", V80*$M$3, 0) -> 219.92727 | X80: =IF(C80="CLT", I80/12, 0) -> 572.72727 | Y80: =IF(C80="CLT", X80/3, 0) -> 190.90909 | Z80: =IF(C80="CLT", I80/12, 0) -> 572.72727 | AA80: =IF(C80="CLT", I80*$S$2,0) -> 1890 | AB80: =IF(C80="CLT", SUM(X80:Z80) * $M$2,0) -> 106.90909 | AC80: =IF(C80="CLT", SUM(X80:Z80)*$S$2,0) -> 367.5 | AD80: =IF(C80="CLT", I80/30*3, 0) -> 687.27273 | AE80: =IF(C80="CLT", AD80*$M$2, 0) -> 54.981818 | AF80: =IF(C80="CLT", I80*$M$4, 0) -> 618.54545 | AH80: =IF(B80<>"", IF(C80="CLT", $Q$2, 0),0) -> 600 | AI80: =SUM(V80:AH80)+H80 -> 8971.3182 | AJ80: =IF(E80="Sim", T80*$G$4, 0) -> 6741.6413 | AK80: =T80-AJ80-J80-R80 -> 6725.7973 | AL80: =(IF(AK80>0,AK80/T80,0)) -> 0.22945946 | AM80: =(IF(AK80>0,AK80/(T80-AJ80),0)) -> 0.2979993
B81: DevSecOps Especialista | C81: CLT | D81: 168 | E81: Sim | F81: 0 | G81: =IF(F81>0,F81, IF(B81<>"", IF(C81="CLT",VLOOKUP(B81,'Lista Profissionais'!$C$11:$H$348,3,0), VLOOKUP(B81,'Lista Profissionais'!$C$11:$H$348,6,0)), 0)) -> 9600 | H81: =IF(B81<>"", IF(C81="CLT", 22*$M$5 + (G81*'Lista Profissionais'!$G$9),0),0) -> 3020 | I81: =(G81/$G$2)*D81 -> 9163.6364 | J81: =I81+AI81 -> 20558.727 | K81: =J81+S81+AJ81 -> 29306.466 | L81: =IF(D81>0,J81/D81,0) -> 122.37338 | N81: 0 | O81: =J81*$G$6 -> 0 | P81: =IF(M81>0,M81, J81*(1+$G$5)) -> 38033.645 | Q81: =(P81+O81) -> 38033.645 | R81: =IF(E81="Sim", Q81*$G$3,0) -> 0 | S81: 0 | T81: =IF($D$4="Sim",(IF(E81="Não",0,(Q81+(Q81*$O$4)+R81+S81)*$D$5)+Q81), IF(E81="Não",0,Q81+(Q81*$O$4)+R81+S81 )) -> 38033.645 | U81: =IF(D81>0,T81/D81,0) -> 226.39075 | V81: =IF(C81="CLT", I81*$M$2, 0) -> 733.09091 | W81: =IF(C81="CLT", V81*$M$3, 0) -> 293.23636 | X81: =IF(C81="CLT", I81/12, 0) -> 763.63636 | Y81: =IF(C81="CLT", X81/3, 0) -> 254.54545 | Z81: =IF(C81="CLT", I81/12, 0) -> 763.63636 | AA81: =IF(C81="CLT", I81*$S$2,0) -> 2520 | AB81: =IF(C81="CLT", SUM(X81:Z81) * $M$2,0) -> 142.54545 | AC81: =IF(C81="CLT", SUM(X81:Z81)*$S$2,0) -> 490 | AD81: =IF(C81="CLT", I81/30*3, 0) -> 916.36364 | AE81: =IF(C81="CLT", AD81*$M$2, 0) -> 73.309091 | AF81: =IF(C81="CLT", I81*$M$4, 0) -> 824.72727 | AH81: =IF(B81<>"", IF(C81="CLT", $Q$2, 0),0) -> 600 | AI81: =SUM(V81:AH81)+H81 -> 11395.091 | AJ81: =IF(E81="Sim", T81*$G$4, 0) -> 8747.7385 | AK81: =T81-AJ81-J81-R81 -> 8727.1797 | AL81: =(IF(AK81>0,AK81/T81,0)) -> 0.22945946 | AM81: =(IF(AK81>0,AK81/(T81-AJ81),0)) -> 0.2979993
B82: DevSecOps Júnior | C82: CLT | D82: 168 | E82: Sim | F82: 0 | G82: =IF(F82>0,F82, IF(B82<>"", IF(C82="CLT",VLOOKUP(B82,'Lista Profissionais'!$C$11:$H$348,3,0), VLOOKUP(B82,'Lista Profissionais'!$C$11:$H$348,6,0)), 0)) -> 3920 | H82: =IF(B82<>"", IF(C82="CLT", 22*$M$5 + (G82*'Lista Profissionais'!$G$9),0),0) -> 1884 | I82: =(G82/$G$2)*D82 -> 3741.8182 | J82: =I82+AI82 -> 9400.647 | K82: =J82+S82+AJ82 -> 13400.622 | L82: =IF(D82>0,J82/D82,0) -> 55.956232 | N82: 0 | O82: =J82*$G$6 -> 0 | P82: =IF(M82>0,M82, J82*(1+$G$5)) -> 17391.197 | Q82: =(P82+O82) -> 17391.197 | R82: =IF(E82="Sim", Q82*$G$3,0) -> 0 | S82: 0 | T82: =IF($D$4="Sim",(IF(E82="Não",0,(Q82+(Q82*$O$4)+R82+S82)*$D$5)+Q82), IF(E82="Não",0,Q82+(Q82*$O$4)+R82+S82 )) -> 17391.197 | U82: =IF(D82>0,T82/D82,0) -> 103.51903 | V82: =IF(C82="CLT", I82*$M$2, 0) -> 299.34545 | W82: =IF(C82="CLT", V82*$M$3, 0) -> 119.73818 | X82: =IF(C82="CLT", I82/12, 0) -> 311.81818 | Y82: =IF(C82="CLT", X82/3, 0) -> 103.93939 | Z82: =IF(C82="CLT", I82/12, 0) -> 311.81818 | AA82: =IF(C82="CLT", I82*$S$2,0) -> 1029 | AB82: =IF(C82="CLT", SUM(X82:Z82) * $M$2,0) -> 58.206061 | AC82: =IF(C82="CLT", SUM(X82:Z82)*$S$2,0) -> 200.08333 | AD82: =IF(C82="CLT", I82/30*3, 0) -> 374.18182 | AE82: =IF(C82="CLT", AD82*$M$2, 0) -> 29.934545 | AF82: =IF(C82="CLT", I82*$M$4, 0) -> 336.76364 | AH82: =IF(B82<>"", IF(C82="CLT", $Q$2, 0),0) -> 600 | AI82: =SUM(V82:AH82)+H82 -> 5658.8288 | AJ82: =IF(E82="Sim", T82*$G$4, 0) -> 3999.9753 | AK82: =T82-AJ82-J82-R82 -> 3990.5746 | AL82: =(IF(AK82>0,AK82/T82,0)) -> 0.22945946 | AM82: =(IF(AK82>0,AK82/(T82-AJ82),0)) -> 0.2979993
B83: DevSecOps Pleno | C83: CLT | D83: 168 | E83: Sim | F83: 0 | G83: =IF(F83>0,F83, IF(B83<>"", IF(C83="CLT",VLOOKUP(B83,'Lista Profissionais'!$C$11:$H$348,3,0), VLOOKUP(B83,'Lista Profissionais'!$C$11:$H$348,6,0)), 0)) -> 7200 | H83: =IF(B83<>"", IF(C83="CLT", 22*$M$5 + (G83*'Lista Profissionais'!$G$9),0),0) -> 2540 | I83: =(G83/$G$2)*D83 -> 6872.7273 | J83: =I83+AI83 -> 15844.045 | K83: =J83+S83+AJ83 -> 22585.687 | L83: =IF(D83>0,J83/D83,0) -> 94.309794 | N83: 0 | O83: =J83*$G$6 -> 0 | P83: =IF(M83>0,M83, J83*(1+$G$5)) -> 29311.484 | Q83: =(P83+O83) -> 29311.484 | R83: =IF(E83="Sim", Q83*$G$3,0) -> 0 | S83: 0 | T83: =IF($D$4="Sim",(IF(E83="Não",0,(Q83+(Q83*$O$4)+R83+S83)*$D$5)+Q83), IF(E83="Não",0,Q83+(Q83*$O$4)+R83+S83 )) -> 29311.484 | U83: =IF(D83>0,T83/D83,0) -> 174.47312 | V83: =IF(C83="CLT", I83*$M$2, 0) -> 549.81818 | W83: =IF(C83="CLT", V83*$M$3, 0) -> 219.92727 | X83: =IF(C83="CLT", I83/12, 0) -> 572.72727 | Y83: =IF(C83="CLT", X83/3, 0) -> 190.90909 | Z83: =IF(C83="CLT", I83/12, 0) -> 572.72727 | AA83: =IF(C83="CLT", I83*$S$2,0) -> 1890 | AB83: =IF(C83="CLT", SUM(X83:Z83) * $M$2,0) -> 106.90909 | AC83: =IF(C83="CLT", SUM(X83:Z83)*$S$2,0) -> 367.5 | AD83: =IF(C83="CLT", I83/30*3, 0) -> 687.27273 | AE83: =IF(C83="CLT", AD83*$M$2, 0) -> 54.981818 | AF83: =IF(C83="CLT", I83*$M$4, 0) -> 618.54545 | AH83: =IF(B83<>"", IF(C83="CLT", $Q$2, 0),0) -> 600 | AI83: =SUM(V83:AH83)+H83 -> 8971.3182 | AJ83: =IF(E83="Sim", T83*$G$4, 0) -> 6741.6413 | AK83: =T83-AJ83-J83-R83 -> 6725.7973 | AL83: =(IF(AK83>0,AK83/T83,0)) -> 0.22945946 | AM83: =(IF(AK83>0,AK83/(T83-AJ83),0)) -> 0.2979993
B84: DevSecOps Sênior | C84: CLT | D84: 168 | E84: Sim | F84: 0 | G84: =IF(F84>0,F84, IF(B84<>"", IF(C84="CLT",VLOOKUP(B84,'Lista Profissionais'!$C$11:$H$348,3,0), VLOOKUP(B84,'Lista Profissionais'!$C$11:$H$348,6,0)), 0)) -> 8800 | H84: =IF(B84<>"", IF(C84="CLT", 22*$M$5 + (G84*'Lista Profissionais'!$G$9),0),0) -> 2860 | I84: =(G84/$G$2)*D84 -> 8400 | J84: =I84+AI84 -> 18987.167 | K84: =J84+S84+AJ84 -> 27066.206 | L84: =IF(D84>0,J84/D84,0) -> 113.01885 | N84: 0 | O84: =J84*$G$6 -> 0 | P84: =IF(M84>0,M84, J84*(1+$G$5)) -> 35126.258 | Q84: =(P84+O84) -> 35126.258 | R84: =IF(E84="Sim", Q84*$G$3,0) -> 0 | S84: 0 | T84: =IF($D$4="Sim",(IF(E84="Não",0,(Q84+(Q84*$O$4)+R84+S84)*$D$5)+Q84), IF(E84="Não",0,Q84+(Q84*$O$4)+R84+S84 )) -> 35126.258 | U84: =IF(D84>0,T84/D84,0) -> 209.08487 | V84: =IF(C84="CLT", I84*$M$2, 0) -> 672 | W84: =IF(C84="CLT", V84*$M$3, 0) -> 268.8 | X84: =IF(C84="CLT", I84/12, 0) -> 700 | Y84: =IF(C84="CLT", X84/3, 0) -> 233.33333 | Z84: =IF(C84="CLT", I84/12, 0) -> 700 | AA84: =IF(C84="CLT", I84*$S$2,0) -> 2310 | AB84: =IF(C84="CLT", SUM(X84:Z84) * $M$2,0) -> 130.66667 | AC84: =IF(C84="CLT", SUM(X84:Z84)*$S$2,0) -> 449.16667 | AD84: =IF(C84="CLT", I84/30*3, 0) -> 840 | AE84: =IF(C84="CLT", AD84*$M$2, 0) -> 67.2 | AF84: =IF(C84="CLT", I84*$M$4, 0) -> 756 | AH84: =IF(B84<>"", IF(C84="CLT", $Q$2, 0),0) -> 600 | AI84: =SUM(V84:AH84)+H84 -> 10587.167 | AJ84: =IF(E84="Sim", T84*$G$4, 0) -> 8079.0394 | AK84: =T84-AJ84-J84-R84 -> 8060.0523 | AL84: =(IF(AK84>0,AK84/T84,0)) -> 0.22945946 | AM84: =(IF(AK84>0,AK84/(T84-AJ84),0)) -> 0.2979993
... B125: Analista de Segurança da Informação Júnior | C125: CLT | D125: 168 | E125: Sim | F125: 0 | G125: =IF(F125>0,F125, IF(B125<>"", IF(C125="CLT",VLOOKUP(B125,'Lista Profissionais'!$C$11:$H$348,3,0), VLOOKUP(B125,'Lista Profissionais'!$C$11:$H$348,6,0)), 0)) -> 4400 | H125: =IF(B125<>"", IF(C125="CLT", 22*$M$5 + (G125*'Lista Profissionais'!$G$9),0),0) -> 1980 | I125: =(G125/$G$2)*D125 -> 4200 | J125: =I125+AI125 -> 10343.583 | K125: =J125+S125+AJ125 -> 14744.778 | L125: =IF(D125>0,J125/D125,0) -> 61.568948 | N125: 0 | O125: =J125*$G$6 -> 0 | P125: =IF(M125>0,M125, J125*(1+$G$5)) -> 19135.629 | Q125: =(P125+O125) -> 19135.629 | R125: =IF(E125="Sim", Q125*$G$3,0) -> 0 | S125: 0 | T125: =IF($D$4="Sim",(IF(E125="Não",0,(Q125+(Q125*$O$4)+R125+S125)*$D$5)+Q125), IF(E125="Não",0,Q125+(Q125*$O$4)+R125+S125 )) -> 19135.629 | U125: =IF(D125>0,T125/D125,0) -> 113.90255 | V125: =IF(C125="CLT", I125*$M$2, 0) -> 336 | W125: =IF(C125="CLT", V125*$M$3, 0) -> 134.4 | X125: =IF(C125="CLT", I125/12, 0) -> 350 | Y125: =IF(C125="CLT", X125/3, 0) -> 116.66667 | Z125: =IF(C125="CLT", I125/12, 0) -> 350 | AA125: =IF(C125="CLT", I125*$S$2,0) -> 1155 | AB125: =IF(C125="CLT", SUM(X125:Z125) * $M$2,0) -> 65.333333 | AC125: =IF(C125="CLT", SUM(X125:Z125)*$S$2,0) -> 224.58333 | AD125: =IF(C125="CLT", I125/30*3, 0) -> 420 | AE125: =IF(C125="CLT", AD125*$M$2, 0) -> 33.6 | AF125: =IF(C125="CLT", I125*$M$4, 0) -> 378 | AH125: =IF(B125<>"", IF(C125="CLT", $Q$2, 0),0) -> 600 | AI125: =SUM(V125:AH125)+H125 -> 6143.5833 | AJ125: =IF(E125="Sim", T125*$G$4, 0) -> 4401.1947 | AK125: =T125-AJ125-J125-R125 -> 4390.8511 | AL125: =(IF(AK125>0,AK125/T125,0)) -> 0.22945946 | AM125: =(IF(AK125>0,AK125/(T125-AJ125),0)) -> 0.2979993
B126: Analista de Segurança da Informação Pleno | C126: CLT | D126: 176 | E126: Sim | F126: 3100 | G126: =IF(F126>0,F126, IF(B126<>"", IF(C126="CLT",VLOOKUP(B126,'Lista Profissionais'!$C$11:$H$348,3,0), VLOOKUP(B126,'Lista Profissionais'!$C$11:$H$348,6,0)), 0)) -> 3100 | H126: =IF(B126<>"", IF(C126="CLT", 5*$M$5 + (G126*'Lista Profissionais'!$G$9),0),0) -> 870 | I126: =(G126/$G$2)*D126 -> 3100 | J126: =I126+AI126 -> 7457.2639 | K126: =J126+S126+AJ126 -> 10199.324 | L126: =IF(D126>0,J126/D126,0) -> 42.370818 | M126: 11922 | N126: 0 | O126: =J126*$G$6 -> 0 | P126: =IF(M126>0,M126, J126*(1+$G$5)) -> 11922 | Q126: =(P126+O126) -> 11922 | R126: =IF(E126="Sim", Q126*$G$3,0) -> 0 | S126: 0 | T126: =IF($D$4="Sim",(IF(E126="Não",0,(Q126+(Q126*$O$4)+R126+S126)*$D$5)+Q126), IF(E126="Não",0,Q126+(Q126*$O$4)+R126+S126 )) -> 11922 | U126: =IF(D126>0,T126/D126,0) -> 67.738636 | V126: =IF(C126="CLT", I126*$M$2, 0) -> 248 | W126: =IF(C126="CLT", V126*$M$3, 0) -> 99.2 | X126: =IF(C126="CLT", I126/12, 0) -> 258.33333 | Y126: =IF(C126="CLT", X126/3, 0) -> 86.111111 | Z126: =IF(C126="CLT", I126/12, 0) -> 258.33333 | AA126: =IF(C126="CLT", I126*$S$2,0) -> 852.5 | AB126: =IF(C126="CLT", SUM(X126:Z126) * $M$2,0) -> 48.222222 | AC126: =IF(C126="CLT", SUM(X126:Z126)*$S$2,0) -> 165.76389 | AD126: =IF(C126="CLT", I126/30*3, 0) -> 310 | AE126: =IF(C126="CLT", AD126*$M$2, 0) -> 24.8 | AF126: =IF(C126="CLT", I126*$M$4, 0) -> 279 | AG126: 257 | AH126: =IF(B126<>"", IF(C126="CLT", $Q$2, 0),0) -> 600 | AI126: =SUM(V126:AH126)+H126 -> 4357.2639 | AJ126: =IF(E126="Sim", T126*$G$4, 0) -> 2742.06 | AK126: =T126-AJ126-J126-R126 -> 1722.6761 | AL126: =(IF(AK126>0,AK126/T126,0)) -> 0.14449556 | AM126: =(IF(AK126>0,AK126/(T126-AJ126),0)) -> 0.18765658
B127: Analista de Segurança da Informação Sênior | C127: PJ | D127: 176 | E127: Sim | F127: 6920 | G127: =IF(F127>0,F127, IF(B127<>"", IF(C127="CLT",VLOOKUP(B127,'Lista Profissionais'!$C$11:$H$348,3,0), VLOOKUP(B127,'Lista Profissionais'!$C$11:$H$348,6,0)), 0)) -> 6920 | H127: =IF(B127<>"", IF(C127="CLT", 22*$M$5 + (G127*'Lista Profissionais'!$G$9),0),0) -> 0 | I127: =(G127/$G$2)*D127 -> 6920 | J127: =I127+AI127 -> 6920 | K127: =J127+S127+AJ127 -> 9662.06 | L127: =IF(D127>0,J127/D127,0) -> 39.318182 | M127: 11922 | N127: 0 | O127: =J127*$G$6 -> 0 | P127: =IF(M127>0,M127, J127*(1+$G$5)) -> 11922 | Q127: =(P127+O127) -> 11922 | R127: =IF(E127="Sim", Q127*$G$3,0) -> 0 | S127: 0 | T127: =IF($D$4="Sim",(IF(E127="Não",0,(Q127+(Q127*$O$4)+R127+S127)*$D$5)+Q127), IF(E127="Não",0,Q127+(Q127*$O$4)+R127+S127 )) -> 11922 | U127: =IF(D127>0,T127/D127,0) -> 67.738636 | V127: =IF(C127="CLT", I127*$M$2, 0) -> 0 | W127: =IF(C127="CLT", V127*$M$3, 0) -> 0 | X127: =IF(C127="CLT", I127/12, 0) -> 0 | Y127: =IF(C127="CLT", X127/3, 0) -> 0 | Z127: =IF(C127="CLT", I127/12, 0) -> 0 | AA127: =IF(C127="CLT", I127*$S$2,0) -> 0 | AB127: =IF(C127="CLT", SUM(X127:Z127) * $M$2,0) -> 0 | AC127: =IF(C127="CLT", SUM(X127:Z127)*$S$2,0) -> 0 | AD127: =IF(C127="CLT", I127/30*3, 0) -> 0 | AE127: =IF(C127="CLT", AD127*$M$2, 0) -> 0 | AF127: =IF(C127="CLT", I127*$M$4, 0) -> 0 | AH127: =IF(B127<>"", IF(C127="CLT", $Q$2, 0),0) -> 0 | AI127: =SUM(V127:AH127)+H127 -> 0 | AJ127: =IF(E127="Sim", T127*$G$4, 0) -> 2742.06 | AK127: =T127-AJ127-J127-R127 -> 2259.94 | AL127: =(IF(AK127>0,AK127/T127,0)) -> 0.18956048 | AM127: =(IF(AK127>0,AK127/(T127-AJ127),0)) -> 0.24618244
B128: Coordenador de T.I. Sênior | C128: CLT | D128: 168 | E128: Sim | F128: 0 | G128: =IF(F128>0,F128, IF(B128<>"", IF(C128="CLT",VLOOKUP(B128,'Lista Profissionais'!$C$11:$H$348,3,0), VLOOKUP(B128,'Lista Profissionais'!$C$11:$H$348,6,0)), 0)) -> 12000 | H128: =IF(B128<>"", IF(C128="CLT", 22*$M$5 + (G128*'Lista Profissionais'!$G$9),0),0) -> 3500 | I128: =(G128/$G$2)*D128 -> 11454.545 | J128: =I128+AI128 -> 25273.409 | K128: =J128+S128+AJ128 -> 36027.245 | L128: =IF(D128>0,J128/D128,0) -> 150.43696 | N128: 0 | O128: =J128*$G$6 -> 0 | P128: =IF(M128>0,M128, J128*(1+$G$5)) -> 46755.807 | Q128: =(P128+O128) -> 46755.807 | R128: =IF(E128="Sim", Q128*$G$3,0) -> 0 | S128: 0 | T128: =IF($D$4="Sim",(IF(E128="Não",0,(Q128+(Q128*$O$4)+R128+S128)*$D$5)+Q128), IF(E128="Não",0,Q128+(Q128*$O$4)+R128+S128 )) -> 46755.807 | U128: =IF(D128>0,T128/D128,0) -> 278.30837 | V128: =IF(C128="CLT", I128*$M$2, 0) -> 916.36364 | W128: =IF(C128="CLT", V128*$M$3, 0) -> 366.54545 | X128: =IF(C128="CLT", I128/12, 0) -> 954.54545 | Y128: =IF(C128="CLT", X128/3, 0) -> 318.18182 | Z128: =IF(C128="CLT", I128/12, 0) -> 954.54545 | AA128: =IF(C128="CLT", I128*$S$2,0) -> 3150 | AB128: =IF(C128="CLT", SUM(X128:Z128) * $M$2,0) -> 178.18182 | AC128: =IF(C128="CLT", SUM(X128:Z128)*$S$2,0) -> 612.5 | AD128: =IF(C128="CLT", I128/30*3, 0) -> 1145.4545 | AE128: =IF(C128="CLT", AD128*$M$2, 0) -> 91.636364 | AF128: =IF(C128="CLT", I128*$M$4, 0) -> 1030.9091 | AH128: =IF(B128<>"", IF(C128="CLT", $Q$2, 0),0) -> 600 | AI128: =SUM(V128:AH128)+H128 -> 13818.864 | AJ128: =IF(E128="Sim", T128*$G$4, 0) -> 10753.836 | AK128: =T128-AJ128-J128-R128 -> 10728.562 | AL128: =(IF(AK128>0,AK128/T128,0)) -> 0.22945946 | AM128: =(IF(AK128>0,AK128/(T128-AJ128),0)) -> 0.2979993
AC132: =2500/3 -> 833.33333 | AI132: 5
T133: =176*U126 -> 11922 | AI133: 51.4
AI134: =AI132*AI133 -> 257
H136: =(F72-16000)/16000 -> 0.09375

Sheet Rate Card PJ
E2: RESUMO | F2: Base horas mês | G2: 176 | I2: $ salários + encargos | J2: =SUBTOTAL(9,J9:J50008) -> 2062346 | L2: FGTS | M2: 0.08 | N2: Nº colab bilable | O2: =COUNTIF(E9:E5008, "Sim") -> 151 | P2: Valor convênio | Q2: 600 | R2: INSS+RAT+TERC | S2: 0.275 | W2: Ajustes do cálculo CLT que precisamos ajustar em todas tabelas
C3: modelo | D3: CLT | F3: % Comissão vend. | G3: 0.03 | I3: $ faturamento | J3: =SUBTOTAL(9,T9:T50008) -> 4036011.1 | L3: FGTS Multa | M3: 0.4 | N3: Nº colab no bilable | O3: =COUNTIF(E9:E5008, "Não") -> 0 | P3: Valor comissão | Q3: =SUBTOTAL(9,R9:R54) -> 27299.922 | W3: Ok
C4: Híbrido | D4: Não | F4: % Imposto NF | G4: 0.23 | I4: $ Custos | J4: =SUBTOTAL(9,K9:K5008)+Q3 -> 3017928.5 | L4: INSS | M4: 0.09 | N4: % Rateio no Bilable | O4: 0 | P4: Soma de horas | Q4: =SUBTOTAL(9,D9:D5008) -> 26576 | W4: Incluídos
C5: Perc.Hib. | D5: 0 | G5: 0.9 | I5: $ lucratividade | J5: =J3-J4 -> 1018082.6 | L5: Ticket Rest. Dia | M5: 25 | N5: Total Billable | O5: =L12 -> 84.943182 | P5: hora média | Q5: =J3/Q4 -> 151.86676 | W5: Alterados
F6: Taxa de risco | G6: 0 | I6: % lucro real | J6: =J5/J3 -> 0.25224971 | L6: Tarifa média hr. | M6: =SUM(T9:T5008)/SUM(D9:D5008) -> 151.86676 | N6: Total No Bilable | O6: =SUMIF(E9:E5008,"Não",Q9:Q5008) -> 0 | W6: Remover
B7: CONFIGURAÇÃO EQUIPE | C7: CONFIG RECURSO | F7: C U S T O S C O M C O L A B O R A D O R E S | M7: T A R I F A / F A T U R A M E N T O | V7: C U S T O S C L T | AI7: IMPOSTOS | AJ7: LUCRATIVIDADE
B8: Necessidade cliente | C8: Reg | D8: H.trab | E8: Billable | F8: $ Negociado/salário | G8: $ salário cheio | H8: Vale Refeição/Alimentação | I8: $ Salário real | J8: $ Custo Colab | K8: $ Custo colab + Imp | L8: Custo hora | M8: $ Tarifa negociada | N8: Markup | O8: $ Risco | P8: $ Tarifa | Q8: $ Tar. calculada | R8: $ Comissão | S8: Loc. Equip. | T8: $ Tarifa bilable | U8: Valor hora | V8: FGTS | W8: FGTS multa | X8: Férias | Y8: 1/3 férias | Z8: 13º salário | AA8: INSS+RAT+TERC | AB8: FGTS sobre 13º e Férias | AC8: INSS+RAT+Terc (13º e Fér) | AD8: Aviso Remuner | AE8: FGTS Sobre Aviso | AF8: INSS | AG8: Convênio | AH8: $ Total Encargos | AI8: Imposto Nota | AJ8: $ lucro | AK8: % Lucro | AL8: Marg Contrib
B9: Agilista Especialista | C9: PJ | D9: 176 | E9: Sim | F9: 0 | G9: =IF(F9>0,F9, IF(B9<>"", IF(C9="CLT",VLOOKUP(B9,'Lista Profissionais'!$C$11:$H$348,3,0), VLOOKUP(B9,'Lista Profissionais'!$C$11:$H$348,6,0)), 0)) -> 17550 | H9: =IF(B9<>"", IF(C9="CLT", 22*$M$5 + (G9*'Lista Profissionais'!$G$9),0),0) -> 0 | I9: =(G9/$G$2)*D9 -> 17550 | J9: =I9+AH9 -> 17550 | K9: =J9+S9+AI9 -> 25449.431 | L9: =IF(D9>0,J9/D9,0) -> 99.715909 | N9: 0 | O9: =J9*$G$6 -> 0 | P9: =IF(M9>0,M9, J9*(1+$G$5)) -> 33345 | Q9: =(P9+O9) -> 33345 | R9: =IF(E9="Sim", Q9*$G$3,0) -> 1000.35 | S9: 0 | T9: =IF($D$4="Sim",(IF(E9="Não",0,(Q9+(Q9*$O$4)+R9+S9)*$D$5)+Q9), IF(E9="Não",0,Q9+(Q9*$O$4)+R9+S9 )) -> 34345.35 | U9: =IF(D9>0,T9/D9,0) -> 195.14403 | V9: =IF(C9="CLT", I9*$M$2, 0) -> 0 | W9: =IF(C9="CLT", V9*$M$3, 0) -> 0 | X9: =IF(C9="CLT", I9/12, 0) -> 0 | Y9: =IF(C9="CLT", X9/3, 0) -> 0 | Z9: =IF(C9="CLT", I9/12, 0) -> 0 | AA9: =IF(C9="CLT", I9*$S$2,0) -> 0 | AB9: =IF(C9="CLT", SUM(X9:Z9) * $M$2,0) -> 0 | AC9: =IF(C9="CLT", SUM(X9:Z9)*$S$2,0) -> 0 | AD9: =IF(C9="CLT", I9/30*3, 0) -> 0 | AE9: =IF(C9="CLT", AD9*$M$2, 0) -> 0 | AF9: =IF(C9="CLT", I9*$M$4, 0) -> 0 | AG9: =IF(B9<>"", IF(C9="CLT", $Q$2, 0),0) -> 0 | AH9: =SUM(V9:AG9)+H9 -> 0 | AI9: =IF(E9="Sim", T9*$G$4, 0) -> 7899.4305 | AJ9: =T9-AI9-J9-R9 -> 7895.5695 | AK9: =(IF(AJ9>0,AJ9/T9,0)) -> 0.22988758 | AL9: =(IF(AJ9>0,AJ9/(T9-AI9),0)) -> 0.2985553
B10: Agilista - Junior Júnior | C10: PJ | D10: 176 | E10: Sim | F10: 0 | G10: =IF(F10>0,F10, IF(B10<>"", IF(C10="CLT",VLOOKUP(B10,'Lista Profissionais'!$C$11:$H$348,3,0), VLOOKUP(B10,'Lista Profissionais'!$C$11:$H$348,6,0)), 0)) -> 6370 | H10: =IF(B10<>"", IF(C10="CLT", 22*$M$5 + (G10*'Lista Profissionais'!$G$9),0),0) -> 0 | I10: =(G10/$G$2)*D10 -> 6370 | J10: =I10+AH10 -> 6370 | K10: =J10+S10+AI10 -> 9237.2007 | L10: =IF(D10>0,J10/D10,0) -> 36.193182 | N10: 0 | O10: =J10*$G$6 -> 0 | P10: =IF(M10>0,M10, J10*(1+$G$5)) -> 12103 | Q10: =(P10+O10) -> 12103 | R10: =IF(E10="Sim", Q10*$G$3,0) -> 363.09 | S10: 0 | T10: =IF($D$4="Sim",(IF(E10="Não",0,(Q10+(Q10*$O$4)+R10+S10)*$D$5)+Q10), IF(E10="Não",0,Q10+(Q10*$O$4)+R10+S10 )) -> 12466.09 | U10: =IF(D10>0,T10/D10,0) -> 70.830057 | V10: =IF(C10="CLT", I10*$M$2, 0) -> 0 | W10: =IF(C10="CLT", V10*$M$3, 0) -> 0 | X10: =IF(C10="CLT", I10/12, 0) -> 0 | Y10: =IF(C10="CLT", X10/3, 0) -> 0 | Z10: =IF(C10="CLT", I10/12, 0) -> 0 | AA10: =IF(C10="CLT", I10*$S$2,0) -> 0 | AB10: =IF(C10="CLT", SUM(X10:Z10) * $M$2,0) -> 0 | AC10: =IF(C10="CLT", SUM(X10:Z10)*$S$2,0) -> 0 | AD10: =IF(C10="CLT", I10/30*3, 0) -> 0 | AE10: =IF(C10="CLT", AD10*$M$2, 0) -> 0 | AF10: =IF(C10="CLT", I10*$M$4, 0) -> 0 | AG10: =IF(B10<>"", IF(C10="CLT", $Q$2, 0),0) -> 0 | AH10: =SUM(V10:AG10)+H10 -> 0 | AI10: =IF(E10="Sim", T10*$G$4, 0) -> 2867.2007 | AJ10: =T10-AI10-J10-R10 -> 2865.7993 | AK10: =(IF(AJ10>0,AJ10/T10,0)) -> 0.22988758 | AL10: =(IF(AJ10>0,AJ10/(T10-AI10),0)) -> 0.2985553
B11: Agilista Pleno | C11: PJ | D11: 176 | E11: Sim | F11: 0 | G11: =IF(F11>0,F11, IF(B11<>"", IF(C11="CLT",VLOOKUP(B11,'Lista Profissionais'!$C$11:$H$348,3,0), VLOOKUP(B11,'Lista Profissionais'!$C$11:$H$348,6,0)), 0)) -> 10270 | H11: =IF(B11<>"", IF(C11="CLT", 22*$M$5 + (G11*'Lista Profissionais'!$G$9),0),0) -> 0 | I11: =(G11/$G$2)*D11 -> 10270 | J11: =I11+AH11 -> 10270 | K11: =J11+S11+AI11 -> 14892.63 | L11: =IF(D11>0,J11/D11,0) -> 58.352273 | N11: 0 | O11: =J11*$G$6 -> 0 | P11: =IF(M11>0,M11, J11*(1+$G$5)) -> 19513 | Q11: =(P11+O11) -> 19513 | R11: =IF(E11="Sim", Q11*$G$3,0) -> 585.39 | S11: 0 | T11: =IF($D$4="Sim",(IF(E11="Não",0,(Q11+(Q11*$O$4)+R11+S11)*$D$5)+Q11), IF(E11="Não",0,Q11+(Q11*$O$4)+R11+S11 )) -> 20098.39 | U11: =IF(D11>0,T11/D11,0) -> 114.1954 | V11: =IF(C11="CLT", I11*$M$2, 0) -> 0 | W11: =IF(C11="CLT", V11*$M$3, 0) -> 0 | X11: =IF(C11="CLT", I11/12, 0) -> 0 | Y11: =IF(C11="CLT", X11/3, 0) -> 0 | Z11: =IF(C11="CLT", I11/12, 0) -> 0 | AA11: =IF(C11="CLT", I11*$S$2,0) -> 0 | AB11: =IF(C11="CLT", SUM(X11:Z11) * $M$2,0) -> 0 | AC11: =IF(C11="CLT", SUM(X11:Z11)*$S$2,0) -> 0 | AD11: =IF(C11="CLT", I11/30*3, 0) -> 0 | AE11: =IF(C11="CLT", AD11*$M$2, 0) -> 0 | AF11: =IF(C11="CLT", I11*$M$4, 0) -> 0 | AG11: =IF(B11<>"", IF(C11="CLT", $Q$2, 0),0) -> 0 | AH11: =SUM(V11:AG11)+H11 -> 0 | AI11: =IF(E11="Sim", T11*$G$4, 0) -> 4622.6297 | AJ11: =T11-AI11-J11-R11 -> 4620.3703 | AK11: =(IF(AJ11>0,AJ11/T11,0)) -> 0.22988758 | AL11: =(IF(AJ11>0,AJ11/(T11-AI11),0)) -> 0.2985553
B12: Agilista Sênior | C12: PJ | D12: 176 | E12: Sim | F12: 0 | G12: =IF(F12>0,F12, IF(B12<>"", IF(C12="CLT",VLOOKUP(B12,'Lista Profissionais'!$C$11:$H$348,3,0), VLOOKUP(B12,'Lista Profissionais'!$C$11:$H$348,6,0)), 0)) -> 14950 | H12: =IF(B12<>"", IF(C12="CLT", 22*$M$5 + (G12*'Lista Profissionais'!$G$9),0),0) -> 0 | I12: =(G12/$G$2)*D12 -> 14950 | J12: =I12+AH12 -> 14950 | K12: =J12+S12+AI12 -> 21679.145 | L12: =IF(D12>0,J12/D12,0) -> 84.943182 | N12: 0 | O12: =J12*$G$6 -> 0 | P12: =IF(M12>0,M12, J12*(1+$G$5)) -> 28405 | Q12: =(P12+O12) -> 28405 | R12: =IF(E12="Sim", Q12*$G$3,0) -> 852.15 | S12: 0 | T12: =IF($D$4="Sim",(IF(E12="Não",0,(Q12+(Q12*$O$4)+R12+S12)*$D$5)+Q12), IF(E12="Não",0,Q12+(Q12*$O$4)+R12+S12 )) -> 29257.15 | U12: =IF(D12>0,T12/D12,0) -> 166.23381 | V12: =IF(C12="CLT", I12*$M$2, 0) -> 0 | W12: =IF(C12="CLT", V12*$M$3, 0) -> 0 | X12: =IF(C12="CLT", I12/12, 0) -> 0 | Y12: =IF(C12="CLT", X12/3, 0) -> 0 | Z12: =IF(C12="CLT", I12/12, 0) -> 0 | AA12: =IF(C12="CLT", I12*$S$2,0) -> 0 | AB12: =IF(C12="CLT", SUM(X12:Z12) * $M$2,0) -> 0 | AC12: =IF(C12="CLT", SUM(X12:Z12)*$S$2,0) -> 0 | AD12: =IF(C12="CLT", I12/30*3, 0) -> 0 | AE12: =IF(C12="CLT", AD12*$M$2, 0) -> 0 | AF12: =IF(C12="CLT", I12*$M$4, 0) -> 0 | AG12: =IF(B12<>"", IF(C12="CLT", $Q$2, 0),0) -> 0 | AH12: =SUM(V12:AG12)+H12 -> 0 | AI12: =IF(E12="Sim", T12*$G$4, 0) -> 6729.1445 | AJ12: =T12-AI12-J12-R12 -> 6725.8555 | AK12: =(IF(AJ12>0,AJ12/T12,0)) -> 0.22988758 | AL12: =(IF(AJ12>0,AJ12/(T12-AI12),0)) -> 0.2985553
B13: Analista de Dados/ BI Especialista | C13: PJ | D13: 176 | E13: Sim | F13: 0 | G13: =IF(F13>0,F13, IF(B13<>"", IF(C13="CLT",VLOOKUP(B13,'Lista Profissionais'!$C$11:$H$348,3,0), VLOOKUP(B13,'Lista Profissionais'!$C$11:$H$348,6,0)), 0)) -> 14300 | H13: =IF(B13<>"", IF(C13="CLT", 22*$M$5 + (G13*'Lista Profissionais'!$G$9),0),0) -> 0 | I13: =(G13/$G$2)*D13 -> 14300 | J13: =I13+AH13 -> 14300 | K13: =J13+S13+AI13 -> 20736.573 | L13: =IF(D13>0,J13/D13,0) -> 81.25 | N13: 0 | O13: =J13*$G$6 -> 0 | P13: =IF(M13>0,M13, J13*(1+$G$5)) -> 27170 | Q13: =(P13+O13) -> 27170 | R13: =IF(E13="Sim", Q13*$G$3,0) -> 815.1 | S13: 0 | T13: =IF($D$4="Sim",(IF(E13="Não",0,(Q13+(Q13*$O$4)+R13+S13)*$D$5)+Q13), IF(E13="Não",0,Q13+(Q13*$O$4)+R13+S13 )) -> 27985.1 | U13: =IF(D13>0,T13/D13,0) -> 159.00625 | V13: =IF(C13="CLT", I13*$M$2, 0) -> 0 | W13: =IF(C13="CLT", V13*$M$3, 0) -> 0 | X13: =IF(C13="CLT", I13/12, 0) -> 0 | Y13: =IF(C13="CLT", X13/3, 0) -> 0 | Z13: =IF(C13="CLT", I13/12, 0) -> 0 | AA13: =IF(C13="CLT", I13*$S$2,0) -> 0 | AB13: =IF(C13="CLT", SUM(X13:Z13) * $M$2,0) -> 0 | AC13: =IF(C13="CLT", SUM(X13:Z13)*$S$2,0) -> 0 | AD13: =IF(C13="CLT", I13/30*3, 0) -> 0 | AE13: =IF(C13="CLT", AD13*$M$2, 0) -> 0 | AF13: =IF(C13="CLT", I13*$M$4, 0) -> 0 | AG13: =IF(B13<>"", IF(C13="CLT", $Q$2, 0),0) -> 0 | AH13: =SUM(V13:AG13)+H13 -> 0 | AI13: =IF(E13="Sim", T13*$G$4, 0) -> 6436.573 | AJ13: =T13-AI13-J13-R13 -> 6433.427 | AK13: =(IF(AJ13>0,AJ13/T13,0)) -> 0.22988758 | AL13: =(IF(AJ13>0,AJ13/(T13-AI13),0)) -> 0.2985553
B14: Analista de Dados/ BI Júnior | C14: PJ | D14: 176 | E14: Sim | F14: 0 | G14: =IF(F14>0,F14, IF(B14<>"", IF(C14="CLT",VLOOKUP(B14,'Lista Profissionais'!$C$11:$H$348,3,0), VLOOKUP(B14,'Lista Profissionais'!$C$11:$H$348,6,0)), 0)) -> 5460 | H14: =IF(B14<>"", IF(C14="CLT", 22*$M$5 + (G14*'Lista Profissionais'!$G$9),0),0) -> 0 | I14: =(G14/$G$2)*D14 -> 5460 | J14: =I14+AH14 -> 5460 | K14: =J14+S14+AI14 -> 7917.6006 | L14: =IF(D14>0,J14/D14,0) -> 31.022727 | N14: 0 | O14: =J14*$G$6 -> 0 | P14: =IF(M14>0,M14, J14*(1+$G$5)) -> 10374 | Q14: =(P14+O14) -> 10374 | R14: =IF(E14="Sim", Q14*$G$3,0) -> 311.22 | S14: 0 | T14: =IF($D$4="Sim",(IF(E14="Não",0,(Q14+(Q14*$O$4)+R14+S14)*$D$5)+Q14), IF(E14="Não",0,Q14+(Q14*$O$4)+R14+S14 )) -> 10685.22 | U14: =IF(D14>0,T14/D14,0) -> 60.711477 | V14: =IF(C14="CLT", I14*$M$2, 0) -> 0 | W14: =IF(C14="CLT", V14*$M$3, 0) -> 0 | X14: =IF(C14="CLT", I14/12, 0) -> 0 | Y14: =IF(C14="CLT", X14/3, 0) -> 0 | Z14: =IF(C14="CLT", I14/12, 0) -> 0 | AA14: =IF(C14="CLT", I14*$S$2,0) -> 0 | AB14: =IF(C14="CLT", SUM(X14:Z14) * $M$2,0) -> 0 | AC14: =IF(C14="CLT", SUM(X14:Z14)*$S$2,0) -> 0 | AD14: =IF(C14="CLT", I14/30*3, 0) -> 0 | AE14: =IF(C14="CLT", AD14*$M$2, 0) -> 0 | AF14: =IF(C14="CLT", I14*$M$4, 0) -> 0 | AG14: =IF(B14<>"", IF(C14="CLT", $Q$2, 0),0) -> 0 | AH14: =SUM(V14:AG14)+H14 -> 0 | AI14: =IF(E14="Sim", T14*$G$4, 0) -> 2457.6006 | AJ14: =T14-AI14-J14-R14 -> 2456.3994 | AK14: =(IF(AJ14>0,AJ14/T14,0)) -> 0.22988758 | AL14: =(IF(AJ14>0,AJ14/(T14-AI14),0)) -> 0.2985553
B15: Analista de Dados/ BI Pleno | C15: PJ | D15: 176 | E15: Sim | F15: 0 | G15: =IF(F15>0,F15, IF(B15<>"", IF(C15="CLT",VLOOKUP(B15,'Lista Profissionais'!$C$11:$H$348,3,0), VLOOKUP(B15,'Lista Profissionais'!$C$11:$H$348,6,0)), 0)) -> 9750 | H15: =IF(B15<>"", IF(C15="CLT", 22*$M$5 + (G15*'Lista Profissionais'!$G$9),0),0) -> 0 | I15: =(G15/$G$2)*D15 -> 9750 | J15: =I15+AH15 -> 9750 | K15: =J15+S15+AI15 -> 14138.573 | L15: =IF(D15>0,J15/D15,0) -> 55.397727 | N15: 0 | O15: =J15*$G$6 -> 0 | P15: =IF(M15>0,M15, J15*(1+$G$5)) -> 18525 | Q15: =(P15+O15) -> 18525 | R15: =IF(E15="Sim", Q15*$G$3,0) -> 555.75 | S15: 0 | T15: =IF($D$4="Sim",(IF(E15="Não",0,(Q15+(Q15*$O$4)+R15+S15)*$D$5)+Q15), IF(E15="Não",0,Q15+(Q15*$O$4)+R15+S15 )) -> 19080.75 | U15: =IF(D15>0,T15/D15,0) -> 108.41335 | V15: =IF(C15="CLT", I15*$M$2, 0) -> 0 | W15: =IF(C15="CLT", V15*$M$3, 0) -> 0 | X15: =IF(C15="CLT", I15/12, 0) -> 0 | Y15: =IF(C15="CLT", X15/3, 0) -> 0 | Z15: =IF(C15="CLT", I15/12, 0) -> 0 | AA15: =IF(C15="CLT", I15*$S$2,0) -> 0 | AB15: =IF(C15="CLT", SUM(X15:Z15) * $M$2,0) -> 0 | AC15: =IF(C15="CLT", SUM(X15:Z15)*$S$2,0) -> 0 | AD15: =IF(C15="CLT", I15/30*3, 0) -> 0 | AE15: =IF(C15="CLT", AD15*$M$2, 0) -> 0 | AF15: =IF(C15="CLT", I15*$M$4, 0) -> 0 | AG15: =IF(B15<>"", IF(C15="CLT", $Q$2, 0),0) -> 0 | AH15: =SUM(V15:AG15)+H15 -> 0 | AI15: =IF(E15="Sim", T15*$G$4, 0) -> 4388.5725 | AJ15: =T15-AI15-J15-R15 -> 4386.4275 | AK15: =(IF(AJ15>0,AJ15/T15,0)) -> 0.22988758 | AL15: =(IF(AJ15>0,AJ15/(T15-AI15),0)) -> 0.2985553
B16: Analista de Dados/ BI Sênior | C16: PJ | D16: 176 | E16: Sim | F16: 0 | G16: =IF(F16>0,F16, IF(B16<>"", IF(C16="CLT",VLOOKUP(B16,'Lista Profissionais'!$C$11:$H$348,3,0), VLOOKUP(B16,'Lista Profissionais'!$C$11:$H$348,6,0)), 0)) -> 12350 | H16: =IF(B16<>"", IF(C16="CLT", 22*$M$5 + (G16*'Lista Profissionais'!$G$9),0),0) -> 0 | I16: =(G16/$G$2)*D16 -> 12350 | J16: =I16+AH16 -> 12350 | K16: =J16+S16+AI16 -> 17908.859 | L16: =IF(D16>0,J16/D16,0) -> 70.170455 | N16: 0 | O16: =J16*$G$6 -> 0 | P16: =IF(M16>0,M16, J16*(1+$G$5)) -> 23465 | Q16: =(P16+O16) -> 23465 | R16: =IF(E16="Sim", Q16*$G$3,0) -> 703.95 | S16: 0 | T16: =IF($D$4="Sim",(IF(E16="Não",0,(Q16+(Q16*$O$4)+R16+S16)*$D$5)+Q16), IF(E16="Não",0,Q16+(Q16*$O$4)+R16+S16 )) -> 24168.95 | U16: =IF(D16>0,T16/D16,0) -> 137.32358 | V16: =IF(C16="CLT", I16*$M$2, 0) -> 0 | W16: =IF(C16="CLT", V16*$M$3, 0) -> 0 | X16: =IF(C16="CLT", I16/12, 0) -> 0 | Y16: =IF(C16="CLT", X16/3, 0) -> 0 | Z16: =IF(C16="CLT", I16/12, 0) -> 0 | AA16: =IF(C16="CLT", I16*$S$2,0) -> 0 | AB16: =IF(C16="CLT", SUM(X16:Z16) * $M$2,0) -> 0 | AC16: =IF(C16="CLT", SUM(X16:Z16)*$S$2,0) -> 0 | AD16: =IF(C16="CLT", I16/30*3, 0) -> 0 | AE16: =IF(C16="CLT", AD16*$M$2, 0) -> 0 | AF16: =IF(C16="CLT", I16*$M$4, 0) -> 0 | AG16: =IF(B16<>"", IF(C16="CLT", $Q$2, 0),0) -> 0 | AH16: =SUM(V16:AG16)+H16 -> 0 | AI16: =IF(E16="Sim", T16*$G$4, 0) -> 5558.8585 | AJ16: =T16-AI16-J16-R16 -> 5556.1415 | AK16: =(IF(AJ16>0,AJ16/T16,0)) -> 0.22988758 | AL16: =(IF(AJ16>0,AJ16/(T16-AI16),0)) -> 0.2985553
B17: Analista de Inteligência Artificial Especialista | C17: PJ | D17: 176 | E17: Sim | F17: 0 | G17: =IF(F17>0,F17, IF(B17<>"", IF(C17="CLT",VLOOKUP(B17,'Lista Profissionais'!$C$11:$H$348,3,0), VLOOKUP(B17,'Lista Profissionais'!$C$11:$H$348,6,0)), 0)) -> 17550 | H17: =IF(B17<>"", IF(C17="CLT", 22*$M$5 + (G17*'Lista Profissionais'!$G$9),0),0) -> 0 | I17: =(G17/$G$2)*D17 -> 17550 | J17: =I17+AH17 -> 17550 | K17: =J17+S17+AI17 -> 25449.431 | L17: =IF(D17>0,J17/D17,0) -> 99.715909 | N17: 0 | O17: =J17*$G$6 -> 0 | P17: =IF(M17>0,M17, J17*(1+$G$5)) -> 33345 | Q17: =(P17+O17) -> 33345 | R17: =IF(E17="Sim", Q17*$G$3,0) -> 1000.35 | S17: 0 | T17: =IF($D$4="Sim",(IF(E17="Não",0,(Q17+(Q17*$O$4)+R17+S17)*$D$5)+Q17), IF(E17="Não",0,Q17+(Q17*$O$4)+R17+S17 )) -> 34345.35 | U17: =IF(D17>0,T17/D17,0) -> 195.14403 | V17: =IF(C17="CLT", I17*$M$2, 0) -> 0 | W17: =IF(C17="CLT", V17*$M$3, 0) -> 0 | X17: =IF(C17="CLT", I17/12, 0) -> 0 | Y17: =IF(C17="CLT", X17/3, 0) -> 0 | Z17: =IF(C17="CLT", I17/12, 0) -> 0 | AA17: =IF(C17="CLT", I17*$S$2,0) -> 0 | AB17: =IF(C17="CLT", SUM(X17:Z17) * $M$2,0) -> 0 | AC17: =IF(C17="CLT", SUM(X17:Z17)*$S$2,0) -> 0 | AD17: =IF(C17="CLT", I17/30*3, 0) -> 0 | AE17: =IF(C17="CLT", AD17*$M$2, 0) -> 0 | AF17: =IF(C17="CLT", I17*$M$4, 0) -> 0 | AG17: =IF(B17<>"", IF(C17="CLT", $Q$2, 0),0) -> 0 | AH17: =SUM(V17:AG17)+H17 -> 0 | AI17: =IF(E17="Sim", T17*$G$4, 0) -> 7899.4305 | AJ17: =T17-AI17-J17-R17 -> 7895.5695 | AK17: =(IF(AJ17>0,AJ17/T17,0)) -> 0.22988758 | AL17: =(IF(AJ17>0,AJ17/(T17-AI17),0)) -> 0.2985553
B18: Analista de Inteligência Artificial Júnior | C18: PJ | D18: 176 | E18: Sim | F18: 0 | G18: =IF(F18>0,F18, IF(B18<>"", IF(C18="CLT",VLOOKUP(B18,'Lista Profissionais'!$C$11:$H$348,3,0), VLOOKUP(B18,'Lista Profissionais'!$C$11:$H$348,6,0)), 0)) -> 6370 | H18: =IF(B18<>"", IF(C18="CLT", 22*$M$5 + (G18*'Lista Profissionais'!$G$9),0),0) -> 0 | I18: =(G18/$G$2)*D18 -> 6370 | J18: =I18+AH18 -> 6370 | K18: =J18+S18+AI18 -> 9237.2007 | L18: =IF(D18>0,J18/D18,0) -> 36.193182 | N18: 0 | O18: =J18*$G$6 -> 0 | P18: =IF(M18>0,M18, J18*(1+$G$5)) -> 12103 | Q18: =(P18+O18) -> 12103 | R18: =IF(E18="Sim", Q18*$G$3,0) -> 363.09 | S18: 0 | T18: =IF($D$4="Sim",(IF(E18="Não",0,(Q18+(Q18*$O$4)+R18+S18)*$D$5)+Q18), IF(E18="Não",0,Q18+(Q18*$O$4)+R18+S18 )) -> 12466.09 | U18: =IF(D18>0,T18/D18,0) -> 70.830057 | V18: =IF(C18="CLT", I18*$M$2, 0) -> 0 | W18: =IF(C18="CLT", V18*$M$3, 0) -> 0 | X18: =IF(C18="CLT", I18/12, 0) -> 0 | Y18: =IF(C18="CLT", X18/3, 0) -> 0 | Z18: =IF(C18="CLT", I18/12, 0) -> 0 | AA18: =IF(C18="CLT", I18*$S$2,0) -> 0 | AB18: =IF(C18="CLT", SUM(X18:Z18) * $M$2,0) -> 0 | AC18: =IF(C18="CLT", SUM(X18:Z18)*$S$2,0) -> 0 | AD18: =IF(C18="CLT", I18/30*3, 0) -> 0 | AE18: =IF(C18="CLT", AD18*$M$2, 0) -> 0 | AF18: =IF(C18="CLT", I18*$M$4, 0) -> 0 | AG18: =IF(B18<>"", IF(C18="CLT", $Q$2, 0),0) -> 0 | AH18: =SUM(V18:AG18)+H18 -> 0 | AI18: =IF(E18="Sim", T18*$G$4, 0) -> 2867.2007 | AJ18: =T18-AI18-J18-R18 -> 2865.7993 | AK18: =(IF(AJ18>0,AJ18/T18,0)) -> 0.22988758 | AL18: =(IF(AJ18>0,AJ18/(T18-AI18),0)) -> 0.2985553
B19: Analista de Inteligência Artificial Pleno | C19: PJ | D19: 176 | E19: Sim | F19: 0 | G19: =IF(F19>0,F19, IF(B19<>"", IF(C19="CLT",VLOOKUP(B19,'Lista Profissionais'!$C$11:$H$348,3,0), VLOOKUP(B19,'Lista Profissionais'!$C$11:$H$348,6,0)), 0)) -> 9750 | H19: =IF(B19<>"", IF(C19="CLT", 22*$M$5 + (G19*'Lista Profissionais'!$G$9),0),0) -> 0 | I19: =(G19/$G$2)*D19 -> 9750 | J19: =I19+AH19 -> 9750 | K19: =J19+S19+AI19 -> 14138.573 | L19: =IF(D19>0,J19/D19,0) -> 55.397727 | N19: 0 | O19: =J19*$G$6 -> 0 | P19: =IF(M19>0,M19, J19*(1+$G$5)) -> 18525 | Q19: =(P19+O19) -> 18525 | R19: =IF(E19="Sim", Q19*$G$3,0) -> 555.75 | S19: 0 | T19: =IF($D$4="Sim",(IF(E19="Não",0,(Q19+(Q19*$O$4)+R19+S19)*$D$5)+Q19), IF(E19="Não",0,Q19+(Q19*$O$4)+R19+S19 )) -> 19080.75 | U19: =IF(D19>0,T19/D19,0) -> 108.41335 | V19: =IF(C19="CLT", I19*$M$2, 0) -> 0 | W19: =IF(C19="CLT", V19*$M$3, 0) -> 0 | X19: =IF(C19="CLT", I19/12, 0) -> 0 | Y19: =IF(C19="CLT", X19/3, 0) -> 0 | Z19: =IF(C19="CLT", I19/12, 0) -> 0 | AA19: =IF(C19="CLT", I19*$S$2,0) -> 0 | AB19: =IF(C19="CLT", SUM(X19:Z19) * $M$2,0) -> 0 | AC19: =IF(C19="CLT", SUM(X19:Z19)*$S$2,0) -> 0 | AD19: =IF(C19="CLT", I19/30*3, 0) -> 0 | AE19: =IF(C19="CLT", AD19*$M$2, 0) -> 0 | AF19: =IF(C19="CLT", I19*$M$4, 0) -> 0 | AG19: =IF(B19<>"", IF(C19="CLT", $Q$2, 0),0) -> 0 | AH19: =SUM(V19:AG19)+H19 -> 0 | AI19: =IF(E19="Sim", T19*$G$4, 0) -> 4388.5725 | AJ19: =T19-AI19-J19-R19 -> 4386.4275 | AK19: =(IF(AJ19>0,AJ19/T19,0)) -> 0.22988758 | AL19: =(IF(AJ19>0,AJ19/(T19-AI19),0)) -> 0.2985553
B20: Analista de Inteligência Artificial Sênior | C20: PJ | D20: 176 | E20: Sim | F20: 0 | G20: =IF(F20>0,F20, IF(B20<>"", IF(C20="CLT",VLOOKUP(B20,'Lista Profissionais'!$C$11:$H$348,3,0), VLOOKUP(B20,'Lista Profissionais'!$C$11:$H$348,6,0)), 0)) -> 14300 | H20: =IF(B20<>"", IF(C20="CLT", 22*$M$5 + (G20*'Lista Profissionais'!$G$9),0),0) -> 0 | I20: =(G20/$G$2)*D20 -> 14300 | J20: =I20+AH20 -> 14300 | K20: =J20+S20+AI20 -> 20736.573 | L20: =IF(D20>0,J20/D20,0) -> 81.25 | N20: 0 | O20: =J20*$G$6 -> 0 | P20: =IF(M20>0,M20, J20*(1+$G$5)) -> 27170 | Q20: =(P20+O20) -> 27170 | R20: =IF(E20="Sim", Q20*$G$3,0) -> 815.1 | S20: 0 | T20: =IF($D$4="Sim",(IF(E20="Não",0,(Q20+(Q20*$O$4)+R20+S20)*$D$5)+Q20), IF(E20="Não",0,Q20+(Q20*$O$4)+R20+S20 )) -> 27985.1 | U20: =IF(D20>0,T20/D20,0) -> 159.00625 | V20: =IF(C20="CLT", I20*$M$2, 0) -> 0 | W20: =IF(C20="CLT", V20*$M$3, 0) -> 0 | X20: =IF(C20="CLT", I20/12, 0) -> 0 | Y20: =IF(C20="CLT", X20/3, 0) -> 0 | Z20: =IF(C20="CLT", I20/12, 0) -> 0 | AA20: =IF(C20="CLT", I20*$S$2,0) -> 0 | AB20: =IF(C20="CLT", SUM(X20:Z20) * $M$2,0) -> 0 | AC20: =IF(C20="CLT", SUM(X20:Z20)*$S$2,0) -> 0 | AD20: =IF(C20="CLT", I20/30*3, 0) -> 0 | AE20: =IF(C20="CLT", AD20*$M$2, 0) -> 0 | AF20: =IF(C20="CLT", I20*$M$4, 0) -> 0 | AG20: =IF(B20<>"", IF(C20="CLT", $Q$2, 0),0) -> 0 | AH20: =SUM(V20:AG20)+H20 -> 0 | AI20: =IF(E20="Sim", T20*$G$4, 0) -> 6436.573 | AJ20: =T20-AI20-J20-R20 -> 6433.427 | AK20: =(IF(AJ20>0,AJ20/T20,0)) -> 0.22988758 | AL20: =(IF(AJ20>0,AJ20/(T20-AI20),0)) -> 0.2985553
... B159: Especialista DQ / DQA Especialista | C159: PJ | D159: 176 | E159: Sim | F159: 0 | G159: =IF(F159>0,F159, IF(B159<>"", IF(C159="CLT",VLOOKUP(B159,'Lista Profissionais'!$C$11:$H$348,3,0), VLOOKUP(B159,'Lista Profissionais'!$C$11:$H$348,6,0)), 0)) -> 31200 | H159: =IF(B159<>"", IF(C159="CLT", 22*$M$5 + (G159*'Lista Profissionais'!$G$9),0),0) -> 0 | I159: =(G159/$G$2)*D159 -> 31200 | J159: =I159+AH159 -> 31200 | K159: =J159+S159+AI159 -> 45243.432 | L159: =IF(D159>0,J159/D159,0) -> 177.27273 | N159: 0 | O159: =J159*$G$6 -> 0 | P159: =IF(M159>0,M159, J159*(1+$G$5)) -> 59280 | Q159: =(P159+O159) -> 59280 | R159: =IF(E159="Sim", Q159*$G$3,0) -> 1778.4 | S159: 0 | T159: =IF($D$4="Sim",(IF(E159="Não",0,(Q159+(Q159*$O$4)+R159+S159)*$D$5)+Q159), IF(E159="Não",0,Q159+(Q159*$O$4)+R159+S159 )) -> 61058.4 | U159: =IF(D159>0,T159/D159,0) -> 346.92273 | V159: =IF(C159="CLT", I159*$M$2, 0) -> 0 | W159: =IF(C159="CLT", V159*$M$3, 0) -> 0 | X159: =IF(C159="CLT", I159/12, 0) -> 0 | Y159: =IF(C159="CLT", X159/3, 0) -> 0 | Z159: =IF(C159="CLT", I159/12, 0) -> 0 | AA159: =IF(C159="CLT", I159*$S$2,0) -> 0 | AB159: =IF(C159="CLT", SUM(X159:Z159) * $M$2,0) -> 0 | AC159: =IF(C159="CLT", SUM(X159:Z159)*$S$2,0) -> 0 | AD159: =IF(C159="CLT", I159/30*3, 0) -> 0 | AE159: =IF(C159="CLT", AD159*$M$2, 0) -> 0 | AF159: =IF(C159="CLT", I159*$M$4, 0) -> 0 | AG159: =IF(B159<>"", IF(C159="CLT", $Q$2, 0),0) -> 0 | AH159: =SUM(V159:AG159)+H159 -> 0 | AI159: =IF(E159="Sim", T159*$G$4, 0) -> 14043.432 | AJ159: =T159-AI159-J159-R159 -> 14036.568 | AK159: =(IF(AJ159>0,AJ159/T159,0)) -> 0.22988758 | AL159: =(IF(AJ159>0,AJ159/(T159-AI159),0)) -> 0.2985553

Sheet Rate Formatado CLT
B1: Qtde horas | C1: 168
A2: ="RATE CARD CLT"& " - BASE " &C1& " HORAS" -> RATE CARD CLT - BASE 168 HORAS | I2: Home office | J2: 0.1
B3: Tarifa home office | D3: Tarifa híbrido/presencial
A4: Perfil | B4: $ hora | C4: $ mensal | D4: $ hora | E4: $ mensal | F4: Diferença home office
A5: =IF('Rate Card CLT'!B9<>"",'Rate Card CLT'!B9,"") -> Agilista Especialista | B5: =IF(A5<>"",TRUNC('Rate Card CLT'!U9,2),"") -> 251.97 | C5: =IF(A5<>"",$C$1*B5,"") -> 42330.96 | D5: =B5+(B5*$J$2) -> 277.167 | E5: =IF(A5<>"",$C$1*D5,"") -> 46564.056 | F5: =IF(A5<>"",(E5-C5)/C5,"") -> 0.1
A6: =IF('Rate Card CLT'!B10<>"",'Rate Card CLT'!B10,"") -> Agilista - Junior Júnior | B6: =IF(A6<>"",TRUNC('Rate Card CLT'!U10,2),"") -> 99.38 | C6: =IF(A6<>"",$C$1*B6,"") -> 16695.84 | D6: =B6+(B6*$J$2) -> 109.318 | E6: =IF(A6<>"",$C$1*D6,"") -> 18365.424 | F6: =IF(A6<>"",(E6-C6)/C6,"") -> 0.1
A7: =IF('Rate Card CLT'!B11<>"",'Rate Card CLT'!B11,"") -> Agilista Pleno | B7: =IF(A7<>"",TRUNC('Rate Card CLT'!U11,2),"") -> 152.61 | C7: =IF(A7<>"",$C$1*B7,"") -> 25638.48 | D7: =B7+(B7*$J$2) -> 167.871 | E7: =IF(A7<>"",$C$1*D7,"") -> 28202.328 | F7: =IF(A7<>"",(E7-C7)/C7,"") -> 0.1
A8: =IF('Rate Card CLT'!B12<>"",'Rate Card CLT'!B12,"") -> Agilista Sênior | B8: =IF(A8<>"",TRUNC('Rate Card CLT'!U12,2),"") -> 216.49 | C8: =IF(A8<>"",$C$1*B8,"") -> 36370.32 | D8: =B8+(B8*$J$2) -> 238.139 | E8: =IF(A8<>"",$C$1*D8,"") -> 40007.352 | F8: =IF(A8<>"",(E8-C8)/C8,"") -> 0.1
A9: =IF('Rate Card CLT'!B13<>"",'Rate Card CLT'!B13,"") -> Analista de Dados/ BI Especialista | B9: =IF(A9<>"",TRUNC('Rate Card CLT'!U13,2),"") -> 207.61 | C9: =IF(A9<>"",$C$1*B9,"") -> 34878.48 | D9: =B9+(B9*$J$2) -> 228.371 | E9: =IF(A9<>"",$C$1*D9,"") -> 38366.328 | F9: =IF(A9<>"",(E9-C9)/C9,"") -> 0.1
A10: =IF('Rate Card CLT'!B14<>"",'Rate Card CLT'!B14,"") -> Analista de Dados/ BI Júnior | B10: =IF(A10<>"",TRUNC('Rate Card CLT'!U14,2),"") -> 86.96 | C10: =IF(A10<>"",$C$1*B10,"") -> 14609.28 | D10: =B10+(B10*$J$2) -> 95.656 | E10: =IF(A10<>"",$C$1*D10,"") -> 16070.208 | F10: =IF(A10<>"",(E10-C10)/C10,"") -> 0.1
A11: =IF('Rate Card CLT'!B15<>"",'Rate Card CLT'!B15,"") -> Analista de Dados/ BI Pleno | B11: =IF(A11<>"",TRUNC('Rate Card CLT'!U15,2),"") -> 145.51 | C11: =IF(A11<>"",$C$1*B11,"") -> 24445.68 | D11: =B11+(B11*$J$2) -> 160.061 | E11: =IF(A11<>"",$C$1*D11,"") -> 26890.248 | F11: =IF(A11<>"",(E11-C11)/C11,"") -> 0.1
A12: =IF('Rate Card CLT'!B16<>"",'Rate Card CLT'!B16,"") -> Analista de Dados/ BI Sênior | B12: =IF(A12<>"",TRUNC('Rate Card CLT'!U16,2),"") -> 181 | C12: =IF(A12<>"",$C$1*B12,"") -> 30408 | D12: =B12+(B12*$J$2) -> 199.1 | E12: =IF(A12<>"",$C$1*D12,"") -> 33448.8 | F12: =IF(A12<>"",(E12-C12)/C12,"") -> 0.1
A13: =IF('Rate Card CLT'!B17<>"",'Rate Card CLT'!B17,"") -> Analista de Inteligência Artificial Especialista | B13: =IF(A13<>"",TRUNC('Rate Card CLT'!U17,2),"") -> 251.97 | C13: =IF(A13<>"",$C$1*B13,"") -> 42330.96 | D13: =B13+(B13*$J$2) -> 277.167 | E13: =IF(A13<>"",$C$1*D13,"") -> 46564.056 | F13: =IF(A13<>"",(E13-C13)/C13,"") -> 0.1
A14: =IF('Rate Card CLT'!B18<>"",'Rate Card CLT'!B18,"") -> Analista de Inteligência Artificial Júnior | B14: =IF(A14<>"",TRUNC('Rate Card CLT'!U18,2),"") -> 99.38 | C14: =IF(A14<>"",$C$1*B14,"") -> 16695.84 | D14: =B14+(B14*$J$2) -> 109.318 | E14: =IF(A14<>"",$C$1*D14,"") -> 18365.424 | F14: =IF(A14<>"",(E14-C14)/C14,"") -> 0.1
A15: =IF('Rate Card CLT'!B19<>"",'Rate Card CLT'!B19,"") -> Analista de Inteligência Artificial Pleno | B15: =IF(A15<>"",TRUNC('Rate Card CLT'!U19,2),"") -> 145.51 | C15: =IF(A15<>"",$C$1*B15,"") -> 24445.68 | D15: =B15+(B15*$J$2) -> 160.061 | E15: =IF(A15<>"",$C$1*D15,"") -> 26890.248 | F15: =IF(A15<>"",(E15-C15)/C15,"") -> 0.1
A16: =IF('Rate Card CLT'!B20<>"",'Rate Card CLT'!B20,"") -> Analista de Inteligência Artificial Sênior | B16: =IF(A16<>"",TRUNC('Rate Card CLT'!U20,2),"") -> 207.61 | C16: =IF(A16<>"",$C$1*B16,"") -> 34878.48 | D16: =B16+(B16*$J$2) -> 228.371 | E16: =IF(A16<>"",$C$1*D16,"") -> 38366.328 | F16: =IF(A16<>"",(E16-C16)/C16,"") -> 0.1
... A151: =IF('Rate Card CLT'!B155<>"",'Rate Card CLT'!B155,"") -> Analista de Qualidade Automatizador Sênior | B151: =IF(A151<>"",TRUNC('Rate Card CLT'!U155,2),"") -> 189.87 | C151: =IF(A151<>"",$C$1*B151,"") -> 31898.16 | D151: =B151+(B151*$J$2) -> 208.857 | E151: =IF(A151<>"",$C$1*D151,"") -> 35087.976 | F151: =IF(A151<>"",(E151-C151)/C151,"") -> 0.1
A152: =IF('Rate Card CLT'!B156<>"",'Rate Card CLT'!B156,"") -> Especialista LTMC (Líder Técnico) Especialista | B152: =IF(A152<>"",TRUNC('Rate Card CLT'!U156,2),"") -> 438.27 | C152: =IF(A152<>"",$C$1*B152,"") -> 73629.36 | D152: =B152+(B152*$J$2) -> 482.097 | E152: =IF(A152<>"",$C$1*D152,"") -> 80992.296
A153: =IF('Rate Card CLT'!B157<>"",'Rate Card CLT'!B157,"") -> Especialista LTMC Especialista | B153: =IF(A153<>"",TRUNC('Rate Card CLT'!U157,2),"") -> 402.78 | C153: =IF(A153<>"",$C$1*B153,"") -> 67667.04 | D153: =B153+(B153*$J$2) -> 443.058 | E153: =IF(A153<>"",$C$1*D153,"") -> 74433.744
A154: =IF('Rate Card CLT'!B158<>"",'Rate Card CLT'!B158,"") -> Especialista ETL / Oracle EBS Especialista | B154: =IF(A154<>"",TRUNC('Rate Card CLT'!U158,2),"") -> 367.3 | C154: =IF(A154<>"",$C$1*B154,"") -> 61706.4 | D154: =B154+(B154*$J$2) -> 404.03 | E154: =IF(A154<>"",$C$1*D154,"") -> 67877.04
A155: =IF('Rate Card CLT'!B159<>"",'Rate Card CLT'!B159,"") -> Especialista DQ / DQA Especialista | B155: =IF(A155<>"",TRUNC('Rate Card CLT'!U159,2),"") -> 438.27 | C155: =IF(A155<>"",$C$1*B155,"") -> 73629.36 | D155: =B155+(B155*$J$2) -> 482.097 | E155: =IF(A155<>"",$C$1*D155,"") -> 80992.296

Sheet Rate Formatado PJ
B1: Qtde horas | C1: 168
A2: ="RATE CARD PJ"& " - BASE " &C1& " HORAS" -> RATE CARD PJ - BASE 168 HORAS
B3: Tarifa home office | D3: Tarifa híbrido/presencial | J3: Home office | K3: 0.1
A4: Perfil | B4: $ hora | C4: $ mensal | D4: $ hora | E4: $ mensal | F4: Diferença home office
A5: =IF('Rate Card CLT'!B9<>"",'Rate Card PJ'!B9,"") -> Agilista Especialista | B5: =IF(A5<>"",TRUNC('Rate Card PJ'!U9,2),"") -> 195.14 | C5: =IF(A5<>"",$C$1*B5,"") -> 32783.52 | D5: =B5+(B5*$K$3) -> 214.654 | E5: =IF(A5<>"",$C$1*D5,"") -> 36061.872 | F5: =IF(A5<>"",(C5-#REF!)/C5,"") -> #REF!
A6: =IF('Rate Card CLT'!B10<>"",'Rate Card PJ'!B10,"") -> Agilista - Junior Júnior | B6: =IF(A6<>"",TRUNC('Rate Card PJ'!U10,2),"") -> 70.83 | C6: =IF(A6<>"",$C$1*B6,"") -> 11899.44 | D6: =B6+(B6*$K$3) -> 77.913 | E6: =IF(A6<>"",$C$1*D6,"") -> 13089.384 | F6: =IF(A6<>"",(C6-#REF!)/C6,"") -> #REF!
A7: =IF('Rate Card CLT'!B11<>"",'Rate Card PJ'!B11,"") -> Agilista Pleno | B7: =IF(A7<>"",TRUNC('Rate Card PJ'!U11,2),"") -> 114.19 | C7: =IF(A7<>"",$C$1*B7,"") -> 19183.92 | D7: =B7+(B7*$K$3) -> 125.609 | E7: =IF(A7<>"",$C$1*D7,"") -> 21102.312 | F7: =IF(A7<>"",(C7-#REF!)/C7,"") -> #REF!
A8: =IF('Rate Card CLT'!B12<>"",'Rate Card PJ'!B12,"") -> Agilista Sênior | B8: =IF(A8<>"",TRUNC('Rate Card PJ'!U12,2),"") -> 166.23 | C8: =IF(A8<>"",$C$1*B8,"") -> 27926.64 | D8: =B8+(B8*$K$3) -> 182.853 | E8: =IF(A8<>"",$C$1*D8,"") -> 30719.304 | F8: =IF(A8<>"",(C8-#REF!)/C8,"") -> #REF!
A9: =IF('Rate Card CLT'!B13<>"",'Rate Card PJ'!B13,"") -> Analista de Dados/ BI Especialista | B9: =IF(A9<>"",TRUNC('Rate Card PJ'!U13,2),"") -> 159 | C9: =IF(A9<>"",$C$1*B9,"") -> 26712 | D9: =B9+(B9*$K$3) -> 174.9 | E9: =IF(A9<>"",$C$1*D9,"") -> 29383.2 | F9: =IF(A9<>"",(C9-#REF!)/C9,"") -> #REF!
A10: =IF('Rate Card CLT'!B14<>"",'Rate Card PJ'!B14,"") -> Analista de Dados/ BI Júnior | B10: =IF(A10<>"",TRUNC('Rate Card PJ'!U14,2),"") -> 60.71 | C10: =IF(A10<>"",$C$1*B10,"") -> 10199.28 | D10: =B10+(B10*$K$3) -> 66.781 | E10: =IF(A10<>"",$C$1*D10,"") -> 11219.208 | F10: =IF(A10<>"",(C10-#REF!)/C10,"") -> #REF!
A11: =IF('Rate Card CLT'!B15<>"",'Rate Card PJ'!B15,"") -> Analista de Dados/ BI Pleno | B11: =IF(A11<>"",TRUNC('Rate Card PJ'!U15,2),"") -> 108.41 | C11: =IF(A11<>"",$C$1*B11,"") -> 18212.88 | D11: =B11+(B11*$K$3) -> 119.251 | E11: =IF(A11<>"",$C$1*D11,"") -> 20034.168 | F11: =IF(A11<>"",(C11-#REF!)/C11,"") -> #REF!
A12: =IF('Rate Card CLT'!B16<>"",'Rate Card PJ'!B16,"") -> Analista de Dados/ BI Sênior | B12: =IF(A12<>"",TRUNC('Rate Card PJ'!U16,2),"") -> 137.32 | C12: =IF(A12<>"",$C$1*B12,"") -> 23069.76 | D12: =B12+(B12*$K$3) -> 151.052 | E12: =IF(A12<>"",$C$1*D12,"") -> 25376.736 | F12: =IF(A12<>"",(C12-#REF!)/C12,"") -> #REF!
A13: =IF('Rate Card CLT'!B17<>"",'Rate Card PJ'!B17,"") -> Analista de Inteligência Artificial Especialista | B13: =IF(A13<>"",TRUNC('Rate Card PJ'!U17,2),"") -> 195.14 | C13: =IF(A13<>"",$C$1*B13,"") -> 32783.52 | D13: =B13+(B13*$K$3) -> 214.654 | E13: =IF(A13<>"",$C$1*D13,"") -> 36061.872 | F13: =IF(A13<>"",(C13-#REF!)/C13,"") -> #REF!
A14: =IF('Rate Card CLT'!B18<>"",'Rate Card PJ'!B18,"") -> Analista de Inteligência Artificial Júnior | B14: =IF(A14<>"",TRUNC('Rate Card PJ'!U18,2),"") -> 70.83 | C14: =IF(A14<>"",$C$1*B14,"") -> 11899.44 | D14: =B14+(B14*$K$3) -> 77.913 | E14: =IF(A14<>"",$C$1*D14,"") -> 13089.384 | F14: =IF(A14<>"",(C14-#REF!)/C14,"") -> #REF!
A15: =IF('Rate Card CLT'!B19<>"",'Rate Card PJ'!B19,"") -> Analista de Inteligência Artificial Pleno | B15: =IF(A15<>"",TRUNC('Rate Card PJ'!U19,2),"") -> 108.41 | C15: =IF(A15<>"",$C$1*B15,"") -> 18212.88 | D15: =B15+(B15*$K$3) -> 119.251 | E15: =IF(A15<>"",$C$1*D15,"") -> 20034.168 | F15: =IF(A15<>"",(C15-#REF!)/C15,"") -> #REF!
A16: =IF('Rate Card CLT'!B20<>"",'Rate Card PJ'!B20,"") -> Analista de Inteligência Artificial Sênior | B16: =IF(A16<>"",TRUNC('Rate Card PJ'!U20,2),"") -> 159 | C16: =IF(A16<>"",$C$1*B16,"") -> 26712 | D16: =B16+(B16*$K$3) -> 174.9 | E16: =IF(A16<>"",$C$1*D16,"") -> 29383.2 | F16: =IF(A16<>"",(C16-#REF!)/C16,"") -> #REF!
... A123: =IF('Rate Card CLT'!B127<>"",'Rate Card PJ'!B127,"") -> Coordenador de T.I. Sênior | B123: =IF(A123<>"",TRUNC('Rate Card PJ'!U127,2),"") -> 216.82 | C123: =IF(A123<>"",$C$1*B123,"") -> 36425.76 | D123: =B123+(B123*$K$3) -> 238.502 | E123: =IF(A123<>"",$C$1*D123,"") -> 40068.336 | F123: =IF(A123<>"",(C123-#REF!)/C123,"") -> #REF!
A124: =IF('Rate Card CLT'!B128<>"",'Rate Card PJ'!B128,"") -> Consultor SAP SuccessFactors / Ariba Especialista | B124: =IF(A124<>"",TRUNC('Rate Card PJ'!U128,2),"") -> 361.37 | C124: =IF(A124<>"",$C$1*B124,"") -> 60710.16 | D124: =B124+(B124*$K$3) -> 397.507 | E124: =IF(A124<>"",$C$1*D124,"") -> 66781.176
A125: =IF('Rate Card CLT'!B129<>"",'Rate Card PJ'!B129,"") -> Consultor SAP SuccessFactors / Ariba Júnior | B125: =IF(A125<>"",TRUNC('Rate Card PJ'!U129,2),"") -> 115.64 | C125: =IF(A125<>"",$C$1*B125,"") -> 19427.52 | D125: =B125+(B125*$K$3) -> 127.204 | E125: =IF(A125<>"",$C$1*D125,"") -> 21370.272
A126: =IF('Rate Card CLT'!B130<>"",'Rate Card PJ'!B130,"") -> Consultor SAP SuccessFactors / Ariba Pleno | B126: =IF(A126<>"",TRUNC('Rate Card PJ'!U130,2),"") -> 202.37 | C126: =IF(A126<>"",$C$1*B126,"") -> 33998.16 | D126: =B126+(B126*$K$3) -> 222.607 | E126: =IF(A126<>"",$C$1*D126,"") -> 37397.976
A127: =IF('Rate Card CLT'!B131<>"",'Rate Card PJ'!B131,"") -> Consultor SAP SuccessFactors / Ariba Sênior | B127: =IF(A127<>"",TRUNC('Rate Card PJ'!U131,2),"") -> 296.32 | C127: =IF(A127<>"",$C$1*B127,"") -> 49781.76 | D127: =B127+(B127*$K$3) -> 325.952 | E127: =IF(A127<>"",$C$1*D127,"") -> 54759.936
A128: =IF('Rate Card CLT'!B132<>"",'Rate Card PJ'!B132,"") -> Consultor SAP MM/SD Especialista | B128: =IF(A128<>"",TRUNC('Rate Card PJ'!U132,2),"") -> 361.37 | C128: =IF(A128<>"",$C$1*B128,"") -> 60710.16 | D128: =B128+(B128*$K$3) -> 397.507 | E128: =IF(A128<>"",$C$1*D128,"") -> 66781.176
A129: =IF('Rate Card CLT'!B133<>"",'Rate Card PJ'!B133,"") -> Consultor SAP MM/SD Júnior | B129: =IF(A129<>"",TRUNC('Rate Card PJ'!U133,2),"") -> 118.53 | C129: =IF(A129<>"",$C$1*B129,"") -> 19913.04 | D129: =B129+(B129*$K$3) -> 130.383 | E129: =IF(A129<>"",$C$1*D129,"") -> 21904.344
A130: =IF('Rate Card CLT'!B134<>"",'Rate Card PJ'!B134,"") -> Consultor SAP MM/SD Pleno | B130: =IF(A130<>"",TRUNC('Rate Card PJ'!U134,2),"") -> 202.37 | C130: =IF(A130<>"",$C$1*B130,"") -> 33998.16 | D130: =B130+(B130*$K$3) -> 222.607 | E130: =IF(A130<>"",$C$1*D130,"") -> 37397.976
A131: =IF('Rate Card CLT'!B135<>"",'Rate Card PJ'!B135,"") -> Consultor SAP MM/SD Sênior | B131: =IF(A131<>"",TRUNC('Rate Card PJ'!U135,2),"") -> 296.32 | C131: =IF(A131<>"",$C$1*B131,"") -> 49781.76 | D131: =B131+(B131*$K$3) -> 325.952 | E131: =IF(A131<>"",$C$1*D131,"") -> 54759.936
A132: =IF('Rate Card CLT'!B136<>"",'Rate Card PJ'!B136,"") -> Consultor SAP FI/CO Especialista | B132: =IF(A132<>"",TRUNC('Rate Card PJ'!U136,2),"") -> 419.19 | C132: =IF(A132<>"",$C$1*B132,"") -> 70423.92 | D132: =B132+(B132*$K$3) -> 461.109 | E132: =IF(A132<>"",$C$1*D132,"") -> 77466.312
A133: =IF('Rate Card CLT'!B137<>"",'Rate Card PJ'!B137,"") -> Consultor SAP FI/CO Júnior | B133: =IF(A133<>"",TRUNC('Rate Card PJ'!U137,2),"") -> 127.2 | C133: =IF(A133<>"",$C$1*B133,"") -> 21369.6 | D133: =B133+(B133*$K$3) -> 139.92 | E133: =IF(A133<>"",$C$1*D133,"") -> 23506.56
A134: =IF('Rate Card CLT'!B138<>"",'Rate Card PJ'!B138,"") -> Consultor SAP FI/CO Pleno | B134: =IF(A134<>"",TRUNC('Rate Card PJ'!U138,2),"") -> 224.05 | C134: =IF(A134<>"",$C$1*B134,"") -> 37640.4 | D134: =B134+(B134*$K$3) -> 246.455 | E134: =IF(A134<>"",$C$1*D134,"") -> 41404.44
A135: =IF('Rate Card CLT'!B139<>"",'Rate Card PJ'!B139,"") -> Consultor SAP FI/CO Sênior | B135: =IF(A135<>"",TRUNC('Rate Card PJ'!U139,2),"") -> 303.55 | C135: =IF(A135<>"",$C$1*B135,"") -> 50996.4 | D135: =B135+(B135*$K$3) -> 333.905 | E135: =IF(A135<>"",$C$1*D135,"") -> 56096.04
... A155: =IF('Rate Card CLT'!B159<>"",'Rate Card PJ'!B159,"") -> Especialista DQ / DQA Especialista | B155: =IF(A155<>"",TRUNC('Rate Card PJ'!U159,2),"") -> 346.92 | C155: =IF(A155<>"",$C$1*B155,"") -> 58282.56 | D155: =B155+(B155*$K$3) -> 381.612 | E155: =IF(A155<>"",$C$1*D155,"") -> 64110.816

Sheet CLT - ORDER
B2: RATE CARD CLT - BASE 168 HORAS
C3: Tarifa home office | E3: Tarifa híbrido/presencial
B4: Perfil | C4: $ hora | D4: $ mensal | E4: $ hora | F4: $ mensal
B5: Agilista - Junior Júnior | C5: 99.38 | D5: 16695.84 | E5: 109.318 | F5: 18365.424
B6: Agilista Especialista | C6: 251.97 | D6: 42330.96 | E6: 277.167 | F6: 46564.056
B7: Agilista Pleno | C7: 152.61 | D7: 25638.48 | E7: 167.871 | F7: 28202.328
B8: Agilista Sênior | C8: 216.49 | D8: 36370.32 | E8: 238.139 | F8: 40007.352
B9: Analista de Dados/ BI Especialista | C9: 207.61 | D9: 34878.48 | E9: 228.371 | F9: 38366.328
B10: Analista de Dados/ BI Júnior | C10: 86.96 | D10: 14609.28 | E10: 95.656 | F10: 16070.208
B11: Analista de Dados/ BI Pleno | C11: 145.51 | D11: 24445.68 | E11: 160.061 | F11: 26890.248
B12: Analista de Dados/ BI Sênior | C12: 181 | D12: 30408 | E12: 199.1 | F12: 33448.8
B13: Analista de Inteligência Artificial Especialista | C13: 251.97 | D13: 42330.96 | E13: 277.167 | F13: 46564.056
B14: Analista de Inteligência Artificial Júnior | C14: 99.38 | D14: 16695.84 | E14: 109.318 | F14: 18365.424
B15: Analista de Inteligência Artificial Pleno | C15: 145.51 | D15: 24445.68 | E15: 160.061 | F15: 26890.248
B16: Analista de Inteligência Artificial Sênior | C16: 207.61 | D16: 34878.48 | E16: 228.371 | F16: 38366.328
... B151: Tech Lead Sênior | C151: 243.1 | D151: 40840.8 | E151: 267.41 | F151: 44924.88

Sheet PJ - ORDER
B2: RATE CARD PJ - BASE 168 HORAS
C3: Tarifa home office | E3: Tarifa híbrido/presencial
B4: Perfil | C4: $ hora | D4: $ mensal | E4: $ hora | F4: $ mensal
B5: Agilista - Junior Júnior | C5: 70.83 | D5: 11899.44 | E5: 77.913 | F5: 13089.384
B6: Agilista Especialista | C6: 195.14 | D6: 32783.52 | E6: 214.654 | F6: 36061.872
B7: Agilista Pleno | C7: 114.19 | D7: 19183.92 | E7: 125.609 | F7: 21102.312
B8: Agilista Sênior | C8: 166.23 | D8: 27926.64 | E8: 182.853 | F8: 30719.304
B9: Analista de Dados/ BI Especialista | C9: 159 | D9: 26712 | E9: 174.9 | F9: 29383.2
B10: Analista de Dados/ BI Júnior | C10: 60.71 | D10: 10199.28 | E10: 66.781 | F10: 11219.208
B11: Analista de Dados/ BI Pleno | C11: 108.41 | D11: 18212.88 | E11: 119.251 | F11: 20034.168
B12: Analista de Dados/ BI Sênior | C12: 137.32 | D12: 23069.76 | E12: 151.052 | F12: 25376.736
B13: Analista de Inteligência Artificial Especialista | C13: 195.14 | D13: 32783.52 | E13: 214.654 | F13: 36061.872
B14: Analista de Inteligência Artificial Júnior | C14: 70.83 | D14: 11899.44 | E14: 77.913 | F14: 13089.384
B15: Analista de Inteligência Artificial Pleno | C15: 108.41 | D15: 18212.88 | E15: 119.251 | F15: 20034.168
B16: Analista de Inteligência Artificial Sênior | C16: 159 | D16: 26712 | E16: 174.9 | F16: 29383.2
... B151: Tech Lead Sênior | C151: 187.91 | D151: 31568.88 | E151: 206.701 | F151: 34725.768

Sheet Rate Base C&A
E1: 0.11 | F1: 176 | I1: IPCA 2024 | J1: 4.83
B2: Perfil | C2: Perfil cod | D2: Valor 2023 | E2: Rate para 2026 | F2: Total (176 hrs) | I2: IPCA 2025 | J2: 4.26
B3: Analista de Governança de TI Especialista REMOTO | C3: 3006385 Analista de Governança de TI Especialista REMOTO | D3: 88.2 | E3: =(D3*$E$1) + D3 -> 97.902 | F3: =E3*$F$1 -> 17230.752 | I3: IPCA 2026 até março | J3: 1.92
B4: Analista de Governança de TI Especialista PRESENCIAL | C4: 3006386 Analista de Governança de TI Especialista PRESENCIAL | D4: 92.61 | E4: =(D4*$E$1) + D4 -> 102.7971 | F4: =E4*$F$1 -> 18092.29
B5: Analista de Governança de TI JR REMOTO | C5: 3006387 Analista de Governança de TI JR REMOTO | D5: 37.24 | E5: =(D5*$E$1) + D5 -> 41.3364 | F5: =E5*$F$1 -> 7275.2064
B6: Analista de Governança de TI JR PRESENCIAL | C6: 3006388 Analista de Governança de TI JR PRESENCIAL | D6: 39.1 | E6: =(D6*$E$1) + D6 -> 43.401 | F6: =E6*$F$1 -> 7638.576
B7: Analista de Governança de TI PL REMOTO | C7: 3006389 Analista de Governança de TI PL REMOTO | D7: 51.94 | E7: =(D7*$E$1) + D7 -> 57.6534 | F7: =E7*$F$1 -> 10146.998
B8: Analista de Governança de TI PL PRESENCIAL | C8: 3006373 Analista de Governança de TI PL PRESENCIAL | D8: 54.54 | E8: =(D8*$E$1) + D8 -> 60.5394 | F8: =E8*$F$1 -> 10654.934
B9: Analista de Governança de TI SR REMOTO | C9: 3006391 Analista de Governança de TI SR REMOTO | D9: 70.56 | E9: =(D9*$E$1) + D9 -> 78.3216 | F9: =E9*$F$1 -> 13784.602
B10: Analista de Governança de TI SR PRESENCIAL | C10: 3006390 Analista de Governança de TI SR PRESENCIAL | D10: 74.09 | E10: =(D10*$E$1) + D10 -> 82.2399 | F10: =E10*$F$1 -> 14474.222
B11: Analista DevOps Especialista REMOTO | C11: 3006374 Analista DevOps Especialista REMOTO | D11: 133.53 | E11: =(D11*$E$1) + D11 -> 148.2183 | F11: =E11*$F$1 -> 26086.421
B12: Analista DevOps Especialista PRESENCIAL | C12: 3006379 Analista DevOps Especialista PRESENCIAL | D12: 125.26 | E12: =(D12*$E$1) + D12 -> 139.0386 | F12: =E12*$F$1 -> 24470.794
B13: Analista DevOps JR REMOTO | C13: 3006398 Analista DevOps JR REMOTO | D13: 77.42 | E13: =(D13*$E$1) + D13 -> 85.9362 | F13: =E13*$F$1 -> 15124.771
B14: Analista DevOps JR PRESENCIAL | C14: 3006393 Analista DevOps JR PRESENCIAL | D14: 83.55 | E14: =(D14*$E$1) + D14 -> 92.7405 | F14: =E14*$F$1 -> 16322.328
B15: Analista DevOps PL REMOTO | C15: 3006405 Analista DevOps PL REMOTO | D15: 113.68 | E15: =(D15*$E$1) + D15 -> 126.1848 | F15: =E15*$F$1 -> 22208.525
... B522: UX SR PRESENCIAL | C522: 3004883 UX SR PRESENCIAL | D522: 93.64 | E522: =(D522*$E$1) + D522 -> 103.9404 | F522: =E522*$F$1 -> 18293.51

Sheet Licitação - Implantação
E2: RESUMO | F2: Base horas mês | G2: 176 | H2: $ salários + encargos | I2: =SUM(I9:I68) -> #N/A | J2: FGTS | L2: 0.08 | M2: Nº colab bilable | N2: =COUNTIF(E9:E413, "Sim") -> 17 | O2: Valor convênio | P2: 750
C3: modelo | D3: PJ | F3: % Comissão vend. | G3: 0 | H3: $ faturamento | I3: =SUM(S9:S68) -> #N/A | J3: FGTS Multa | L3: 0.4 | M3: Nº colab no bilable | N3: =COUNTIF(E9:E413, "Não") -> 0 | O3: Valor comissão | P3: 0
C4: Híbrido | D4: Sim | F4: % Imposto NF | G4: 0.175 | H4: $ Custos | I4: =SUM(J9:J68)+P3 -> #N/A | J4: INSS | L4: 0.09 | M4: % Rateio no Bilable | N4: 0 | O4: Soma de horas | P4: =SUM(D9:D40) -> 2992
C5: Perc.Hib. | D5: 0 | G5: 0.8 | H5: $ lucratividade | I5: =I3-I4 -> #N/A | J5: Ticket Rest. Dia | L5: 38 | M5: Total Billable | N5: =SUMIF(E9:E68,"Sim",P9:P68) -> #N/A | O5: hora média | P5: =I3/P4 -> #N/A
F6: Taxa de risco | G6: 0 | H6: % lucro real | I6: =I5/I3 -> #N/A | J6: Tarifa média hr. | L6: =SUM(S9:S68)/SUM(D9:D68) -> #N/A | M6: Total No Bilable | N6: =SUMIF(#REF!,"Não",#REF!) -> #REF!
B7: CONFIGURAÇÃO EQUIPE | C7: CONFIG RECURSO | F7: C U S T O S C O M C O L A B O R A D O R E S | L7: T A R I F A / F A T U R A M E N T O | U7: C U S T O S C L T | AE7: IMPOSTOS | AF7: LUCRATIVIDADE
B8: Necessidade cliente | C8: Reg | D8: H.trab | E8: Billable | F8: $ Negociado/salário | G8: $ salário cheio | H8: $ Salário real | I8: $ Custo Colab | J8: $ Custo colab + Imp | K8: Custo hora | L8: $ Tarifa negociada | M8: Markup | N8: $ Risco | O8: $ Tarifa | P8: $ Tar. calculada | Q8: $ Comissão | R8: Loc. Equip. | S8: $ Tarifa bilable | T8: Valor hora | U8: FGTS | V8: FGTS multa | W8: Férias | X8: 1/3 férias | Y8: 13º salário | Z8: Aviso Remuner | AA8: Vl. Restaurante | AB8: INSS | AC8: Convênio | AD8: $ Total Encargos | AE8: Imposto Nota | AF8: $ lucro | AG8: % Lucro
B9: Gerente de Projetos - Senior | C9: CLT | D9: 176 | E9: Sim | F9: 0 | G9: =IF(F9>0,F9, IF(B9<>"", IF(C9="CLT",VLOOKUP(B9,'Lista Profissionais'!$C$11:$H$348,3,0), VLOOKUP(B9,'Lista Profissionais'!$C$11:$H$348,4,0)), 0)) -> #N/A | H9: =(G9/$G$2)*D9 -> #N/A | I9: =H9+AD9 -> #N/A | J9: =I9+R9+AE9 -> #N/A | K9: =IF(D9>0,I9/D9,0) -> #N/A | M9: 0 | N9: =I9*$G$6 -> #N/A | O9: =IF(L9>0,L9, I9*(1+$G$5)) -> #N/A | P9: =(O9+N9) -> #N/A | Q9: =IF(E9="Sim", P9*$G$3,0) -> #N/A | R9: 0 | S9: =IF($D$4="Sim",(IF(E9="Não",0,(P9+(P9*$N$4)+Q9+R9)*$D$5)+P9), IF(E9="Não",0,P9+(P9*$N$4)+Q9+R9 )) -> #N/A | T9: =IF(D9>0,S9/D9,0) -> #N/A | U9: =IF(C9="CLT", H9*$L$2, 0) -> #N/A | V9: =IF(C9="CLT", U9*$L$3, 0) -> #N/A | W9: =IF(C9="CLT", H9/12, 0) -> #N/A | X9: =IF(C9="CLT", W9/3, 0) -> #N/A | Y9: =IF(C9="CLT", H9/12, 0) -> #N/A | Z9: =IF(C9="CLT", H9/12, 0) -> #N/A | AA9: =IF(B9<>"", IF(C9="CLT", 22*$L$5,0),0) -> 836 | AB9: =IF(C9="CLT", H9*$L$4, 0) -> #N/A | AC9: =IF(B9<>"", IF(C9="CLT", $P$2, 0),0) -> 750 | AD9: =SUM(U9:AC9) -> #N/A | AE9: =IF(E9="Sim", S9*$G$4, 0) -> #N/A | AF9: =S9-AE9-I9-Q9 -> #N/A | AG9: =(IF(AF9>0,AF9/S9,0)) -> #N/A
